Workbook
Name _Toc210311535: VAS!$B$32
Name _Toc210311536: VAS!$B$33
Name _Toc210311538: VAS!$B$34
Name _Toc210311539: VAS!$B$35
Name rel_date: Top!$B$3

Sheet Top
A1: Test Case Reference List for the Bluetooth Qualification Program (specifications external to Core).
A2: This TCRL includes qualification requirements for next generation audio; transport agnostic control, audio streaming over LE isochronous channels, codec and upper layer profiles. Published as part of TCRL.pkg101.p1.**
A3: Release Date: | B3: 46007 | C3: Specification | E3: Previous Requirements | G3: Updated Requirements
A4: Key to the Tables of the Test Case Reference List
A5: Table | B5: Contents | C5: Version | D5: Adoption Date | E5: TS | F5: ICS | G5: TS | H5: ICS | I5: Notes
A6: VAP | B6: Voice Assistant Profile | C6: 1 | D6: 46006 | G6: VAP.TS.p0 | H6: VAP.ICS.p0
A7: VAS | B7: Voice Assistant Service | C7: 1 | D7: 46006 | G7: VAS.TS.p0 | H7: VAS.ICS.p0
A9: Red text is used throughout this rollup TCRL to designate all updates made since the previous TCRL Package release.
A11: * The Test System Alternatives columns of each TCRL include references to validated and commercially available test equipment that was in a validated state in time for the compilation of the rollup TCRL. If validation occurs later, in the interim between two published TCRL Packages, the newly validated Test System can be used to satisfy existing Category A requirements in the same way as a Test System referenced by the TCRL, provided that a corresponding TCW, in the “Approved for Qualification” state, exists.
A12: **The TCRL document and Package naming structure was modified to align with industry standards and enable flexibility in release timing. After the publication of TCRL 2025-2, TCRL Package numbering adopted the use of a generic, incrementing integer starting at pkg100, with the package number incremented by one with each publication. Individual rollup TCRLs within the TCRL Package are numbered with publication numbers (e.g., Mesh.TCRL.p14) and incremented by one each time that particular rollup TCRL is published. For more details, refer to the Document Naming and Marking Document (DNMD).
A14: Notes:
A16: Tab Color Legend
B17: Sheet updated in this rollup TCRL.
B18: No changes to this sheet in this TCRL compared to the previous TCRL.
B19: Updates made to the Test System Alternatives column and/or the TC Category column in an individual TCRL, but there are no changes to test requirements compared to the previous TCRL Package.
A22: References: For additional information regarding test categories, requirements, evidence, issue resolution, branding, and naming, please refer to the following:
A23: Qualification Program Reference Document (QPRD) | C23: Qualification Workspace
A24: Specifications and Test Documents List | C24: TCRL Maintenance Process Document
A25: Test Declaration Upload Best Practices | C25: Bluetooth Help and Support
A26: Bluetooth Brand Guide | C26: Errata Process Document (EPD)
A27: TCRLs and Supplementary Documents
A29: Testing Errors: To report and resolve errors encountered in testing, follow the instructions below.
A30: Test Category | B30: Steps | G30: Action
A31: A | B31: 1. If the Test System used is PTS, file a PTS Issue either by visiting support.bluetooth.com or by selecting “PTS Issues” from the Help menu in PTS. Otherwise, go directly to Step 2. | G31: File PTS Issue
B32: 2. A Test Coverage Waiver (TCW) is required. File a TSE and follow the instructions to include a TCW request. | G32: File TSE/TCW
B33: 3. Once the TCW is granted, proceed with a Member-defined test setup that meets test requirements defined in the Test Suites. Refer to Appendix A of the QPRD for evidence requirements. | G33: Review QPRD
A34: B or C | B34: 1. If the Test System used is PTS, file a PTS Issue either by visiting support.bluetooth.com or by selecting “PTS Issues” from the Help menu in PTS. Otherwise, go directly to Step 2. | G34: File PTS Issue
B35: 2. If an error is identified in the test requirements, file a TSE. If the error blocks a qualification, follow the instructions to include a TCW request. Otherwise, go to Step 3. | G35: File TSE/TCW
B36: 3. Proceed with a Member-defined test setup that meets test requirements defined in the Test Suites. Refer to Appendix A of the QPRD for evidence requirements. | G36: Review QPRD
A37: D or X | B37: 1. If the Test System used is PTS, file a PTS Issue either by visiting support.bluetooth.com or by selecting “PTS Issues” from the Help menu in PTS. Otherwise, go directly to Step 2. | G37: File PTS Issue
B38: 2. If an error is identified in the test requirements, file a TSE. For these test categories, no TCW is required. | G38: File TSE/TCW

Sheet Disclaimer
A1: Disclaimer and Copyright Notice
A2: This document, regardless of its title or content, is not a Bluetooth Specification as defined in the Bluetooth Patent/Copyright License Agreement (“PCLA”) and Bluetooth Trademark License Agreement. Use of this document by Members of Bluetooth SIG is governed by the membership and other related agreements between Bluetooth SIG Inc. (“Bluetooth SIG”) and its Members, including the PCLA and other agreements posted on Bluetooth SIG’s website located at www.bluetooth.com. THIS DOCUMENT IS PROVIDED “AS IS” AND BLUETOOTH SIG, ITS MEMBERS, AND THEIR AFFILIATES MAKE NO REPRESENTATIONS OR WARRANTIES AND DISCLAIM ALL WARRANTIES, EXPRESS OR IMPLIED, INCLUDING ANY WARRANTY OF MERCHANTABILITY, TITLE, NON-INFRINGEMENT, FITNESS FOR ANY PARTICULAR PURPOSE, THAT THE CONTENT OF THIS DOCUMENT IS FREE OF ERRORS. TO THE EXTENT NOT PROHIBITED BY LAW, BLUETOOTH SIG, ITS MEMBERS, AND THEIR AFFILIATES DISCLAIM ALL LIABILITY ARISING OUT OF OR RELATING TO USE OF THIS DOCUMENT AND ANY INFORMATION CONTAINED IN THIS DOCUMENT, INCLUDING LOST REVENUE, PROFITS, DATA OR PROGRAMS, OR BUSINESS INTERRUPTION, OR FOR SPECIAL, INDIRECT, CONSEQUENTIAL, INCIDENTAL OR PUNITIVE DAMAGES, HOWEVER CAUSED AND REGARDLESS OF THE THEORY OF LIABILITY, AND EVEN IF BLUETOOTH SIG, ITS MEMBERS, OR THEIR AFFILIATES HAVE BEEN ADVISED OF THE POSSIBILITY OF SUCH DAMAGES. This document is proprietary to Bluetooth SIG. This document may contain or cover subject matter that is intellectual property of Bluetooth SIG and its Members. The furnishing of this document does not grant any license to any intellectual property of Bluetooth SIG or its Members. This document is subject to change without notice.
A3: Copyright © 2025 by Bluetooth SIG, Inc. The Bluetooth word mark and logos are owned by Bluetooth SIG, Inc. Other third-party brands and names are the property of their respective owners.
A684: 2) Category B starting on 2020-Jan-15, Category A starting 2020-Apr-15

Sheet VAP
A1: Test Case Reference List
A2: =Top!B6 -> Voice Assistant Profile | D2: Previous TS | H2: TS | I2: =Top!G6 -> VAP.TS.p0 | J2: Available Date: | K2: =rel_date -> 46007
A3: Release Date: | B3: =rel_date -> 46007 | D3: Previous ICS | H3: ICS | I3: =Top!H6 -> VAP.ICS.p0 | J3: Available Date: | K3: =rel_date -> 46007
A4: Back to Top Sheet | D4: Previously published Test Requirements | H4: Updated Test Requirements through this Release
A5: TCID*** | B5: Description | C5: TCRL Package Version Last Updated | D5: TC Category | E5: Active Date | F5: Test System Alternatives | G5: Notes | H5: TC Category | I5: Active Date | J5: Test System Alternatives | K5: Notes*
A6: TCMT | B6: Test Case Mapping Table | I6: =$B$3 -> 46007
A7: ICS | B7: Implementation Conformance Statement | I7: =$B$3 -> 46007
A8: VAP/VAG/VAGP/BV-01-C | B8: VAG Initiated VA Session, GVAS | H8: B | I8: =$B$3 -> 46007 | J8: Member Defined
A9: VAP/VAG/VAGP/BV-02-C | B9: VAG Initiated VA Session with Voice Assistant Session Flags, GVAS | H9: B | I9: =$B$3 -> 46007 | J9: Member Defined
A10: VAP/VAG/VAGP/BV-03-C | B10: VAG Initiated VA Session, VAS | H10: B | I10: =$B$3 -> 46007 | J10: Member Defined
A11: VAP/VAG/VAGP/BV-04-C | B11: VAG Initiated VA Session with Voice Assistant Session Flags, VAS | H11: B | I11: =$B$3 -> 46007 | J11: Member Defined
A12: VAP/VAT/CGGIT/CHA/BV-01-C | B12: Characteristic GGIT - Voice Assistant Name | H12: B | I12: =$B$3 -> 46007 | J12: Member Defined
A13: VAP/VAT/CGGIT/CHA/BV-02-C | B13: Characteristic GGIT - Voice Assistant UUID | H13: B | I13: =$B$3 -> 46007 | J13: Member Defined
A14: VAP/VAT/CGGIT/CHA/BV-03-C | B14: Characteristic GGIT - VAS Control Point | H14: B | I14: =$B$3 -> 46007 | J14: Member Defined
A15: VAP/VAT/CGGIT/CHA/BV-04-C | B15: Characteristic GGIT - Installed Location | H15: B | I15: =$B$3 -> 46007 | J15: Member Defined
A16: VAP/VAT/CGGIT/CHA/BV-05-C | B16: Characteristic GGIT - Content Control ID (CCID) | H16: B | I16: =$B$3 -> 46007 | J16: Member Defined
A17: VAP/VAT/CGGIT/CHA/BV-06-C | B17: Characteristic GGIT - Voice Assistant Session State | H17: B | I17: =$B$3 -> 46007 | J17: Member Defined
A18: VAP/VAT/CGGIT/CHA/BV-07-C | B18: Characteristic GGIT - Voice Assistant Session Flag | H18: B | I18: =$B$3 -> 46007 | J18: Member Defined
A19: VAP/VAT/CGGIT/CHA/BV-08-C | B19: Characteristic GGIT - Voice Assistant Supported Languages | H19: B | I19: =$B$3 -> 46007 | J19: Member Defined
... A32: VAP/VAT/VATP/BV-10-C | B32: VA Initialization Procedure: Session Unavailable, VAS | H32: B | I32: =$B$3 -> 46007 | J32: Member Defined
A34: * Any technical changes in this release are indicated in the Notes column.
A35: *** Previous TCIDs of active test cases, if any, are listed in the TCID History tab at the end of this workbook.

Sheet VAS
A1: Test Case Reference List
A2: =Top!B7 -> Voice Assistant Service | D2: Previous TS | H2: TS | I2: =Top!G6 -> VAP.TS.p0 | J2: Available Date: | K2: =rel_date -> 46007
A3: Release Date: | B3: =rel_date -> 46007 | D3: Previous ICS | H3: ICS | I3: =Top!H6 -> VAP.ICS.p0 | J3: Available Date: | K3: =rel_date -> 46007
A4: Back to Top Sheet | D4: Previously published Test Requirements | H4: Updated Test Requirements through this Release
A5: TCID*** | B5: Description | C5: TCRL Package Version Last Updated | D5: TC Category | E5: Active Date | F5: Test System Alternatives | G5: Notes | H5: TC Category | I5: Active Date | J5: Test System Alternatives | K5: Notes*
A6: TCMT | B6: Test Case Mapping Table | I6: =$B$3 -> 46007
A7: ICS | B7: Implementation Conformance Statement | I7: =$B$3 -> 46007
A8: GVAS/SR/SGGIT/CHA/BV-01-C | B8: Characteristic GGIT - Voice Assistant Name | H8: B | I8: =$B$3 -> 46007 | J8: Member Defined
A9: GVAS/SR/SGGIT/CHA/BV-02-C | B9: Characteristic GGIT - Voice Assistant UUID | H9: B | I9: =$B$3 -> 46007 | J9: Member Defined
A10: GVAS/SR/SGGIT/CHA/BV-03-C | B10: Characteristic GGIT - VAS Control Point | H10: B | I10: =$B$3 -> 46007 | J10: Member Defined
A11: GVAS/SR/SGGIT/CHA/BV-04-C | B11: Characteristic GGIT - Installed Location | H11: B | I11: =$B$3 -> 46007 | J11: Member Defined
A12: GVAS/SR/SGGIT/CHA/BV-05-C | B12: Characteristic GGIT - Installed Location, Notify | H12: B | I12: =$B$3 -> 46007 | J12: Member Defined
A13: GVAS/SR/SGGIT/CHA/BV-06-C | B13: Characteristic GGIT - Content Control ID (CCID) | H13: B | I13: =$B$3 -> 46007 | J13: Member Defined
A14: GVAS/SR/SGGIT/CHA/BV-07-C | B14: Characteristic GGIT - Voice Assistant Session State | H14: B | I14: =$B$3 -> 46007 | J14: Member Defined
A15: GVAS/SR/SGGIT/CHA/BV-08-C | B15: Characteristic GGIT - Voice Assistant Session Flag | H15: B | I15: =$B$3 -> 46007 | J15: Member Defined
A16: GVAS/SR/SGGIT/CHA/BV-09-C | B16: Characteristic GGIT - Voice Assistant Supported Languages | H16: B | I16: =$B$3 -> 46007 | J16: Member Defined
A17: GVAS/SR/SGGIT/CHA/BV-10-C | B17: Characteristic GGIT - Voice Assistant Supported Features | H17: B | I17: =$B$3 -> 46007 | J17: Member Defined
A18: GVAS/SR/SGGIT/SER/BV-01-C | B18: Service GGIT - Generic Voice Assistant | H18: B | I18: =$B$3 -> 46007 | J18: Member Defined
A19: GVAS/SR/SPE/BI-01-C | B19: Opcode Not Supported Error and CCCD Not Configured | H19: B | I19: =$B$3 -> 46007 | J19: Member Defined
... A62: VAS/SR/VCO/BV-11-C | B62: Characteristic Notification, Voice Assistant Session Flag | H62: B | I62: =$B$3 -> 46007 | J62: Member Defined
A64: * Any technical changes in this release are indicated in the Notes column.
A65: *** Previous TCIDs of active test cases, if any, are listed in the TCID History tab at the end of this workbook.
