Workbook
Name _Toc125985155: 'Release Notes'!$E$122
Name rel_date: [1]Top!$B$2
Name rel_date: Top!$B$2

Sheet Top
A1: Test Case Reference List for the Bluetooth Qualification Program (Bluetooth Core 4.2–6.2 Implementations).
A2: Release Date | B2: 45965 | C2: Specification | E2: Previous Requirements | G2: Updated Requirements
A3: Key to the Tables of the TCRL
A4: Table | C4: Contents | D4: Volume, Part, Version(s) | E4: TS | F4: ICS | G4: TS | H4: ICS | I4: Notes
A5: RF | B5: BR/EDR Core Controller | C5: BR/EDR Radio Physical Layer Conformance | D5: Vol 2 Part A, 4.2–6.2 | E5: RF.TS.p35 | F5: RF.ICS.p24 | G5: RF.TS.p36 | H5: RF.ICS.p24 | I5: 4) TSE 25827 5)
A6: BB | C6: Baseband Conformance | D6: Vol 2 Part B, 4.2–6.2 | E6: BB.TS.p38 | F6: BB.ICS.p27 | G6: BB.TS.p39 | H6: BB.ICS.p28 | I6: 5)
A7: LMP | C7: Link Manager Protocol Conformance | D7: Vol 2 Part C, 4.2–6.2 | E7: LMP.TS.p48 | F7: LMP.ICS.p40 | G7: LMP.TS.p49 | H7: LMP.ICS.p41 | I7: 5)
A8: SEC | C8: BR/EDR Security Conformance | D8: Vol 2 Part H, 4.2–6.2 | E8: LMP.TS.p48 | F8: SEC.ICS.p0 | G8: LMP.TS.p49 | H8: SEC.ICS.p0
A9: 80211PAL | B9: AMP Core Controller | C9: 802.11 PAL Conformance | D9: Vol 5 Part A, 4.2–5.2 | E9: 80211PAL.TS.p13 | F9: 80211PAL.ICS.p9 | G9: 80211PAL.TS.p13 | H9: 80211PAL.ICS.p9
A10: RFPHY | B10: LE Controller | C10: LE Radio Physical Layer Conformance | D10: Vol 6 Part A, 4.2–6.2 | E10: RFPHY.TS.p23 | F10: RFPHY.ICS.p12 | G10: RFPHY.TS.p24 | H10: RFPHY.ICS.p13 | I10: 3) TSEs 27815, 27822, 28075 4) TSE 25828, 27158 5)
A11: LL | C11: Link Layer Conformance | D11: Vol 6 Part B, 4.2–6.2 | E11: LL.TS.p26 | F11: LL.ICS.p24 | G11: LL.TS.p27 | H11: LL.ICS.p25 | I11: 3) TSE 27724 4) TSE 27692 5)
A12: LE SEC | C12: LE LL Security Conformance | D12: Vol 6 Part E, 4.2–6.2 | E12: LL.TS.p26 | F12: LESEC.ICS.p1 | G12: LL.TS.p27 | H12: LESEC.ICS.p1 | I12: 3) TSE 27724 4) TSE 27692 5)
A13: IAL | C13: Isochronous Adaptation Layer Conformance | D13: Vol 6 Part G, 5.2–6.2 | E13: IAL.TS.p9 | F13: IAL.ICS.p3 | G13: IAL.TS.p10 | H13: IAL.ICS.p3 | I13: 3) TSE 27725
A14: CS | C14: Channel Sounding Conformance | D14: Vol 6 Part H, 6.0–6.2 | E14: CS.TS.p2 | F14: CS.ICS.p2 | G14: CS.TS.p3 | H14: CS.ICS.p3 | I14: 4) TSE 27907 (CSAA)
A15: HCI | B15: Host Controller Interface | C15: Host Controller Interface Conformance (Lower HCI role) | D15: Vol 2 Part E, 4.2–6.2 | E15: HCI.TS.p37 | F15: HCI.ICS.p32 | G15: HCI.TS.p38 | H15: HCI.ICS.p33 | I15: 4) TSE 27140 5)
A16: UHCI | C16: Host Controller Interface Conformance (Upper HCI role) | D16: Vol 2 Part E, 4.2–6.2 | E16: HCI.TS.p37 | F16: UHCI.ICS.p2 | G16: HCI.TS.p38 | H16: UHCI.ICS.p3 | I16: 4) TSE 27140 5)
A17: L2CAP | B17: Core Host | C17: Logical Link Control and Adaptation Protocol Conformance | D17: Vol 3 Part A, 4.2–6.2 | E17: L2CAP.TS.p40 | F17: L2CAP.ICS.p28 | G17: L2CAP.TS.p41 | H17: L2CAP.ICS.p29 | I17: 4) TSE 27460 5)
A18: SDP | C18: Service Discovery Protocol Conformance | D18: Vol 3 Part B, 4.2–6.2 | E18: SDP.TS.p24 | F18: SDP.ICS.p24 | G18: SDP.TS.p25 | H18: SDP.ICS.p25 | I18: 3) TSE 28089 4) TSEs 27439, 27748 5)
A19: GAP | C19: Generic Access Profile Conformance | D19: Vol 3 Part C, 4.2–6.2 | E19: GAP.TS.p48 | F19: GAP.ICS.p44 | G19: GAP.TS.p49 | H19: GAP.ICS.p45 | I19: 4) TSE 27509 5)
A20: A2MP | C20: AMP Manager Conformance | D20: Vol 3 Part E, 4.2–5.2 | E20: A2MP.TS.p8 | F20: A2MP.ICS.p8 | G20: A2MP.TS.p8 | H20: A2MP.ICS.p8
A21: ATT | C21: Attribute Protocol Conformance | D21: Vol 3 Part F, 4.2–6.2 | E21: GATT.TS.p28 | F21: ATT.ICS.p14 | G21: GATT.TS.p29 | H21: ATT.ICS.p15 | I21: 4) TSE 25413 5)
A22: GATT | C22: Generic Attribute Profile Conformance | D22: Vol 3 Part G, 4.2–6.2 | E22: GATT.TS.p28 | F22: GATT.ICS.p21 | G22: GATT.TS.p29 | H22: GATT.ICS.p22 | I22: 4) TSE 25413 5)
A23: SM | C23: Security Manager Conformance | D23: Vol 3 Part H, 4.2–6.2 | E23: SM.TS.p28 | F23: SM.ICS.p12 | G23: SM.TS.p29 | H23: SM.ICS.p13 | I23: 4) TSE 27423 5)
A24: 80211MP | B24: External to Core | C24: IEEE 802.11 PHY and MAC Layers | D24: IEEE 802.11-2007 (1) | E24: 80211MP.TS.p7 | F24: 80211MP.ICS.p7 | G24: 80211MP.TS.p7 | H24: 80211MP.ICS.p7
A25: CORE ICS | B25: CORE ICS | C25: Core Configurations (CORE) | D25: Vol 0 Part D, 6.0–6.2* | E25: N/A | F25: CORE.ICS.p3 | G25: N/A | H25: CORE.ICS.p4 | I25: 2) TSE 27886 (LETM) 2) TSE 27934 (SCI) 2) TSE 27576
A27: Red text is used throughout this rollup TCRL to designate all updates made since the previous TCRL Package release.
A29: * Please note that this also applies to v4.2–v5.4 amended versions.
A30: Note: The Test System Alternatives columns of each TCRL include references to validated and commercially available test equipment that was in a validated state in time for the compilation of the rollup TCRL. If validation occurs later, in the interim between two published TCRL Packages, the newly validated Test System can be used to satisfy existing Category A requirements in the same way as a Test System referenced by the TCRL, provided that a corresponding TCW, in the “Approved for Qualification” state, exists.
A32: Adoption Dates
A33: Specification Version | B33: Adoption Date
A34: 6.2 | B34: 45964
A35: 6.1 | B35: 45782
A36: 6 | B36: 45531
A37: 5.4 | B37: 44957
A38: 5.3 | B38: 44383
A39: 5.2 | B39: 43830
A40: 5.1 | B40: 43480
A41: ESR11 | B41: 43088
A42: CSA6 | B42: 42928
A43: ESR10 | B43: 42710
A44: 5.0 | B44: 42710
A45: CSA5 | B45: 42353
A46: ESR09 | B46: 42192
A47: 4.2 | B47: 41975
A48: ESR08 | B48: 41975
... A61: ESR03 | B61: 39484
A62: IEEE 802.11 PHY and MAC | B62: IEEE Adoption 2007
A63: 2.1/2.1+EDR | B63: 39289
A64: ESR02 | B64: 38524
A66: Notes:
B67: 0) TCRL Version Last Updated column only captures changes from TCRL 2017-1 and onward in this TCRL.
B68: 1) "IEEE 802.11-2007" refers to IEEE 802.11-2007 Standard and Amendment 1 (Radio Resource Measurement)
B69: 2) CORE ICS TSEs and changes are reflected only on the Top Sheet, there is no CORE ICS tab.
B70: 3) The TSE impact affects the rollup TCRL only.
B71: 4) Updates to IXIT.
B72: 5) Changes made due to an editorial TSE (impact rating 1) or a moderate content change to a Test Suite (impact rating 2). See Release Notes tab for additional details.
B73: 6) Changes made that affect an area of the TS not included in test cases or TCMT.
A76: Tab Color Legend
B77: Sheet updated in this rollup TCRL.
B78: No changes to this sheet in this TCRL compared to the previous TCRL.
B79: Updates made to the Test System Alternatives column in an individual TCRL, but there are no changes to test requirements compared to the previous TCRL Package.
A82: References: For additional information regarding test categories, requirements, evidence, issue resolution, branding, and naming, please refer to the following:
A83: Qualification Program Reference Document (QPRD) | C83: Qualification Workspace
A84: Specifications and Test Documents List
A85: Test Declaration Upload Best Practices | C85: TCRL Maintenance Process Document
A86: Bluetooth Brand Guide | C86: Bluetooth Help and Support
A87: TCRLs and Supplementary Documents | C87: Errata Process Document (EPD)
A89: Testing Errors: To report and resolve errors encountered in testing, follow the instructions below.
A90: Test Category | B90: Steps | E90: Action
A91: A | B91: 1. If the Test System used is PTS, file a PTS Issue either by visiting support.bluetooth.com or by selecting “PTS Issues” from the Help menu in PTS. Otherwise, go directly to step 2. | E91: File PTS Issue
B92: 2. A Test Coverage Waiver (TCW) is required. File a TSE and follow the instructions to include a TCW request. | E92: File TSE/TCW
B93: 3. Once the TCW is granted, proceed with a member-defined test setup that meets test requirements defined in the Test Suites. Refer to Appendix A of the QPRD for evidence requirements. | E93: Review QPRD
A94: B or C | B94: 1. If the Test System used is PTS, file a PTS Issue either by visiting support.bluetooth.com or by selecting “PTS Issues” from the Help menu in PTS. Otherwise, go directly to step 2. | E94: File PTS Issue
B95: 2. If an error is identified in the test requirements, file a TSE. If the error blocks a qualification, follow the instructions to include a TCW request. Otherwise, go to step 3. | E95: File TSE/TCW
B96: 3. Proceed with a Member-defined test setup that meets test requirements defined in the Test Suites. Refer to Appendix A of the QPRD for evidence requirements. | E96: Review QPRD
A97: D or X | B97: 1. If the Test System used is PTS, file a PTS Issue either by visiting support.bluetooth.com or by selecting “PTS Issues” from the Help menu in PTS. Otherwise, go directly to step 2. | E97: File PTS Issue
B98: 2. If an error is identified in the test requirements, file a TSE. For these test categories no TCW is required. | E98: File TSE/TCW

Sheet Deprecations
A1: Deprecated and Withdrawn Specification History
A2: Deprecation and Withdrawal announcements may occur at any time. This sheet is updated with the information from the Bluetooth Board of Directors' resolutions made at the time of the finalization of this TCRL Package and is provided for information only. Updates are made to this sheet only during a TCRL Package maintenance release cycle.
A3: References: For additional information regarding test categories, requirements, evidence, issue resolution, branding, and naming please refer to the TOP sheet of this rollup TCRL
A4: For additional information regarding specification status and Deprecation and Withdrawal KBAs, the following Bluetooth SIG sites may be helpful:
A5: Specifications List
A6: Core Deprecation and Withdrawal Policy
A7: KBA - How Do Specification Deprecation or Withdrawal Impact Members Existing Qualified Products?
A8: KBA - Deprecation and Withdrawal (D&W)
A10: Last updated date: | B10: 45965 | D10: Deprecated Specification | E10: Withdrawn Specification | F10: Requirements Last Maintained | H10: TCRL Package release requirements where the version moved to Deprecated
A11: Key to the Tables of the Test Case Reference List
A12: Table | B12: Contents | C12: Version | D12: Deprecation Date* | E12: Withdrawal Date** | F12: TS | G12: ICS | I12: Notes
A13: 2.0+ EDR | B13: Core Specification 2.0 + EDR | C13: 2.0 | D13: 41956 | E13: 43493 | F13: 4) | G13: 4) | H13: Core TCRL 2015-1
A14: 2.1+ EDR | B14: Core Specification 2.1 + EDR | C14: 2.1 | D14: 43493 | E14: 44013 | F14: 4) | G14: 4) | H14: Core TCRL 2018-2
A15: 3.0+ HS | B15: Core Specification 3.0 + HS | C15: 3.0 | D15: 43493 | E15: 44013 | F15: 4) | G15: 4) | H15: Core TCRL 2018-2
A16: 4.0 | B16: Core Specification 4.0 | C16: 4.0 | D16: 43493 | E16: 44593 | F16: 4) | G16: 4) | H16: Core TCRL 2018-2
A17: 4.1 | B17: Core Specification 4.1 | C17: 4.1 | D17: 43493 | E17: 44958 | F17: 4) | G17: 4) | H17: Core TCRL 2018-2
A18: 4.2 | B18: Core Specification 4.2 | C18: 4.2 | D18: 46054 | E18: 47880 | F18: TBD | G18: TBD | H18: TBD
A19: 5 | B19: Core Specification 5.0 | C19: 5.0 | D19: 46419 | E19: 48245 | F19: TBD | G19: TBD | H19: TBD
A20: 5.1 | B20: Core Specification 5.1*** | C20: 5.1 | D20: 47150 | E20: 48976 | F20: TBD | G20: TBD | H20: TBD
A21: 5.2 | B21: Core Specification 5.2*** | C21: 5.2 | D21: 47515 | E21: 49341 | F21: TBD | G21: TBD | H21: TBD
A22: 5.3 | B22: Core Specification 5.3*** | C22: 5.3 | D22: 48030 | E22: 49857 | F22: TBD | G22: TBD | H22: TBD
A23: 5.4 | B23: Core Specification 5.4*** | C23: 5.4 | D23: 48611 | E23: 50437 | F23: TBD | G23: TBD | H23: TBD
A24: 6 | B24: Core Specification 6.0*** | C24: 6.0 | D24: 49341 | E24: 51167 | F24: TBD | G24: TBD | H24: TBD
A25: 3DSP 1.0 | B25: 3D Synchronization Profile 1.0 | C25: 1.0 | D25: 41751 | E25: 44593 | F25: 3DSP.TS.1.0.1 | G25: 3DSP.ICS.1.0.2 | H25: Traditional TCRL 2015-1
A26: 3DSP 1.0.1 | B26: 3D Synchronization Profile 1.0.1 | C26: 1.0.1 | D26: 44228 | E26: 44593 | F26: 3DSP.TS.1.0.3.1 | G26: 3DSP.ICS.1.0.3.1 | H26: Traditional TCRL 2020-1
A27: 3DSP 1.0.2 | B27: 3D Synchronization Profile 1.0.2 | C27: 1.0.2 | D27: 44228 | E27: 44593 | F27: 3DSP.TS.1.0.3.1 | G27: 3DSP.ICS.1.0.3.1 | H27: Traditional TCRL 2020-1
A28: A2DP 1.0 | B28: Advanced Audio Dist. Profile 1.0​ | C28: 1.0 | D28: 44593 | E28: 44958 | F28: A2DP.TS.p16 | G28: A2DP.ICS.p14 | H28: Traditional TCRL 2021-2
A29: A2DP 1.2 | B29: Advanced Audio Dist. Profile 1.2 | C29: 1.2 | D29: 46784 | E29: 47515 | F29: TBD | G29: TBD | H29: TBD
A30: A2DP 1.3 | B30: Advanced Audio Dist. Profile 1.3 | C30: 1.3 | D30: 44228 | E30: 45323 | F30: A2DP.TS.1.3.2.1 | G30: A2DP.ICS.1.3.2.2 | H30: Traditional TCRL 2020-1
A31: A2DP 1.3.1 | B31: Advanced Audio Dist. Profile 1.3.1 | C31: 1.3.1 | D31: 44228 | E31: 45323 | F31: A2DP.TS.1.3.2.1 | G31: A2DP.ICS.1.3.2.2 | H31: Traditional TCRL 2020-1
A32: AVCTP 1.0 | B32: Audio/Video Control Transport Protocol 1.0 | C32: 1.0 | D32: 44593 | E32: 44958 | F32: AVCTP.TS.1.4.1 | G32: AVCTP.ICS.1.4.2 | H32: Traditional TCRL 2021-2
A33: AVCTP 1.2 | B33: Audio/Video Control Transport Protocol 1.2 | C33: 1.2 | D33: 44593 | E33: 44958 | F33: AVCTP.TS.1.4.1 | G33: AVCTP.ICS.1.4.2 | H33: Traditional TCRL 2021-2
A34: AVCTP 1.3 | B34: Audio/Video Control Transport Protocol 1.3 | C34: 1.3 | D34: 41479 | E34: 44958 | F34: AVCTP.TS.1.4.0 | G34: AVCTP.ICS.1.4.0 | H34: Traditional TCRL 2015-1
A35: AVDTP 1.0 | B35: A/V Distribution Transport Protocol 1.0​ | C35: 1.0 | D35: 44593 | E35: 44958 | F35: AVDTP.TS.p19 | G35: AVDTP.ICS.1.3.4 | H35: Traditional TCRL 2021-2
A36: AVDTP 1.2 | B36: A/V Distribution Transport Protocol 1.2 | C36: 1.2 | D36: 44958 | E36: 45323 | F36: AVDTP.TS.p19 | G36: AVDTP.ICS.1.3.4 | H36: Traditional TCRL 2022-1
A37: AVRCP 1.0 | B37: Audio/Video Remote Control Profile 1.0 | C37: 1.0 | D37: 44593 | E37: 44958 | F37: AVRCP.TS.1.6.2.2 | G37: AVRCP.ICS.1.6.2.0 | H37: Traditional TCRL 2021-2
A38: AVRCP 1.3 | B38: Audio/Video Remote Control Profile 1.3 | C38: 1.3 | D38: 44958 | E38: 46419 | F38: AVRCP.TS.1.6.2.2 | G38: AVRCP.ICS.1.6.2.0 | H38: Traditional TCRL 2022-1
A39: AVRCP 1.4 | B39: Audio/Video Remote Control Profile 1.4 | C39: 1.4 | D39: 41479 | E39: 44958 | F39: AVRCP.TS.1.6.0 | G39: AVRCP.ICS.1.6.0 | H39: Traditional TCRL 2015-1
A40: AVRCP 1.6 | B40: Audio/Video Remote Control Profile 1.6 | C40: 1.6 | D40: 44228 | E40: 45323 | F40: AVRCP.TS.1.6.2.2 | G40: AVRCP.ICS.1.6.2.0 | H40: Traditional TCRL 2020-1
A41: AVRCP 1.6.1 | B41: Audio/Video Remote Control Profile 1.6.1 | C41: 1.6.1 | D41: 44228 | E41: 45323 | F41: AVRCP.TS.1.6.2.2 | G41: AVRCP.ICS.1.6.2.0 | H41: Traditional TCRL 2020-1
A42: BAP 1.0 | B42: Basic Audio Profile 1.0 | C42: 1.0 | D42: 45689 | E42: 46419 | F42: BAP.TS.p7 | G42: BAP.ICS.p7 | H42: GATTBasedAudio TCRL 2024-1
A43: BIP 1.0 | B43: Basic Imaging Profile 1.0 | C43: 1.0 | D43: 44228 | E43: 44958 | F43: BIP.TS.p14 | G43: BIP.ICS.1.2.1.0 | H43: Traditional TCRL 2020-1
A44: BIP 1.0.1 | B44: Basic Imaging Profile 1.0.1 | C44: 1.0.1 | D44: 44958 | E44: 45689 | F44: BIP.TS.p16 | G44: BIP.ICS.p9 | H44: Traditional TCRL 2022-1
A45: BIP 1.1 | B45: Basic Imaging Profile 1.1 | C45: 1.1 | D45: 41479 | E45: 44958 | F45: BIP.TS.1.2.2 | G45: BIP.ICS.1.2.2 | H45: Traditional TCRL 2015-1
A46: BIP 1.2 | B46: Basic Imaging Profile 1.2 | C46: 1.2 | D46: 44228 | E46: 44958 | F46: BIP.TS.p14 | G46: BIP.ICS.1.2.1.0 | H46: Traditional TCRL 2020-1
A47: BLP 1.0 | B47: Blood Pressure Profile 1.0 | C47: 1.0 | D47: 44958 | E47: 45323 | F47: BLP.TS.p10 | G47: BLP.ICS.p7 | H47: GATTBased TCRL 2022-1
A48: BLP 1.0.1 | B48: Blood Pressure Profile 1.0.1 | C48: 1.0.1 | D48: 46784 | E48: 47515 | F48: TBD | G48: TBD | H48: TBD
A49: BLP 1.1 | B49: Blood Pressure Profile 1.1 | C49: 1.1 | D49: 44958 | E49: 45689 | F49: BLP.TS.p10 | G49: BLP.ICS.p7 | H49: GATTBased TCRL 2022-1
A50: BLS 1.0 | B50: Blood Pressure Service 1.0 | C50: 1.0 | D50: 44958 | E50: 45323 | F50: BLS.TS.p7 | G50: BLS.ICS.p7 | H50: GATTBased TCRL 2022-1
A51: BLS 1.1 | B51: Blood Pressure Service 1.1 | C51: 1.1 | D51: 44958 | E51: 45689 | F51: BLS.TS.p7 | G51: BLS.ICS.p7 | H51: GATTBased TCRL 2022-1
A52: BMS 1.0 | B52: Bond Management Service 1.0 | C52: 1.0 | D52: 44958 | E52: 45689 | F52: BMS.TS.p5 | G52: BMS.ICS.p2 | H52: GATTBased TCRL 2022-1
A53: BPP 1.0 | B53: Basic Printing Profile 1.0 | C53: 1.0 | D53: 44958 | E53: 45689 | F53: BPP.TS.1.2.6 | G53: BPP.ICS.1.2.4 | H53: Traditional TCRL 2022-1
A54: CGMP 1.0 | B54: Continuous Glucose Monitoring Profile 1.0 | C54: 1.0 | D54: 44228 | E54: 44593 | F54: CGMP.TS.1.0.1.2 | G54: CGMP.ICS.1.0.1.1 | H54: GATTBased TCRL 2020-1
A55: CGMP 1.0.1 | B55: Continuous Glucose Monitoring Profile 1.0.1 | C55: 1.0.1 | D55: 44958 | E55: 45689 | F55: CGMP.TS.p4 | G55: CGMP.ICS.p4 | H55: GATTBased TCRL 2022-1
A56: CGMS 1.0 | B56: Continuous Glucose Monitoring Service 1.0 | C56: 1.0 | D56: 44228 | E56: 44593 | F56: CGMS.TS.p6 | G56: CGMS.ICS.1.0.1.2 | H56: GATTBased TCRL 2020-1
A57: CGMS 1.0.1 | B57: Continuous Glucose Monitoring Service 1.0.1 | C57: 1.0.1 | D57: 44958 | E57: 45689 | F57: CGMS.TS.p7 | G57: CGMS.ICS.p5 | H57: GATTBased TCRL 2022-1
... A63: CTS 1.0 | B63: Current Time Service 1.0​ | C63: 1.0 | D63: 44593 | E63: 44958 | F63: CTS.TS.1.1.2 | G63: CTS.ICS.1.1.1 | H63: GATTBased TCRL 2021-2
A64: DID 1.2 | B64: Device ID 1.2 | C64: 1.2 | D64: 46784 | E64: 47515 | F64: TBD | G64: TBD | H64: TBD
A65: DIS 1.0 | B65: Device Information Service 1.0​ | C65: 1.0 | D65: 40876 | E65: 44958 | F65: DIS.TS.1.0.0 | G65: DIS.ICS.1.0.0 | H65: GATTBased TCRL 2012-1
A66: FTP 1.1 | B66: File Transfer Profile 1.1 | C66: 1.1 | D66: 44593 | E66: 44958 | F66: FTP.TS.1.3.1.2 | G66: FTP.ICS.p8 | H66: Traditional TCRL 2021-2
A67: FTP 1.2 | B67: File Transfer Profile 1.2 | C67: 1.2 | D67: 41479 | E67: 44593 | F67: FTP.TS.1.3.2 | G67: FTP.ICS.1.3.0 | H67: Traditional TCRL 2015-1
A68: FTP 1.3 | B68: File Transfer Profile 1.3 | C68: 1.3 | D68: 44228 | E68: 44593 | F68: FTP.TS.1.3.1.2 | G68: FTP.ICS.1.3.1.1 | H68: Traditional TCRL 2020-1
A69: GAVDP 1.0 | B69: Generic A/V Dist. Profile 1.0​ | C69: 1.0 | D69: 44593 | E69: 44958 | F69: GAVDP.TS.1.3.1 | G69: GAVDP.ICS.1.3.2 | H69: Traditional TCRL 2021-2
A70: GAVDP 1.2 | B70: Generic A/V Dist. Profile 1.2 | C70: 1.2 | D70: 44593 | E70: 46419 | F70: GAVDP.TS.1.3.1 | G70: GAVDP.ICS.1.3.2 | H70: Traditional TCRL 2021-2
A71: GLP 1.0 | B71: Glucose Profile 1.0 | C71: 1.0 | D71: 44958 | E71: 45689 | F71: GLP.TS.p8 | G71: GLP.ICS.p3 | H71: GATTBased TCRL 2022-1
A72: GLS 1.0 | B72: Glucose Service 1.0 | C72: 1.0 | D72: 44958 | E72: 45689 | F72: GLS.TS.p10 | G72: GLS.ICS.p6 | H72: GATTBased TCRL 2022-1
A73: GOEP 2.0 | B73: Generic Object Exchange Profile 2.0 | C73: 2.0 | D73: 41479 | E73: - | F73: GOEP.TS.2.1.0 | G73: N/A | H73: Traditional TCRL 2015-1
A74: GOEP 2.1 | B74: Generic Object Exchange Profile 2.1 | C74: 2.1 | D74: 44228 | E74: 44593 | F74: GOEP.TS.2.1.1.2 | G74: N/A | H74: Traditional TCRL 2020-1
A75: GPP 1.0 | B75: Generic PIM Profile 1.0 | C75: 1.0 | D75: 44228 | E75: 44593 | F75: GPP.TS.1.0.1.1 | G75: N/A | H75: Traditional TCRL 2020-1
A76: HDP 1.0 | B76: Health Device Profile 1.0 | C76: 1.0 | D76: 41479 | E76: 45689 | F76: HDP.TS.1.1.0 | G76: HDP.ICS.1.1.0 | H76: Traditional TCRL 2015-1
A77: HDP 1.1 | B77: Health Device Profile 1.1 | C77: 1.1 | D77: 46784 | E77: 47515 | F77: TBD | G77: TBD | H77: TBD
A78: HFP 1.5 | B78: Hands-Free Profile 1.5​ | C78: 1.5 | D78: 44228 | E78: 44958 | F78: HFP.TS.p22 | G78: HFP.ICS.p18 | H78: Traditional TCRL 2020-1
A79: HFP 1.5.1 | B79: Hands-Free Profile 1.5​.1 | C79: 1.5.1 | D79: 44593 | E79: 44958 | F79: HFP.TS.p23 | G79: HFP.ICS.p18 | H79: Traditional TCRL 2021-2
A80: HFP 1.6 | B80: Hands-Free Profile 1.6 | C80: 1.6 | D80: 44228 | E80: 44958 | F80: HFP.TS.p22 | G80: HFP.ICS.p18 | H80: Traditional TCRL 2020-1
A81: HFP 1.6.1 | B81: Hands-Free Profile 1.6.1 | C81: 1.6.1 | D81: 44593 | E81: 45323 | F81: HFP.TS.p23 | G81: HFP.ICS.p18 | H81: Traditional TCRL 2021-2
A82: HFP 1.7 | B82: Hands-Free Profile 1.7 | C82: 1.7 | D82: 44228 | E82: 45323 | F82: HFP.TS.p22 | G82: HFP.ICS.p18 | H82: Traditional TCRL 2020-1
A83: HFP 1.7.1 | B83: Hands-Free Profile 1.7​.1 | C83: 1.7.1 | D83: 44228 | E83: 45323 | F83: HFP.TS.p22 | G83: HFP.ICS.p18 | H83: Traditional TCRL 2020-1
A84: HID 1.1 | B84: Human Interface Device Profile 1.1 | C84: 1.1 | D84: 44228 | E84: 45323 | F84: HID.TS.1.1.1.3 | G84: HID.ICS.1.1.1.1 | H84: Traditional TCRL 2020-1
A85: HSP 1.1 | B85: Headset Profile 1.1 | C85: 1.1 | D85: 45689 | E85: 46419 | F85: HSP.TS.p11 | G85: HSP.ICS.p6 | H85: Traditional TCRL 2024-1
A86: IDP 1.0 | B86: Insulin Delivery Profile 1.0 | C86: 1.0 | D86: 44958 | E86: 45689 | F86: IDP.TS.p1 | G86: IDP.ICS.p1 | H86: GATTBased TCRL 2022-1
A87: IDP 1.0.1 | B87: Insulin Delivery Profile 1.0.1 | C87: 1.0.1 | D87: 46784 | E87: 47515 | F87: TBD | G87: TBD | H87: TBD
A88: IDS 1.0 | B88: Insulin Delivery Service 1.0 | C88: 1.0 | D88: 44958 | E88: 45689 | F88: IDS.TS.p1 | G88: IDS.ICS.p1 | H88: GATTBased TCRL 2022-1
A89: IDS 1.0.1 | B89: Insulin Delivery Service 1.0.1 | C89: 1.0.1 | D89: 46784 | E89: 47515 | F89: TBD | G89: TBD | H89: TBD
A90: LLS 1.0 | B90: Link Loss Service 1.0 | C90: 1.0 | D90: 46784 | E90: 47515 | F90: TBD | G90: TBD | H90: TBD
A91: MAP 1.0 | B91: Message Access Profile 1.0 | C91: 1.0 | D91: 42201 | E91: 44958 | F91: MAP.TS.1.2.1 | G91: MAP.ICS.1.2.0 | H91: Traditional TCRL 2015-1
A92: MAP 1.1 | B92: Message Access Profile 1.1 | C92: 1.1 | D92: 44958 | E92: 45323 | F92: MAP.TS.p14 | G92: MAP.ICS.p10 | H92: Traditional TCRL 2022-1
A93: MAP 1.2 | B93: Message Access Profile 1.2 | C93: 1.2 | D93: 44228 | E93: 45323 | F93: MAP.TS.1.4.2.0 | G93: MAP.ICS.1.4.2.0 | H93: Traditional TCRL 2020-1
A94: MAP 1.2.1 | B94: Message Access Profile 1.2.1 | C94: 1.2.1 | D94: 44228 | E94: 45323 | F94: MAP.TS.1.4.2.0 | G94: MAP.ICS.1.4.2.0 | H94: Traditional TCRL 2020-1
A95: MAP 1.2.2 | B95: Message Access Profile 1.2.2 | C95: 1.2.2 | D95: 44958 | E95: 45323 | F95: MAP.TS.p14 | G95: MAP.ICS.p10 | H95: Traditional TCRL 2022-1
A96: MAP 1.3 | B96: Message Access Profile 1.3 | C96: 1.3 | D96: 44228 | E96: 45323 | F96: MAP.TS.1.4.2.0 | G96: MAP.ICS.1.4.2.0 | H96: Traditional TCRL 2020-1
A97: MAP 1.3.1 | B97: Message Access Profile 1.3.1 | C97: 1.3.1 | D97: 46784 | E97: 47515 | F97: TBD | G97: TBD | H97: TBD
... A104: PBAP 1.0 | B104: Phone Book Access Profile 1.0 | C104: 1.0 | D104: 42327 | E104: 44958 | F104: PBAP.TS.1.2.3 | G104: PBAP.ICS.1.2.1 | H104: Traditional TCRL 2015-1
A105: PBAP 1.1 | B105: Phone Book Access Profile 1.1 | C105: 1.1 | D105: 42327 | E105: 44958 | F105: PBAP.TS.1.2.3 | G105: PBAP.ICS.1.2.1 | H105: Traditional TCRL 2015-1
A106: PBAP 1.1.1 | B106: Phone Book Access Profile 1.1.1 | C106: 1.1.1 | D106: 46784 | E106: 47515 | F106: TBD | G106: TBD | H106: TBD
A107: PBAP 1.2 | B107: Phone Book Access Profile 1.2 | C107: 1.2 | D107: 44228 | E107: 45323 | F107: PBAP.TS.1.2.3.0 | G107: PBAP.ICS.1.2.3.1 | H107: Traditional TCRL 2020-1
A108: PBAP 1.2.1 | B108: Phone Book Access Profile 1.2.1 | C108: 1.2.1 | D108: 44228 | E108: 45323 | F108: PBAP.TS.1.2.3.0 | G108: PBAP.ICS.1.2.3.1 | H108: Traditional TCRL 2020-1
A109: PLXP 1.0 | B109: Pulse Oximeter Profile 1.0 | C109: 1.0 | D109: 44958 | E109: 45689 | F109: PLXP.TS.p3 | G109: PLXP.ICS.p3 | H109: GATTBased TCRL 2022-1
A110: PLXS 1.0 | B110: Pulse Oximeter Service 1.0 | C110: 1.0 | D110: 44958 | E110: 45689 | F110: PLXS.TS.p4 | G110: PLXS.ICS.p2 | H110: GATTBased TCRL 2022-1
A111: PXP 1.0 | B111: Proximity Profile 1.0 | C111: 1.0 | D111: 44228 | E111: 44593 | F111: PXP.TS.1.0.1.3 | G111: PXP.ICS.1.0.1.1 | H111: GATTBased TCRL 2020-1
A112: RCP 1.0 | B112: Reconnection Configuration Profile 1.0 | C112: 1.0 | D112: 44958 | E112: 45689 | F112: RCP.TS.p1 | G112: RCP.ICS.p1 | H112: GATTBased TCRL 2022-1
...

Sheet Expedited Errata TS&ICS impact
A1: Expedited Errata: TS & ICS impact
A2: This sheet informatively summarizes the qualification requirement changes and additions connected to the expedited specification erratum as defined when first qualifiable.
A3: Note that qualification requirement applicability to an IUT is always determined through the combination of supported features in the ICS, the selection logic in the TCMT, and the status of each test case listed in the rollup TCRL.
A5: Erratum Nr | B5: Adoption Date | C5: Description
A6: 11838 | B6: 43690 | C6: Encryption Key Size Updates
A7: 10734 | B7: 43297 | C7: Pairing Updates
A8: 18552 | B8: 45454 | C8: Access to additional CIS parameters
A9: 24617 | B9: 45531 | C9: Security changes - batch 1
A10: 25800 | B10: 45531 | C10: Expedited fixes to Frame Space Update
A11: 27096 | B11: 45782 | C11: Pause Encryption should be mandatory to support with encryption
A14: Erratum 11838 Encryption Key Size Updates: TS and ICS impact
A15: The erratum was first qualifiable in TCRL 2019-1, with its qualification requirements available from 20-Aug-2019 and active from 20-Feb-2020.
A16: HCI
A17: ICS changes | B17: TCID/Item number | C17: Description
A18: Modified Condition | B18: HCI 16/30 | C18: HCI Read Encryption Key Size Command
A19: GAP
A20: TS changes | B20: TCID/Item number | C20: Description
A21: New TC | B21: GAP/SEC/SEM/BI-01-C | C21: Security Mode 2, Responder - Invalid Encryption Key Size
A22: New TC | B22: GAP/SEC/SEM/BI-02-C | C22: Security Mode 4 Level 2, Responder - Invalid Encryption Key Size
A23: New TC | B23: GAP/SEC/SEM/BI-03-C | C23: Security Mode 4 Level 3, Responder - Invalid Encryption Key Size
A24: New TC | B24: GAP/SEC/SEM/BI-04-C | C24: Security Mode 4 Level 4, Responder - Invalid Encryption Key Size
A25: New TC | B25: GAP/SEC/SEM/BI-05-C | C25: Security Mode 2, Initiator - Invalid Key Size
A26: New TC | B26: GAP/SEC/SEM/BI-06-C | C26: Security Mode 4 Level 2, Initiator - Invalid Encryption Key Size
A27: New TC | B27: GAP/SEC/SEM/BI-07-C | C27: Security Mode 4 Level 3, Initiator - Invalid Encryption Key Size
A28: New TC | B28: GAP/SEC/SEM/BI-08-C | C28: Security Mode 4 Level 4, Initiator - Invalid Encryption Key Size
A29: New TC | B29: GAP/SEC/SEM/BI-09-C | C29: LE Security Mode 1 Level 4, Peripheral - Invalid Encryption Key Size
A30: New TC | B30: GAP/SEC/SEM/BI-10-C | C30: LE Security Mode 1 Level 4, Central - Invalid Encryption Key Size
A31: New TC | B31: GAP/SEC/SEM/BI-11-C | C31: Security Mode 4 Level 1, Responder - Invalid Encryption Key Size
... A34: New ICS item | B34: GAP 2/12 | C34: 56-bit minimum encryption key size
A35: LMP
A36: TS changes | B36: TCID/Item number | C36: Description
A37: New TC | B37: LMP/ENC/BV-51-C | C37: Key Size Negotiation as Peripheral - E0, Acceptor
A38: New TC | B38: LMP/ENC/BV-52-C | C38: Key Size Negotiation as Peripheral - AES, Acceptor
A39: New TC | B39: LMP/ENC/BV-53-C | C39: Key Size Negotiation as Central - E0
A40: New TC | B40: LMP/ENC/BV-54-C | C40: Key Size Negotiation as Central - AES
A41: New TC | B41: LMP/ENC/BV-55-C | C41: Key Size Negotiation as Peripheral - E0, Initiator
A42: New TC | B42: LMP/ENC/BV-56-C | C42: Key Size Negotiation as Peripheral - AES, Initiator
A43: SUM.ICS
A44: ICS changes | B44: TCID/Item number | C44: Description
A45: New ICS item | B45: SUM ICS 21/19 | C45: Core Controller/ Core Erratum 11838 Key Size Updates
A46: New ICS item | B46: SUM ICS 25/5 | C46: LE Core Controller/ Core Erratum 11838 Key Size Updates
A47: New ICS item | B47: SUM ICS 34/15 | C47: LE Host/ Core Erratum 11838 Key Size Updates
A49: Erratum 10734 Pairing Updates: TS and ICS impact
A50: The erratum was first qualifiable in TCRL 2018-1, with its qualification requirements available from 24-Jul-2018 and active from 24-Jan-2019.
A51: HCI
A52: TS changes | B52: TCID/Item number | C52: Description
A53: New TC | B53: HCI/AEN/BI-01-C | C53: Generate DH Key Error With Invalid Point
A54: New TC | B54: HCI/CIN/BV-08-C | C54: Read Local Simple Pairing Options Command
A55: New TC | B55: HCI/CIN/BV-09-C | C55: Read LE Public Key Validation Feature Bit
A56: ICS changes | B56: TCID/Item number | C56: Description
A57: New ICS item | B57: HCI 4/12 | C57: HCI Read Local Simple Pairing Options Command
A58: LL
A59: TS changes | B59: TCID/Item number | C59: Description
A60: Verdict clarification | B60: LL/CON/CEN/BV-13-C | C60: Feature Setup Request
A61: Verdict clarification | B61: LL/CON/CEN/BV-23-C | C61: Responding to Feature exchange
A62: Verdict clarification | B62: LL/CON/PER/BV-14-C | C62: Feature Setup Response
A63: Verdict clarification | B63: LL/CON/PER/BV-22-C | C63: Initiate Feature Exchange
A64: ICS changes | B64: TCID/Item number | C64: Description
A65: New ICS item | B65: LL 9/25 | C65: Remote Public Key Validation
A66: LMP
A67: TS changes | B67: TCID/Item number | C67: Description
A68: New TC | B68: LMP/SP/BI-01-C | C68: Numeric Comparison - IUT Initiator – Invalid Public Key Failure, P-192
A69: New TC | B69: LMP/SP/BI-02-C | C69: Numeric Comparison - IUT Responder – Invalid Public Key Failure, P-192
A70: New TC | B70: LMP/SP/BI-03-C | C70: Passkey Entry - IUT Initiator – Invalid Public Key Failure, P-192
A71: New TC | B71: LMP/SP/BI-04-C | C71: Passkey Entry - IUT Responder – Invalid Public Key Failure, P-192
A72: New TC | B72: LMP/SP/BI-05-C | C72: OOB Protocol - IUT Initiator - IUT with OOB Authentication Data – Invalid Public Key Failure, P-192
A73: New TC | B73: LMP/SP/BI-06-C | C73: OOB Protocol - IUT Responder - IUT with OOB Authentication Data – Invalid Public Key Failure, P-192
A74: New TC | B74: LMP/SP/BI-07-C | C74: Numeric Comparison - IUT Initiator – Invalid Public Key Failure, P-256
A75: New TC | B75: LMP/SP/BI-08-C | C75: Numeric Comparison - IUT Responder – Invalid Public Key Failure, P-256
A76: New TC | B76: LMP/SP/BI-09-C | C76: Passkey Entry - IUT Initiator – Invalid Public Key Failure, P-256
A77: New TC | B77: LMP/SP/BI-10-C | C77: Passkey Entry - IUT Responder – Invalid Public Key Failure, P-256
A78: New TC | B78: LMP/SP/BI-11-C | C78: OOB Protocol - IUT Initiator - IUT with OOB Authentication Data – Invalid Public Key Failure, P-256
A79: New TC | B79: LMP/SP/BI-12-C | C79: OOB Protocol - IUT Responder - IUT with OOB Authentication Data – Invalid Public Key Failure, P-256
A80: SM
A81: TS changes | B81: TCID/Item number | C81: Description
A82: New TC | B82: SM/PER/KDU/BI-01-C | C82: LE Secure Connections Pairing, IUT Responder – Lower Tester sends invalid public key
A83: New TC | B83: SM/CEN/KDU/BI-01-C | C83: LE Secure Connections Pairing, IUT Initiator – Lower Tester sends invalid public key
A84: SUM.ICS
A85: ICS changes | B85: TCID/Item number | C85: Description
A86: New ICS item | B86: SUM ICS 21/17 | C86: Core Controller/ Core Erratum 10734 Pairing updates
A87: New ICS item | B87: SUM ICS 25/4 | C87: LE Core Controller/ Core Erratum 10734 Pairing updates
A88: New ICS item | B88: SUM ICS 34/13 | C88: LE Host/ Core Erratum 10734 Pairing updates
A90: Erratum 18552 Access to additional CIS parameters: TS and ICS impact
A91: The erratum was first qualifiable in TCRL 2024-1, with its qualification requirements available from 2024-Jul-01 and active from 2025-Jan-01.
A92: HCI
A93: TS changes | B93: TCID/Item number | C93: Description
A94: Added Condition, Modified Verdict | B94: HCI/CIS/BV-01-C | C94: Connected Isochronous Stream Using Non-Test Command, Central Initiated, all PHYs, asymmetric PHYs
A95: Added Condition, Modified Verdict | B95: HCI/CIS/BV-02-C | C95: Connected Isochronous Stream Using Non-Test Command, Central Initiated, all PHYs, symmetric PHYs only
A96: Added Condition, Modified Verdict | B96: HCI/CIS/BV-03-C | C96: Connected Isochronous Stream Using Non-Test Command, Central Initiated, not all PHYs, asymmetric PHYs
A97: Added Condition, Modified Verdict | B97: HCI/CIS/BV-04-C | C97: Connected Isochronous Stream Using Non-Test Command, Central Initiated, not all PHYs, symmetric PHYs only
A98: Added Condition, Modified Test Step | B98: HCI/CIS/BI-06-C | C98: Invalid LE Accept or Reject CIS Request, Premature Setup ISO Data Path
A99: ICS changes | B99: TCID/Item number | C99: Description
A100: Modified Capability Name | B100: HCI 10/31 | C100: LE CIS Established event [v1]
A101: New ICS item | B101: HCI 10/31a | C101: LE CIS Established event [v2]
A103: Erratum 24617 Security changes - batch 1
A104: The erratum was first qualifiable in TCRL 2024-2, with its qualification requirements available from 2024-08-27 and active from 2025-03-05.
A105: LMP
A106: TS changes | B106: TCID/Item number | C106: Description
A107: Modified Rounds | B107: LMP/SP/BI-01-C | C107: Numeric Comparison – IUT Initiator – Invalid Public Key Failure, P-192
A108: New TC | B108: LMP/AUT/BI-08-C | C108: Pairing, IUT Initiator, Invalid Combination Key
...

Sheet Disclaimer
A1: Disclaimer and Copyright Notice
A2: This document, regardless of its title or content, is not a Bluetooth Specification as defined in the Bluetooth Patent/Copyright License Agreement (“PCLA”) and Bluetooth Trademark License Agreement. Use of this document by members of Bluetooth SIG is governed by the membership and other related agreements between Bluetooth SIG Inc. (“Bluetooth SIG”) and its members, including the PCLA and other agreements posted on Bluetooth SIG’s website located at www.bluetooth.com. THIS DOCUMENT IS PROVIDED “AS IS” AND BLUETOOTH SIG, ITS MEMBERS, AND THEIR AFFILIATES MAKE NO REPRESENTATIONS OR WARRANTIES AND DISCLAIM ALL WARRANTIES, EXPRESS OR IMPLIED, INCLUDING ANY WARRANTY OF MERCHANTABILITY, TITLE, NON-INFRINGEMENT, FITNESS FOR ANY PARTICULAR PURPOSE, THAT THE CONTENT OF THIS DOCUMENT IS FREE OF ERRORS. TO THE EXTENT NOT PROHIBITED BY LAW, BLUETOOTH SIG, ITS MEMBERS, AND THEIR AFFILIATES DISCLAIM ALL LIABILITY ARISING OUT OF OR RELATING TO USE OF THIS DOCUMENT AND ANY INFORMATION CONTAINED IN THIS DOCUMENT, INCLUDING LOST REVENUE, PROFITS, DATA OR PROGRAMS, OR BUSINESS INTERRUPTION, OR FOR SPECIAL, INDIRECT, CONSEQUENTIAL, INCIDENTAL OR PUNITIVE DAMAGES, HOWEVER CAUSED AND REGARDLESS OF THE THEORY OF LIABILITY, AND EVEN IF BLUETOOTH SIG, ITS MEMBERS, OR THEIR AFFILIATES HAVE BEEN ADVISED OF THE POSSIBILITY OF SUCH DAMAGES. This document is proprietary to Bluetooth SIG. This document may contain or cover subject matter that is intellectual property of Bluetooth SIG and its members. The furnishing of this document does not grant any license to any intellectual property of Bluetooth SIG or its members. This document is subject to change without notice.
A3: Copyright © 2015–2025 by Bluetooth SIG, Inc. The Bluetooth word mark and logos are owned by Bluetooth SIG, Inc. Other third-party brands and names are the property of their respective owners.
A684: 2) Category B starting on 2020-Jan-15, Category A starting 2020-Apr-15

Sheet Release Notes
A1: Release notes Core.TCRL.p49
A2: Published as part of TCRL.pkg101.p0
A3: *Note: The "Impact Rating" column below refers to TSE impact as defined in the Errata Process Document (EPD), available on the Bluetooth SIG member website. All TSEs for this rollup TCRL release are listed in the table below, but only TSEs with an impact rating of 3 or higher (i.e., TSEs that are not purely editorial) are listed in the individual layer tabs, with the exception of TSEs impacting the ICS and TCMT.
A4: **Note: The CRs associated with the Core v6.2 release are noted within this document according to the associated feature involved. LETM (LE Test Mode Enhancements), CSAA (Channel Sounding Amplitude-based Attack Resilience), and SCI (Shorter Connection Intervals).
A6: TSE | B6: Layer | C6: Document | D6: Impact Rating* | E6: Summary
A7: 27575 | B7: ATT | C7: ICS | D7: 1 | E7: Updated the ILDs for ATT 7/2 and ATT 7/3.
A8: 26825 | B8: BB | C8: ICS | D8: 1 | E8: Updated the status value for Item 10/7. Marked condition C.1 for Table 10 as no longer used.
A9: 27061 | B9: BB | C9: ICS | D9: 1 | E9: In Table 2, updated the status for Item 2/4; updated the reference for Items 2/7 and 2/8; added Items 4a and 7a; added an ILD column; updated conditions C.1, C.2, C.4, and C.5; and added C.6. In Table 5a, updated the status for Item 5a/3, updated all existing conditions, and added condition C.6. Added Section 3, Bridge mapping between BB ICS and LMP ICS (informational). Replaced all cross-references to reference [4] with cross-references to [1]. Updated the references list including the addition of a new reference [6].
A10: 27209 | B10: BB | C10: ICS | D10: 1 | E10: Updated language per the current ICS template in Items 1a/1 – 1a/3 and condition C.2 in Table 1a; C.1 and C.3 in Table 5a; and C.1 and C.3 in Table 6a.
A11: 26912 | B11: BB | C11: TS | D11: 2 | E11: Updated the test procedure for BB/PROT/ARQ/BV-33-C, -35-C, -37-C, -43-C, and -45-C.
A12: 27200 | B12: BB | C12: TCMT | D12: 2 | E12: Updated the TCMT entry to remove BB 2/7 for BB/PROT/ARQ/BV-40-C and -41-C and BB/PROT/CON/BV-10-C – -14-C.
A13: 27576 | B13: CORE | C13: ICS | D13: 1 | E13: Removed deleted GAP references from conditional C.1 in Table 20a.
A14: 27907 | B14: Core Test CR (CSAA) | C14: ICS, TS, TCMT, IXIT | D14: 4 | E14: CS.ICS: To support the CSAA feature added for Core v6.2, added 2/16 and associated conditional C.3. CS.TS: To support the CSAA feature in Core v6.2, added a new reference to Core v6.2, a new section entitled “Amplitude-based Attack NADM, Square Wave Test Strategy”, and new Amplitude-based Attack NADM, Square Wave tests CS/NAD/REF/BV-37-C – -48-C. Updated the TCMT accordingly. IXIT: Added IXIT values to the CS tab to support the updates for the CSAA feature in Core v6.2.
A15: 27886 | B15: Core Test CR (LETM) | C15: ICS, TS, TCMT | D15: 4 | E15: Core ICS: Incorporated LE_Test_Mode_Enhancements_TEST_CR_r10 to integrate the LE Test Mode Enhancements feature for Core v6.2. Added item 62 to Table 1a and accompanying conditional C.8. Added 2/62. Added 2a/62 and accompanying conditional C.8. Added 2b/62 and accompanying conditional C.8. LL.ICS: Incorporated LE_Test_Mode_Enhancements_TEST_CR_r10 to integrate the LE Test Mode Enhancements feature for Core v6.2. Added items 63–68 and accompanying conditionals C.58–C.60 to Table 9. Added a reference to Core v6.2 to the References section. Added PDUs to the PDU table. HCI.ICS: Incorporated LE_Test_Mode_Enhancements_TEST_CR_r10 to integrate the LE Test Mode Enhancements feature for Core v6.2. Added items 23–25 and accompanying conditionals C.80–C.81 to Table 17. Added a reference to Core v6.2 to the References section. LL.TS: Incorporated LE_Test_Mode_Enhancements_TEST_CR_r10 to integrate the LE Test Mode Enhancements feature for Core v6.2. Added a new reference to all files to cover the Core v6.2 adoption. In the PAC file, added a new section for UTP OTA Mode, including new TCs LL/PAC/BI-01-C and LL/PAC/BV-01-C – -04-C. Updated the TCMT accordingly. UHCI.ICS: Incorporated LE Test Mode Enhancements changes needed to support Core v6.2. Added a reference to Core v6.2 and added 0/62 with required conditional C.9.
A16: 27934 | B16: Core Test CR (SCI) | C16: ICS, TS, TCMT | D16: 4 | E16: Core ICS: Incorporated Shorter Connection Intervals Test CR r13 to integrate the Shorter Connection Intervals feature for Core v6.2. Added a reference to Core v6.2 to the References section; added item 1/62; added item 1a/62 and accompanying conditional C.8; added item 1b/62 and accompanying conditional C.8. LL.ICS: Incorporated Shorter Connection Intervals Test CR r13 to integrate the Shorter Connection Intervals feature for Core v6.2. Added a reference to Core v6.2 to the References section; added items 9/69 and 9/70 and accompanying conditional C.61. Added associated feature bits to the mapping table in Section 2. Added PDUs to the PDU table. HCI.ICS: Incorporated Shorter Connection Intervals Test CR r13 to integrate the Shorter Connection Intervals feature for Core v6.2. Added a reference to Core v6.2 to the References section; added items 7/53, 7/54, and 7/55 and accompanying conditional C.85; added items 12/4a and 12/5a and accompanying conditional C.86. LL.TS: Incorporated Shorter Connection Intervals Test CR r13 to integrate the Shorter Connection Intervals feature for Core v6.2. Added a reference to Core v6.2 to the References section; in the CON section, added new TCs LL/CON/CEN/BI-20-C – -23-C, LL/CON/CEN/BV-174-C – -176-C, LL/CON/PER/BI-27-C – -30-C, and LL/CON/PER/BV-178-C – -180-C. Updated the TCMT accordingly. (LATER INCORPORATION OF TI27749.) HCI.TS: Incorporated Shorter Connection Intervals Test CR r13 to integrate the Shorter Connection Intervals feature for Core v6.2. Added references to LL and HCI parts of Core v6.2 to the References section; added new TCs HCI/CCO/BI-133-C – -142-C; updated HCI/CCO/BI-63-C with an additional round. Updated the TCMT accordingly. (LATER INCORPORATION OF TI27749 with new TCs HCI/CCO/BI-143-C – 146-C and TI27898 with new TC HCI/CCO/BI-147-C.)
A17: 27815 | B17: CoreTCRL-Validation | C17: TCRL | D17: 2 | E17: Incorporated the validation decision for DEKRA SolutionPRO BEST RF Test System v5.1.0 into the Referenced Test Systems and DEKRA tabs of the TCRL, as well as noting the specific TCIDs on the RFPHY tab.
A18: 27822 | B18: CoreTCRL-Validation | C18: TCRL | D18: 2 | E18: Incorporated the validation decision for MinLian BTS 2.0.0 into the Referenced Test Systems and MinLian tabs of the TCRL, as well as noting the specific TCIDs on the RFPHY tab.
... A156: 27851 | B156: SM | C156: TS, TCMT | D156: 4 | E156: To accommodate E26047, added new TC SM/SIGN/BI-02-C. Updated the TCMT accordingly.

Sheet 80211MP
A1: Test Case Reference List
A2: =Top!C24 -> IEEE 802.11 PHY and MAC Layers | D2: Previous TS | E2: =Top!E24 -> 80211MP.TS.p7 | H2: TS | I2: =Top!G24 -> 80211MP.TS.p7 | J2: Available Date | K2: 45474
A3: =Top!D24 -> IEEE 802.11-2007 (1) | D3: Previous ICS | E3: =Top!F24 -> 80211MP.ICS.p7 | H3: ICS | I3: =Top!H24 -> 80211MP.ICS.p7 | J3: Available Date | K3: 45474
A4: Release date | B4: =rel_date -> 45965
A5: go to top | D5: Previously published test requirements | H5: Updated requirements through this release
A6: TCID*** | B6: Description | C6: TCRL Package Version Last Updated | D6: TC Category | E6: Active Date | F6: Test System Alternatives | G6: Notes | H6: TC Category | I6: Active Date | J6: Test System Alternatives | K6: Notes
A7: TCMT | B7: Test Case Mapping Table | C7: 2024-1 | E7: 45564 | G7: TSE 24025
A8: ICS | B8: Implementation Conformance Statement | C8: 2024-1 | E8: 45564 | G8: TSE 24025
A9: 80211MP/AD/BV-01-C | B9: Duration field zero | D9: B | E9: 45564 | F9: Member Defined
A10: 80211MP/AD/BV-02-C | B10: Duration field non-zero | D10: B | E10: 45564 | F10: Member Defined
A11: 80211MP/AD/BV-03-C | B11: Large duration value | D11: B | E11: 45564 | F11: Member Defined
A12: 80211MP/AD/BI-01-C | B12: FCS validation | D12: B | E12: 45564 | F12: Member Defined
A13: 80211MP/AD/BI-02-C | B13: Non-authenticated source | D13: B | E13: 45564 | F13: Member Defined
A14: 80211MP/ND/BV-01-C | B14: Process properly formatted null data frames | D14: B | E14: 45564 | F14: Member Defined
A15: 80211MP/ND/BI-01-C | B15: Reject improperly formatted null data frames | D15: B | E15: 45564 | F15: Member Defined
A16: 80211MP/RC/BV-01-C | B16: RTS/CTS with proper duration in CTS | D16: B | E16: 45564 | F16: Member Defined
A17: 80211MP/DF/BV-01-C | B17: Receive fragmented frames | D17: B | E17: 45564 | F17: Member Defined
A18: 80211MP/AFP/BI-01-C | B18: authentication frames with failure status code | D18: B | E18: 45564 | F18: Member Defined
A19: 80211MP/AFP/BI-02-C | B19: Authentication Frame Processing - invalid transaction sequence number | D19: B | E19: 45564 | F19: Member Defined
A20: 80211MP/AFP/BI-03-C | B20: authentication frames with invalid algorithm number | D20: B | E20: 45564 | F20: Member Defined
... A60: 80211MP/RT/BV-03-C | B60: IUT retransmits unacknowledged short data frame | D60: B | E60: 45564 | F60: Member Defined
A62: * Any technical changes in this release are indicated in the Notes column.
A63: *** Previous TCIDs of active test cases are listed in the TCID History tab at the end of this workbook.

Sheet 80211PAL
A1: Test Case Reference List
A2: =Top!C9 -> 802.11 PAL Conformance | D2: Previous TS | E2: =Top!E9 -> 80211PAL.TS.p13 | H2: TS | I2: =Top!G9 -> 80211PAL.TS.p13 | J2: Available Date | K2: 45474
A3: =Top!$D$9 -> Vol 5 Part A, 4.2–5.2 | D3: Previous ICS | E3: =Top!F9 -> 80211PAL.ICS.p9 | H3: ICS | I3: =Top!H9 -> 80211PAL.ICS.p9 | J3: Available Date | K3: 45474
A4: =Top!A2 -> Release Date | B4: =rel_date -> 45965
A5: go to top | D5: Previously published test requirements | H5: Updated requirements through this release
A6: TCID*** | B6: Description | C6: TCRL Package Version Last Updated | D6: TC Category | E6: Active Date | F6: Test System Alternatives | G6: Notes | H6: TC Category | I6: Active Date | J6: Test System Alternatives | K6: Notes
A7: TCMT | B7: Test Case Mapping Table | C7: 2024-1 | E7: 45564 | G7: TSE 24026
A8: ICS | B8: Implementation Conformance Statement | C8: 2024-1 | E8: 45564 | G8: TSE 24026
A9: 80211PAL/DI/AI/BV-01-C | B9: Read local AMP info | D9: B | E9: 45564 | F9: Member Defined
A10: 80211PAL/DI/AI/BV-02-C | B10: Read Local AMP Info on HT device, guaranteed logical links not supported | D10: B | E10: 45564 | F10: Member Defined
A11: 80211PAL/DI/AI/BV-03-C | B11: Read Local AMP Info on HT device, guaranteed logical links supported | D11: B | E11: 45564 | F11: Member Defined
A12: 80211PAL/DI/AA/BV-01-C | B12: Read local AMP Assoc, no Physical Link | D12: B | E12: 45564 | F12: Member Defined
A13: 80211PAL/DI/AA/BV-02-C | B13: Write Remote AMP Assoc | D13: B | E13: 45564 | F13: Member Defined
A14: 80211PAL/DI/AA/BI-01-C | B14: Write remote AMP Assoc, unsupported IE token | D14: B | E14: 45564 | F14: Member Defined
A15: 80211PAL/DI/AA/BI-02-C | B15: Read local AMP Assoc, invalid physical link | D15: B | E15: 45564 | F15: Member Defined
A16: 80211PAL/DI/AA/BV-03-C | B16: Read Local AMP Assoc, Activity Reports declared | D16: B | E16: 45564 | F16: Member Defined
A17: 80211PAL/DI/AA/BV-04-C | B17: Read Local AMP Assoc, Activity Report Scheduling supported | D17: B | E17: 45564 | F17: Member Defined
A18: 80211PAL/DI/AA/BV-05-C | B18: Read Local AMP Assoc on HT, 40 MHz channel generation | D18: B | E18: 45564 | F18: Member Defined
A19: 80211PAL/DI/AA/BV-06-C | B19: Write Remote AMP Assoc, 40 MHz channel parsing | D19: B | E19: 45564 | F19: Member Defined
A20: 80211PAL/DI/AA/BI-03-C | B20: Write remote AMP Assoc, invalid length of TLV | D20: B | E20: 45564 | F20: Member Defined
... A68: 80211PAL/OT/SRM/BV-01-C | B68: Short Range Mode | D68: B | E68: 45564 | F68: Member Defined
A70: * Any technical changes in this release are indicated in the Notes column.
A71: *** Previous TCIDs of active test cases are listed in the TCID History tab at the end of this workbook.

Sheet A2MP
A1: Test Case Reference List
A2: =Top!C20 -> AMP Manager Conformance | D2: Previous TS | E2: =Top!E20 -> A2MP.TS.p8 | H2: TS | I2: =Top!G20 -> A2MP.TS.p8 | J2: Available Date | K2: 43493
A3: =Top!$D$20 -> Vol 3 Part E, 4.2–5.2 | D3: Previous ICS | E3: =Top!F20 -> A2MP.ICS.p8 | H3: ICS | I3: =Top!H20 -> A2MP.ICS.p8 | J3: Available Date | K3: 45474
A4: Release date | B4: =rel_date -> 45965
A5: go to top | D5: Previously published test requirements | H5: Updated requirements through this release
A6: TCID*** | B6: Description | C6: TCRL Package Version Last Updated | D6: TC Category | E6: Active Date | F6: Test System Alternatives | G6: Notes | H6: TC Category | I6: Active Date | J6: Test System Alternatives | K6: Notes
A7: TCMT | B7: Test Case Mapping Table | E7: 43583
A8: ICS | B8: Implementation Conformance Statement | C8: 2024-1 | E8: 45564 | G8: TSE 24067
A9: A2MP/RSP/PROT/BV-01-C | B9: Respond to Illegal AMP Command | D9: B | E9: 43583 | F9: Member Defined
A10: A2MP/RSP/PROT/BV-02-C | B10: AMP Discover Request | D10: B | E10: 43583 | F10: Member Defined
A11: A2MP/RSP/PROT/BV-03-C | B11: AMP Discover Response | D11: B | E11: 43583 | F11: Member Defined
A12: A2MP/RSP/PROT/BV-05-C | B12: AMP Change Notify | D12: B | E12: 43583 | F12: Member Defined
A13: A2MP/RSP/PROT/BV-06-C | B13: AMP Change Response | D13: B | E13: 43583 | F13: Member Defined
A14: A2MP/RSP/PROT/BV-07-C | B14: AMP Get Info Request | D14: B | E14: 43583 | F14: Member Defined
A15: A2MP/RSP/PROT/BV-08-C | B15: AMP Get Info Response | D15: B | E15: 43583 | F15: Member Defined
A16: A2MP/RSP/PROT/BV-09-C | B16: AMP Get AMP Assoc Request | D16: B | E16: 43583 | F16: Member Defined
A17: A2MP/RSP/PROT/BV-10-C | B17: AMP Get AMP Assoc Response | D17: B | E17: 43583 | F17: Member Defined
A18: A2MP/RSP/PROT/BV-11-C | B18: AMP Get Info Request containing unsupported AMP ID | D18: B | E18: 43583 | F18: Member Defined
A19: A2MP/RSP/PROT/BV-12-C | B19: AMP Get AMP Assoc Request containing unsupported AMP ID | D19: B | E19: 43583 | F19: Member Defined
A20: A2MP/RSP/PROT/BV-13-C | B20: Extended Feature Mask Extension in AMP Discover Request | D20: B | E20: 43583 | F20: Member Defined
... A36: A2MP/RSP/SEC/BV-03-C | B36: Successful Initiation of Physical Link - Change of BR/EDR Link Key - IUT as Initiator | D36: B | E36: 43583 | F36: Member Defined
A37: A2MP/RSP/SEC/BV-04-C | B37: No longer used | C37: 2021-1
A38: A2MP/RSP/SEC/BV-05-C | B38: Unsuccessful Initiation of Physical Link version 1 - Retry - IUT as Initiator | D38: B | E38: 43583 | F38: Member Defined
A39: A2MP/RSP/SEC/BV-06-C | B39: No longer used | C39: 2021-1
A40: A2MP/RSP/SEC/BV-07-C | B40: Unsuccessful Initiation of Physical Link version 2 - Retry - IUT is Initiator | D40: B | E40: 43583 | F40: Member Defined
A41: A2MP/RSP/SEC/BV-08-C | B41: No longer used | C41: 2021-1
A42: A2MP/RSP/SEC/BV-09-C | B42: Successful Initiation of Physical Link - Reconnection - IUT is Responder | D42: B | E42: 43583 | F42: Member Defined
A43: A2MP/RSP/SEC/BV-10-C | B43: Successful Initiation of Physical Link - Repairing - IUT as Responder | D43: B | E43: 43583 | F43: Member Defined
A44: A2MP/RSP/SEC/BV-11-C | B44: No longer used | C44: 2021-1
A45: A2MP/RSP/SEC/BV-12-C | B45: Unsuccessful Initiation of Physical Link version 1 - Retry - IUT as Responder | D45: B | E45: 43583 | F45: Member Defined
A46: A2MP/RSP/SEC/BV-13-C | B46: No longer used | C46: 2021-1
A47: A2MP/RSP/SEC/BV-14-C | B47: Unsuccessful Initiation of Physical Link version 2 - Retry - IUT is Responder | D47: B | E47: 43583 | F47: Member Defined
A48: A2MP/RSP/SEC/BV-15-C | B48: No longer used | C48: 2021-1
A50: * Any technical changes in this release are indicated in the Notes column.
A51: *** Previous TCIDs of active test cases are listed in the TCID History tab at the end of this workbook.

Sheet BB
A1: Test Case Reference List
A2: =Top!C6 -> Baseband Conformance | D2: Previous TS | E2: =Top!E6 -> BB.TS.p38 | H2: TS | I2: =Top!G6 -> BB.TS.p39 | J2: Available Date | K2: =rel_date -> 45965
A3: =Top!D6 -> Vol 2 Part B, 4.2–6.2 | D3: Previous ICS | E3: =Top!F6 -> BB.ICS.p27 | H3: ICS | I3: =Top!H6 -> BB.ICS.p28 | J3: Available Date | K3: =rel_date -> 45965
A4: =Top!A2 -> Release Date | B4: =Top!$B$2 -> 45965
A5: go to top | D5: Previously published test requirements | H5: Updated requirements through this release
A6: TCID*** | B6: Description | C6: TCRL Package Version Last Updated | D6: TC Category | E6: Active Date | F6: Test System Alternatives | G6: Notes | H6: TC Category | I6: Active Date | J6: Test System Alternatives | K6: Notes
A7: TCMT | B7: Test Case Mapping Table | C7: pkg101 | E7: 45873 | G7: TSE 26887 | I7: =$B$4+90 -> 46055 | K7: TSE 27200
A8: ICS | B8: Implementation Conformance Statement | C8: pkg101 | E8: 45629 | I8: =$B$4+90 -> 46055 | K8: TSEs 26825, 27061, 27209
A9: BB/PHYS/FRE/BV-01-C | B9: 79 Channel Hop Seq | D9: A | E9: 45873 | F9: 15) | H9: A | I9: =$B$4+90 -> 46055 | J9: 15)
A10: BB/PHYS/FRE/BV-02-C | B10: AFH Hop Seq | D10: A | E10: 45873 | F10: 15) | H10: A | I10: =$B$4+90 -> 46055 | J10: 15)
A11: BB/PHYS/FRE/BV-03-C | B11: AFH Hop Seq after Role Switch | D11: A | E11: 45873 | F11: 15) | H11: A | I11: =$B$4+90 -> 46055 | J11: 15)
A12: BB/PHYS/INQ/BV-01-C | B12: Inquiry Hop Sequence | D12: A | E12: 45873 | F12: 15) | H12: A | I12: =$B$4+90 -> 46055 | J12: 15)
A13: BB/PHYS/INQ/BV-03-C | B13: Inquiry Proc | D13: A | E13: 45873 | F13: 15) | H13: A | I13: =$B$4+90 -> 46055 | J13: 15)
A14: BB/PHYS/INQ/BV-10-C | B14: Inquiry Response | D14: A | E14: 45873 | F14: 15) | H14: A | I14: =$B$4+90 -> 46055 | J14: 15)
A15: BB/PHYS/INQ/BV-14-C | B15: Inquiry Scan Window and Interval | D15: A | E15: 45873 | F15: 15) | H15: A | I15: =$B$4+90 -> 46055 | J15: 15)
A16: BB/PHYS/INQ/BV-15-C | B16: Interlaced Inquiry Scan Window and Interval | D16: A | E16: 45873 | F16: 15) | H16: A | I16: =$B$4+90 -> 46055 | J16: 15)
A17: BB/PHYS/INQ/BV-16-C | B17: Reception of Extended Inquiry Response | D17: A | E17: 45873 | F17: 15) | H17: A | I17: =$B$4+90 -> 46055 | J17: 15)
A18: BB/PHYS/INQ/BV-17-C | B18: Transmission of Extended Inquiry Response | D18: A | E18: 45873 | F18: 15) | H18: A | I18: =$B$4+90 -> 46055 | J18: 15)
A19: BB/PHYS/INQ/BV-18-C | B19: Inquiry Result Event Usage | D19: A | E19: 45873 | F19: 15) | H19: A | I19: =$B$4+90 -> 46055 | J19: 15)
A20: BB/PHYS/INQ/BV-19-C | B20: Inquiry Hop Sequence with Train Nudge | D20: A | E20: 45873 | F20: 15) | H20: A | I20: =$B$4+90 -> 46055 | J20: 15)
A21: BB/PHYS/INQ/BV-20-C | B21: Generalized Interlaced Inquiry Scan | D21: A | E21: 45873 | F21: 15) | H21: A | I21: =$B$4+90 -> 46055 | J21: 15)
A22: BB/PHYS/PAG/BI-01-C | B22: Ignore Page from Central using the IUT address | C22: 2024-2 | D22: A | E22: 45873 | F22: 15) | H22: A | I22: =$B$4+90 -> 46055 | J22: 15)
A23: BB/PHYS/PAG/BV-01-C | B23: Page Hop Seq | D23: A | E23: 45873 | F23: 15) | H23: A | I23: =$B$4+90 -> 46055 | J23: 15)
A24: BB/PHYS/PAG/BV-03-C | B24: Page Response to 1st Message | D24: A | E24: 45873 | F24: 15) | H24: A | I24: =$B$4+90 -> 46055 | J24: 15)
A25: BB/PHYS/PAG/BV-05-C | B25: Page Response to 2nd Message | D25: A | E25: 45873 | F25: 15) | H25: A | I25: =$B$4+90 -> 46055 | J25: 15)
A26: BB/PHYS/PAG/BV-10-C | B26: Page Response 1/1 Slot | D26: A | E26: 45873 | F26: 15) | H26: A | I26: =$B$4+90 -> 46055 | J26: 15)
A27: BB/PHYS/PAG/BV-12-C | B27: Page Response 1/2 slot | D27: A | E27: 45873 | F27: 15) | H27: A | I27: =$B$4+90 -> 46055 | J27: 15)
A28: BB/PHYS/PAG/BV-14-C | B28: Page Scan Interval R0 | D28: A | E28: 45873 | F28: 15) | H28: A | I28: =$B$4+90 -> 46055 | J28: 15)
A29: BB/PHYS/PAG/BV-16-C | B29: Page Scan Interval R1 | D29: A | E29: 45873 | F29: 15) | H29: A | I29: =$B$4+90 -> 46055 | J29: 15)
A30: BB/PHYS/PAG/BV-17-C | B30: Page Scan Interval R1 with Interlaced Scan | D30: A | E30: 45873 | F30: 15) | H30: A | I30: =$B$4+90 -> 46055 | J30: 15)
A31: BB/PHYS/PAG/BV-18-C | B31: Page Scan Interval R2 | D31: A | E31: 45873 | F31: 15) | H31: A | I31: =$B$4+90 -> 46055 | J31: 15)
A32: BB/PHYS/PAG/BV-19-C | B32: Page Scan Interval R2 and Interlaced Scan | D32: A | E32: 45873 | F32: 15) | H32: A | I32: =$B$4+90 -> 46055 | J32: 15)
A33: BB/PHYS/PAG/BV-20-C | B33: Page Hop Sequence with Train Nudge | D33: A | E33: 45873 | F33: 15) | H33: A | I33: =$B$4+90 -> 46055 | J33: 15)
A34: BB/PHYS/PAG/BV-21-C | B34: Generalized Interlaced Page Scan | D34: A | E34: 45873 | F34: 15) | H34: A | I34: =$B$4+90 -> 46055 | J34: 15)
... A45: BB/PHYS/TRX/BV-04-C | B45: Peripheral RX/TX Timing | D45: A | E45: 45873 | F45: 15) | H45: A | I45: =$B$4+90 -> 46055 | J45: 15)
A46: BB/PHYS/TRX/BV-05-C to -07-C | B46: No longer used
A47: BB/PROT/ARQ/BV-01-C | B47: Explicit NAK | D47: A | E47: 45873 | F47: 15) | H47: A | I47: =$B$4+90 -> 46055 | J47: 15)
A48: BB/PROT/ARQ/BV-02-C | B48: Implicit NAK | D48: A | E48: 45873 | F48: 15) | H48: A | I48: =$B$4+90 -> 46055 | J48: 15)
A49: BB/PROT/ARQ/BV-03-C | B49: Uncorrectable Packet Header | D49: A | E49: 45873 | F49: 15) | H49: A | I49: =$B$4+90 -> 46055 | J49: 15)
A50: BB/PROT/ARQ/BV-04-C | B50: Uncorrectable Payload | D50: A | E50: 45873 | F50: 15) | H50: A | I50: =$B$4+90 -> 46055 | J50: 15)
A51: BB/PROT/ARQ/BV-05-C | B51: SEQN | D51: A | E51: 45873 | F51: 15) | H51: A | I51: =$B$4+90 -> 46055 | J51: 15)
A52: BB/PROT/ARQ/BV-06-C | B52: FLOW Control | D52: A | E52: 45873 | F52: 15) | H52: A | I52: =$B$4+90 -> 46055 | J52: 15)
A53: BB/PROT/ARQ/BV-08-C | B53: Implicit GO | D53: A | E53: 45873 | F53: 15) | H53: A | I53: =$B$4+90 -> 46055 | J53: 15)
A54: BB/PROT/ARQ/BV-10-C | B54: Same SEQN Value | D54: A | E54: 45873 | F54: 15) | H54: A | I54: =$B$4+90 -> 46055 | J54: 15)
A55: BB/PROT/ARQ/BV-14-C | B55: Uncorrectable Packet Header | D55: A | E55: 45873 | F55: 15) | H55: A | I55: =$B$4+90 -> 46055 | J55: 15)
A56: BB/PROT/ARQ/BV-15-C | B56: Uncorrectable Payload | D56: A | E56: 45873 | F56: 15) | H56: A | I56: =$B$4+90 -> 46055 | J56: 15)
A57: BB/PROT/ARQ/BV-16-C | B57: Explicit NAK | D57: A | E57: 45873 | F57: 15) | H57: A | I57: =$B$4+90 -> 46055 | J57: 15)
A58: BB/PROT/ARQ/BV-18-C | B58: SEQN | D58: A | E58: 45873 | F58: 15) | H58: A | I58: =$B$4+90 -> 46055 | J58: 15)
... A68: BB/PROT/ARQ/BV-32-C | B68: Uncorrectable Header Re-transmission - eSCO Peripheral | D68: A | E68: 45873 | F68: 15) | H68: A | I68: =$B$4+90 -> 46055 | J68: 15)
A69: BB/PROT/ARQ/BV-33-C | B69: Flushable Packet is Flushed | C69: 2019-1 | D69: A | E69: 45873 | F69: 15) | H69: A | I69: =$B$4+90 -> 46055 | J69: 15)
A70: BB/PROT/ARQ/BV-34-C | B70: Non-Flushable Packet is Not Flushed | D70: A | E70: 45873 | F70: 15) | H70: A | I70: =$B$4+90 -> 46055 | J70: 15)
A71: BB/PROT/ARQ/BV-35-C | B71: Flushable L2CAP PDU with Multiple Fragments Flushed after First Fragment Sent | D71: A | E71: 45873 | F71: 15) | H71: A | I71: =$B$4+90 -> 46055 | J71: 15)
A72: BB/PROT/ARQ/BV-36-C | B72: Non-Flushable L2CAP PDU with Multiple Fragments is not Flushed after the First Fragment is Sent | D72: A | E72: 45873 | F72: 15) | H72: A | I72: =$B$4+90 -> 46055 | J72: 15)
A73: BB/PROT/ARQ/BV-37-C | B73: Flushable and Non-Flushable L2CAP PDUs | D73: A | E73: 45873 | F73: 15) | H73: A | I73: =$B$4+90 -> 46055 | J73: 15)
A74: BB/PROT/ARQ/BV-38-C | B74: Invalid MIC, Peripheral | D74: A | E74: 45873 | F74: 15) | H74: A | I74: =$B$4+90 -> 46055 | J74: 15)
A75: BB/PROT/ARQ/BV-39-C | B75: Secure Connections and Uncorrectable payload as Peripheral | D75: A | E75: 45873 | F75: 15) | H75: A | I75: =$B$4+90 -> 46055 | J75: 15)
A76: BB/PROT/ARQ/BV-40-C | B76: Retransmitting eSCO with AES as Peripheral | D76: A | E76: 45873 | F76: 15) | H76: A | I76: =$B$4+90 -> 46055 | J76: 15)
A77: BB/PROT/ARQ/BV-41-C | B77: Receiving eSCO retransmissions with AES as Peripheral | D77: A | E77: 45873 | F77: 15) | H77: A | I77: =$B$4+90 -> 46055 | J77: 15)
A78: BB/PROT/ARQ/BV-42-C | B78: Receiving retransmitted ACL packets that were previously acked with AES | D78: A | E78: 45873 | F78: 15) | H78: A | I78: =$B$4+90 -> 46055 | J78: 15)
A79: BB/PROT/ARQ/BV-43-C | B79: Flushable Packet is flushed with AES encryption | D79: A | E79: 45873 | F79: 15) | H79: A | I79: =$B$4+90 -> 46055 | J79: 15)
A80: BB/PROT/ARQ/BV-44-C | B80: Non-flushable Packet is not flushed with AES encryption | D80: A | E80: 45873 | F80: 15) | H80: A | I80: =$B$4+90 -> 46055 | J80: 15)
A81: BB/PROT/ARQ/BV-45-C | B81: Flushable L2CAP PDU with Multiple Fragments Flushed after First Packet Send, with AES encryption | D81: A | E81: 45873 | F81: 15) | H81: A | I81: =$B$4+90 -> 46055 | J81: 15)
... A85: BB/PROT/ARQ/BV-49-C | B85: Secure Connections and Uncorrectable payload as Central | D85: A | E85: 45873 | F85: 15) | H85: A | I85: =$B$4+90 -> 46055 | J85: 15)
A86: BB/PROT/CB/BV-01-C | B86: Connectionless Peripheral Broadcast Transmission | C86: 2022-2 | D86: A | E86: 45873 | F86: 15) | H86: A | I86: =$B$4+90 -> 46055 | J86: 15)
A87: BB/PROT/CB/BV-02-C | B87: AFH for Connectionless Peripheral Broadcast Transmission | C87: 2022-2 | D87: A | E87: 45873 | F87: 15) | H87: A | I87: =$B$4+90 -> 46055 | J87: 15)
A88: BB/PROT/CB/BV-03-C | B88: Connectionless Peripheral Broadcast Reception | D88: A | E88: 45873 | F88: 15) | H88: A | I88: =$B$4+90 -> 46055 | J88: 15)
A89: BB/PROT/CB/BV-04-C | B89: Connectionless Peripheral Broadcast Header Bits - Transmit | C89: 2022-2 | D89: A | E89: 45873 | F89: 15) | H89: A | I89: =$B$4+90 -> 46055 | J89: 15)
A90: BB/PROT/CB/BV-05-C | B90: Connectionless Peripheral Broadcast Header Bits - Receive | D90: A | E90: 45873 | F90: 15) | H90: A | I90: =$B$4+90 -> 46055 | J90: 15)
A91: BB/PROT/CB/BV-06-C | B91: Connectionless Peripheral Broadcast Data Retransmission | C91: 2022-2 | D91: A | E91: 45873 | F91: 15) | H91: A | I91: =$B$4+90 -> 46055 | J91: 15)
A92: BB/PROT/CB/BV-07-C | B92: Connectionless Peripheral Broadcast NULL Retransmission | C92: 2022-2 | D92: A | E92: 45873 | F92: 15) | H92: A | I92: =$B$4+90 -> 46055 | J92: 15)
A93: BB/PROT/CB/BV-08-C | B93: Connectionless Peripheral Broadcast Synchronization Delay | D93: A | E93: 45873 | F93: 15) | H93: A | I93: =$B$4+90 -> 46055 | J93: 15)
A94: BB/PROT/CB/BV-09-C | B94: Connectionless Peripheral Broadcast - Skip | D94: A | E94: 45873 | F94: 15) | H94: A | I94: =$B$4+90 -> 46055 | J94: 15)
A95: BB/PROT/CB/BV-10-C | B95: Connectionless Peripheral Broadcast - Ignore Skip | D95: A | E95: 45873 | F95: 15) | H95: A | I95: =$B$4+90 -> 46055 | J95: 15)
A96: BB/PROT/CB/BV-11-C | B96: Connectionless Peripheral Broadcast Timeout | D96: A | E96: 45873 | F96: 15) | H96: A | I96: =$B$4+90 -> 46055 | J96: 15)
A97: BB/PROT/COD/BV-01-C | B97: HV1 Packet Type | D97: A | E97: 45873 | F97: 15) | H97: A | I97: =$B$4+90 -> 46055 | J97: 15)
A98: BB/PROT/COD/BV-02-C | B98: HV2 Packet Type | D98: A | E98: 45873 | F98: 15) | H98: A | I98: =$B$4+90 -> 46055 | J98: 15)
A99: BB/PROT/COD/BV-03-C | B99: HV3 Packet Type | D99: A | E99: 45873 | F99: 15) | H99: A | I99: =$B$4+90 -> 46055 | J99: 15)
A100: BB/PROT/COD/BV-04-C | B100: DV Packet Type | D100: A | E100: 45873 | F100: 15) | H100: A | I100: =$B$4+90 -> 46055 | J100: 15)
A101: BB/PROT/COD/BV-05-C | B101: DH1 Packet Type | D101: A | E101: 45873 | F101: 15) | H101: A | I101: =$B$4+90 -> 46055 | J101: 15)
A102: BB/PROT/COD/BV-06-C | B102: DM3 Packet Type | D102: A | E102: 45873 | F102: 15) | H102: A | I102: =$B$4+90 -> 46055 | J102: 15)
A103: BB/PROT/COD/BV-07-C | B103: DH3 Packet Type | D103: A | E103: 45873 | F103: 15) | H103: A | I103: =$B$4+90 -> 46055 | J103: 15)
A104: BB/PROT/COD/BV-08-C | B104: DM5 Packet Type | D104: A | E104: 45873 | F104: 15) | H104: A | I104: =$B$4+90 -> 46055 | J104: 15)
... A143: BB/PROT/CON/BV-01-C | B143: POLL at Start Up | D143: A | E143: 45873 | F143: 15) | H143: A | I143: =$B$4+90 -> 46055 | J143: 15)
A144: BB/PROT/CON/BV-02-C | B144: Polling Peripheral | C144: 2018-1 | D144: A | E144: 45873 | F144: 15) | H144: A | I144: =$B$4+90 -> 46055 | J144: 15)
A145: BB/PROT/CON/BV-03-C | B145: Wrong UAP | D145: A | E145: 45873 | F145: 15) | H145: A | I145: =$B$4+90 -> 46055 | J145: 15)
A146: BB/PROT/CON/BV-04-C | B146: Change from DV to HV1 | D146: A | E146: 45873 | F146: 15) | H146: A | I146: =$B$4+90 -> 46055 | J146: 15)
A147: BB/PROT/CON/BV-05-C | B147: POLL at Start Up | D147: A | E147: 45873 | F147: 15) | H147: A | I147: =$B$4+90 -> 46055 | J147: 15)
A148: BB/PROT/CON/BV-08-C | B148: Wrong UAP | D148: A | E148: 45873 | F148: 15) | H148: A | I148: =$B$4+90 -> 46055 | J148: 15)
A149: BB/PROT/CON/BV-09-C | B149: Change from DV to HV1 | D149: A | E149: 45873 | F149: 15) | H149: A | I149: =$B$4+90 -> 46055 | J149: 15)
A150: BB/PROT/CON/BV-10-C | B150: AES DayCounter Initialization to 1 as Peripheral | D150: A | E150: 45873 | F150: 15) | H150: A | I150: =$B$4+90 -> 46055 | J150: 15)
A151: BB/PROT/CON/BV-11-C | B151: AES DayCounter increment at clock wrap-around as Peripheral | D151: A | E151: 45873 | F151: 15) | H151: A | I151: =$B$4+90 -> 46055 | J151: 15)
A152: BB/PROT/CON/BV-12-C | B152: AES DayCounter not initialized after an eSCO reconnection as Peripheral | D152: A | E152: 45873 | F152: 15) | H152: A | I152: =$B$4+90 -> 46055 | J152: 15)
A153: BB/PROT/CON/BV-13-C | B153: AES DayCounter initialization after a role switch as Peripheral | D153: A | E153: 45873 | F153: 15) | H153: A | I153: =$B$4+90 -> 46055 | J153: 15)
A154: BB/PROT/CON/BV-14-C | B154: AES DayCounter not initialized after an Encryption Pause and Resume | D154: A | E154: 45873 | F154: 15) | H154: A | I154: =$B$4+90 -> 46055 | J154: 15)
A155: BB/PROT/CON/BV-15-C | B155: Connected Peripheral Handles Page Request from the Same Address | C155: 2021-1 | D155: A | E155: 45873 | F155: 15) | H155: A | I155: =$B$4+90 -> 46055 | J155: 15)
A156: BB/PROT/CON/BV-16-C | B156: Terminate Connection at Link Supervision Timeout, Central | C156: 2024-1 | D156: A | E156: 45873 | F156: 15) | H156: A | I156: =$B$4+90 -> 46055 | J156: 15)
A157: BB/PROT/CON/BV-17-C | B157: Terminate Connection at Link Supervision Timeout, Peripheral | C157: 2024-1 | D157: A | E157: 45873 | F157: 15) | H157: A | I157: =$B$4+90 -> 46055 | J157: 15)
A158: BB/PROT/ED/BV-01-C | B158: Missed eSCO Data Packet | D158: B | E158: 45873 | F158: Member Defined | H158: B | I158: =$B$4+90 -> 46055 | J158: Member Defined
A159: BB/PROT/ED/BV-02-C | B159: eSCO data received with incorrect CRC or TYPE not allowed for the connection when eSCO retransmission window = 0 | C159: 2019-1 | D159: B | E159: 45873 | F159: Member Defined | H159: B | I159: =$B$4+90 -> 46055 | J159: Member Defined
A160: BB/PROT/ED/BV-03-C | B160: eSCO Data Received with Correct CRC, followed by a Retransmission with Incorrect CRC or TYPE not allowed for the connection | D160: B | E160: 45873 | F160: Member Defined | H160: B | I160: =$B$4+90 -> 46055 | J160: Member Defined
...

Sheet CS
A1: Test Case Reference List
A2: =Top!C14 -> Channel Sounding Conformance | D2: Previous TS | E2: =Top!E14 -> CS.TS.p2 | H2: TS | I2: =Top!G14 -> CS.TS.p3 | J2: Available Date | K2: =rel_date -> 45965
A3: =Top!D14 -> Vol 6 Part H, 6.0–6.2 | D3: Previous ICS | E3: =Top!F14 -> CS.ICS.p2 | H3: ICS | I3: =Top!H14 -> CS.ICS.p3 | J3: Available Date | K3: =rel_date -> 45965
A4: =Top!A2 -> Release Date | B4: =Top!$B$2 -> 45965
A5: go to top | D5: Previously published test requirements | H5: Updated requirements through this release
A6: TCID*** | B6: Description | C6: TCRL Package Version Last Updated | D6: TC Category | E6: Active Date | F6: Test System Alternatives | G6: Notes | H6: TC Category | I6: Active Date | J6: Test System Alternatives | K6: Notes
A7: TCMT | B7: Test Case Mapping Table | C7: pkg101 | E7: 45873 | G7: TSE 27418 | I7: =$B$4+90 -> 46055 | K7: TSE 27907 (CSAA) TSE 27591
A8: ICS | B8: Implementation Conformance Statement | C8: pkg101 | E8: 45873 | G8: TSE 26663 | I8: =$B$4+90 -> 46055 | K8: TSE 27907 (CSAA)
A9: CS/NAD/INI/BV-01-C | B9: Phase-Based Normalized Attack Detector Metric, Mode-1, Random Sequence 32-bits, Initiator LE 1M PHY | C9: 2024-2 | D9: B | E9: 45873 | F9: Member Defined | H9: B | I9: =$B$4+90 -> 46055 | J9: Member Defined
A10: CS/NAD/INI/BV-02-C | B10: Phase-Based Normalized Attack Detector Metric, Mode-1, Random Sequence 64-bits, Initiator LE 1M PHY | C10: 2024-2 | D10: B | E10: 45873 | F10: Member Defined | H10: B | I10: =$B$4+90 -> 46055 | J10: Member Defined
A11: CS/NAD/INI/BV-03-C | B11: Phase-Based Normalized Attack Detector Metric, Mode-1, Random Sequence 96-bits, Initiator LE 1M PHY | C11: 2024-2 | D11: B | E11: 45873 | F11: Member Defined | H11: B | I11: =$B$4+90 -> 46055 | J11: Member Defined
A12: CS/NAD/INI/BV-04-C | B12: Phase-Based Normalized Attack Detector Metric, Mode-1, Random Sequence 128-bits, Initiator LE 1M PHY | C12: 2024-2 | D12: B | E12: 45873 | F12: Member Defined | H12: B | I12: =$B$4+90 -> 46055 | J12: Member Defined
A13: CS/NAD/INI/BV-05-C | B13: Phase-Based Normalized Attack Detector Metric, Mode-1, Sounding Sequence 32-bits, Initiator LE 1M PHY | C13: 2024-2 | D13: B | E13: 45873 | F13: Member Defined | H13: B | I13: =$B$4+90 -> 46055 | J13: Member Defined
A14: CS/NAD/INI/BV-06-C | B14: Phase-Based Normalized Attack Detector Metric, Mode-1, Sounding Sequence 96-bits, Initiator LE 1M PHY | C14: 2024-2 | D14: B | E14: 45873 | F14: Member Defined | H14: B | I14: =$B$4+90 -> 46055 | J14: Member Defined
A15: CS/NAD/INI/BV-07-C | B15: Phase-Based Normalized Attack Detector Metric, Mode-3, Random Sequence 32-bits, Initiator LE 1M PHY | C15: 2024-2 | D15: B | E15: 45873 | F15: Member Defined | H15: B | I15: =$B$4+90 -> 46055 | J15: Member Defined
A16: CS/NAD/INI/BV-08-C | B16: Phase-Based Normalized Attack Detector Metric, Mode-3, Random Sequence 64-bits, Initiator LE 1M PHY | C16: 2024-2 | D16: B | E16: 45873 | F16: Member Defined | H16: B | I16: =$B$4+90 -> 46055 | J16: Member Defined
A17: CS/NAD/INI/BV-09-C | B17: Phase-Based Normalized Attack Detector Metric, Mode-3, Random Sequence 96-bits, Initiator LE 1M PHY | C17: 2024-2 | D17: B | E17: 45873 | F17: Member Defined | H17: B | I17: =$B$4+90 -> 46055 | J17: Member Defined
A18: CS/NAD/INI/BV-10-C | B18: Phase-Based Normalized Attack Detector Metric, Mode-3, Random Sequence 128-bits, Initiator LE 1M PHY | C18: 2024-2 | D18: B | E18: 45873 | F18: Member Defined | H18: B | I18: =$B$4+90 -> 46055 | J18: Member Defined
A19: CS/NAD/INI/BV-11-C | B19: Phase-Based Normalized Attack Detector Metric, Mode-3, Sounding Sequence 32-bits, Initiator LE 1M PHY | C19: 2024-2 | D19: B | E19: 45873 | F19: Member Defined | H19: B | I19: =$B$4+90 -> 46055 | J19: Member Defined
A20: CS/NAD/INI/BV-12-C | B20: Phase-Based Normalized Attack Detector Metric, Mode-3, Sounding Sequence 96-bits, Initiator LE 1M PHY | C20: 2024-2 | D20: B | E20: 45873 | F20: Member Defined | H20: B | I20: =$B$4+90 -> 46055 | J20: Member Defined
... A80: CS/NAD/REF/BV-36-C | B80: Phase-Based Normalized Attack Detector Metric, Mode-3, Sounding Sequence 96-bits, Reflector LE 2M 2BT PHY | C80: 2024-2 | D80: B | E80: 45873 | F80: Member Defined | H80: B | I80: =$B$4+90 -> 46055 | J80: Member Defined
A81: CS/NAD/REF/BV-37-C | B81: Amplitude-based Attack Resilience NADM, Mode-1, Random Sequence, LE 1M PHY | C81: pkg101 | H81: B | I81: =$B$4+0 -> 45965 | J81: Member Defined | K81: TSE 27907 (CSAA), new TC
A82: CS/NAD/REF/BV-38-C | B82: Amplitude-based Attack Resilience NADM, Mode-1, Sounding Sequence, LE 1M PHY | C82: pkg101 | H82: B | I82: =$B$4+0 -> 45965 | J82: Member Defined | K82: TSE 27907 (CSAA), new TC
A83: CS/NAD/REF/BV-39-C | B83: Amplitude-based Attack Resilience NADM, Mode-3, Random Sequence, LE 1M PHY | C83: pkg101 | H83: B | I83: =$B$4+0 -> 45965 | J83: Member Defined | K83: TSE 27907 (CSAA), new TC
A84: CS/NAD/REF/BV-40-C | B84: Amplitude-based Attack Resilience NADM, Mode-3, Sounding Sequence, LE 1M PHY | C84: pkg101 | H84: B | I84: =$B$4+0 -> 45965 | J84: Member Defined | K84: TSE 27907 (CSAA), new TC
A85: CS/NAD/REF/BV-41-C | B85: Amplitude-based Attack Resilience NADM, Mode-1, Random Sequence, LE 2M PHY | C85: pkg101 | H85: B | I85: =$B$4+0 -> 45965 | J85: Member Defined | K85: TSE 27907 (CSAA), new TC
A86: CS/NAD/REF/BV-42-C | B86: Amplitude-based Attack Resilience NADM, Mode-1, Sounding Sequence, LE 2M PHY | C86: pkg101 | H86: B | I86: =$B$4+0 -> 45965 | J86: Member Defined | K86: TSE 27907 (CSAA), new TC
A87: CS/NAD/REF/BV-43-C | B87: Amplitude-based Attack Resilience NADM, Mode-3, Random Sequence, LE 2M PHY | C87: pkg101 | H87: B | I87: =$B$4+0 -> 45965 | J87: Member Defined | K87: TSE 27907 (CSAA), new TC
A88: CS/NAD/REF/BV-44-C | B88: Amplitude-based Attack Resilience NADM, Mode-3, Sounding Sequence, LE 2M PHY | C88: pkg101 | H88: B | I88: =$B$4+0 -> 45965 | J88: Member Defined | K88: TSE 27907 (CSAA), new TC
A89: CS/NAD/REF/BV-45-C | B89: Amplitude-based Attack Resilience NADM, Mode-1, Random Sequence, LE 2M 2BT PHY | C89: pkg101 | H89: B | I89: =$B$4+0 -> 45965 | J89: Member Defined | K89: TSE 27907 (CSAA), new TC
A90: CS/NAD/REF/BV-46-C | B90: Amplitude-based Attack Resilience NADM, Mode-1, Sounding Sequence, LE 2M 2BT PHY | C90: pkg101 | H90: B | I90: =$B$4+0 -> 45965 | J90: Member Defined | K90: TSE 27907 (CSAA), new TC
A91: CS/NAD/REF/BV-47-C | B91: Amplitude-based Attack Resilience NADM, Mode-3, Random Sequence, LE 2M 2BT PHY | C91: pkg101 | H91: B | I91: =$B$4+0 -> 45965 | J91: Member Defined | K91: TSE 27907 (CSAA), new TC
A92: CS/NAD/REF/BV-48-C | B92: Amplitude-based Attack Resilience NADM, Mode-3, Sounding Sequence, LE 2M 2BT PHY | C92: pkg101 | H92: B | I92: =$B$4+0 -> 45965 | J92: Member Defined | K92: TSE 27907 (CSAA), new TC
A93: CS/PAC/INI/BV-01-C | B93: Sounding Sequence, Marker Signals, Initiator, LE 1M, Mode-1 32-bit | C93: pkg101 | D93: A | E93: 45873 | F93: 15) | H93: A | I93: =$B$4+90 -> 46055 | J93: 15), 20) | K93: TSE 26167
A94: CS/PAC/INI/BV-02-C | B94: Sounding Sequence, Marker Signals, Initiator, LE 2M, Mode-1 32-bit | C94: pkg101 | D94: A | E94: 45873 | F94: 15) | H94: A | I94: =$B$4+90 -> 46055 | J94: 15) | K94: TSE 26167
A95: CS/PAC/INI/BV-03-C | B95: Sounding Sequence, Marker Signals, Initiator, LE 1M, Mode-1 96-bit | C95: pkg101 | D95: A | E95: 45873 | F95: 15) | H95: A | I95: =$B$4+90 -> 46055 | J95: 15), 20) | K95: TSE 26167
A96: CS/PAC/INI/BV-04-C | B96: Sounding Sequence, Marker Signals, Initiator, LE 2M, Mode-1 96-bit | C96: pkg101 | D96: A | E96: 45873 | F96: 15) | H96: A | I96: =$B$4+90 -> 46055 | J96: 15) | K96: TSE 26167
A97: CS/PAC/INI/BV-05-C | B97: Sounding Sequence, Marker Signals, Initiator, LE 1M, Mode-3 32-bit | C97: pkg101 | D97: A | E97: 45873 | F97: 15) | H97: A | I97: =$B$4+90 -> 46055 | J97: 15) | K97: TSE 26167
A98: CS/PAC/INI/BV-06-C | B98: Sounding Sequence, Marker Signals, Initiator, LE 2M, Mode-3 32-bit | C98: pkg101 | D98: A | E98: 45873 | F98: 15) | H98: A | I98: =$B$4+90 -> 46055 | J98: 15) | K98: TSE 26167
A99: CS/PAC/INI/BV-07-C | B99: Sounding Sequence, Marker Signals, Initiator, LE 1M, Mode-3 96-bit | C99: pkg101 | D99: A | E99: 45873 | F99: 15) | H99: A | I99: =$B$4+90 -> 46055 | J99: 15) | K99: TSE 26167
A100: CS/PAC/INI/BV-08-C | B100: Sounding Sequence, Marker Signals, Initiator, LE 2M, Mode-3 96-bit | C100: pkg101 | D100: A | E100: 45873 | F100: 15) | H100: A | I100: =$B$4+90 -> 46055 | J100: 15) | K100: TSE 26167
A101: CS/PAC/INI/BV-09-C | B101: Random Sequence, LE 1M, Mode-1, 32-bit, Initiator | C101: pkg101 | D101: A | E101: 45873 | F101: 15) | H101: A | I101: =$B$4+90 -> 46055 | J101: 15), 20) | K101: TSE 26167
A102: CS/PAC/INI/BV-10-C | B102: Random Sequence, LE 1M, Mode-1, 64-bit, Initiator | C102: pkg101 | D102: A | E102: 45873 | F102: 15) | H102: A | I102: =$B$4+90 -> 46055 | J102: 15), 20) | K102: TSE 26167
A103: CS/PAC/INI/BV-11-C | B103: Random Sequence, LE 1M, Mode-1, 96-bit, Initiator | C103: pkg101 | D103: A | E103: 45873 | F103: 15) | H103: A | I103: =$B$4+90 -> 46055 | J103: 15), 20) | K103: TSE 26167
A104: CS/PAC/INI/BV-12-C | B104: Random Sequence, LE 1M, Mode-1, 128-bit, Initiator | C104: pkg101 | D104: A | E104: 45873 | F104: 15) | H104: A | I104: =$B$4+90 -> 46055 | J104: 15), 20) | K104: TSE 26167
... A146: CS/PAC/REF/BV-24-C | B146: Random Sequence, LE 2M, Mode-3, 128-bit, Reflector | C146: pkg101 | D146: A | E146: 45873 | F146: 15) | H146: A | I146: =$B$4+90 -> 46055 | J146: 15), 20) | K146: TSE 26167
A147: CS/PAC/REF/BV-25-C | B147: Access Address Quality Indicator, LE 1M | C147: 2024-2 | D147: A | E147: 45873 | F147: 15) | H147: A | I147: =$B$4+90 -> 46055 | J147: 15)
A148: CS/PAC/REF/BV-26-C | B148: Access Address Quality Indicator, LE 2M | C148: 2024-2 | D148: A | E148: 45873 | F148: 15) | H148: A | I148: =$B$4+90 -> 46055 | J148: 15)
A149: CS/PAC/REF/BV-27-C | B149: Sounding Sequence, 32-bit with invalid marker, Reflector | C149: pkg101 | D149: B | E149: 45873 | F149: Member Defined | H149: A | I149: =$B$4+90 -> 46055 | J149: 15), 20) | K149: TSE 26167
A150: CS/PAC/REF/BV-28-C | B150: Sounding Sequence, 96-bit with invalid marker, Reflector | C150: pkg101 | D150: B | E150: 45873 | F150: Member Defined | H150: A | I150: =$B$4+90 -> 46055 | J150: 15), 20) | K150: TSE 26167
A151: CS/PAC/REF/BV-29-C | B151: Channel Index Selection Algorithm #3b, Reflector | C151: pkg101 | D151: A | E151: 45873 | F151: 15) | H151: A | I151: =$B$4+90 -> 46055 | J151: 15), 20) | K151: TSE 26167
A152: CS/PAC/REF/BV-30-C | B152: Channel Index Selection Algorithm #3c, Reflector, Hat | C152: pkg101 | D152: A | E152: 45873 | F152: 15) | H152: A | I152: =$B$4+90 -> 46055 | J152: 15), 20) | K152: TSE 26167
A153: CS/PAC/REF/BV-31-C | B153: Channel Index Selection Algorithm #3c, Reflector, X Shape | C153: pkg101 | D153: A | E153: 45873 | F153: 15) | H153: A | I153: =$B$4+90 -> 46055 | J153: 15), 20) | K153: TSE 26167
A154: CS/PAC/REF/BV-32-C | B154: Main Mode Repetition, Verify Main Mode Repeated steps, Reflector | C154: pkg101 | D154: B | E154: 45873 | F154: Member Defined | H154: A | I154: =$B$4+90 -> 46055 | J154: 15), 20) | K154: TSE 26480
A155: CS/PM/INI/BV-01-C | B155: Phase Measurements during T_PM, Initiator, Mode-2 | C155: 2024-2 | D155: B | E155: 45873 | F155: Member Defined | H155: B | I155: =$B$4+90 -> 46055 | J155: Member Defined
A156: CS/PM/INI/BV-02-C | B156: Phase Measurements during T_PM, Initiator, Mode-3 | C156: 2024-2 | D156: B | E156: 45873 | F156: Member Defined | H156: B | I156: =$B$4+90 -> 46055 | J156: Member Defined
A157: CS/PM/INI/BV-03-C | B157: Initiator Transmit Antenna Switching Integrity, LE 1M, Mode-2, N_AP:1 | C157: 2024-2 | D157: B | E157: 45873 | F157: Member Defined | H157: B | I157: =$B$4+90 -> 46055 | J157: Member Defined
A158: CS/PM/INI/BV-04-C | B158: Initiator Transmit Antenna Switching Integrity, LE 1M, Mode-3, N_AP:1 | C158: 2024-2 | D158: B | E158: 45873 | F158: Member Defined | H158: B | I158: =$B$4+90 -> 46055 | J158: Member Defined
A159: CS/PM/INI/BV-07-C | B159: Initiator Transmit Antenna Switching Integrity, LE 1M, Mode-2, 2:2 | C159: 2024-2 | D159: B | E159: 45873 | F159: Member Defined | H159: B | I159: =$B$4+90 -> 46055 | J159: Member Defined
A160: CS/PM/INI/BV-08-C | B160: Initiator Transmit Antenna Switching Integrity, LE 1M, Mode-3, 2:2 | C160: 2024-2 | D160: B | E160: 45873 | F160: Member Defined | H160: B | I160: =$B$4+90 -> 46055 | J160: Member Defined
A161: CS/PM/INI/BV-09-C | B161: Phase-Based Distance Estimate, Sounding Sequence, LE 1M, Initiator, Mode-1, 32-bit Sounding Sequence | C161: 2024-2 | D161: B | E161: 45873 | F161: Member Defined | H161: B | I161: =$B$4+90 -> 46055 | J161: Member Defined
A162: CS/PM/INI/BV-10-C | B162: Phase-Based Distance Estimate, Sounding Sequence, LE 1M, Initiator, Mode-1, 96-bit Sounding Sequence | C162: 2024-2 | D162: B | E162: 45873 | F162: Member Defined | H162: B | I162: =$B$4+90 -> 46055 | J162: Member Defined
A163: CS/PM/INI/BV-11-C | B163: Phase-Based Distance Estimate, Sounding Sequence, LE 1M, Initiator, Mode-3, 32-bit Sounding Sequence | C163: 2024-2 | D163: B | E163: 45873 | F163: Member Defined | H163: B | I163: =$B$4+90 -> 46055 | J163: Member Defined
A164: CS/PM/INI/BV-12-C | B164: Phase-Based Distance Estimate, Sounding Sequence, LE 1M, Initiator, Mode-3, 96-bit Sounding Sequence | C164: 2024-2 | D164: B | E164: 45873 | F164: Member Defined | H164: B | I164: =$B$4+90 -> 46055 | J164: Member Defined
A165: CS/PM/INI/BV-13-C | B165: Phase-Based Distance Estimate, Sounding Sequence, LE 2M, Initiator, Mode-1, 32-bit Sounding Sequence | C165: 2024-2 | D165: B | E165: 45873 | F165: Member Defined | H165: B | I165: =$B$4+90 -> 46055 | J165: Member Defined
A166: CS/PM/INI/BV-14-C | B166: Phase-Based Distance Estimate, Sounding Sequence, LE 2M, Initiator, Mode-1, 96-bit Sounding Sequence | C166: 2024-2 | D166: B | E166: 45873 | F166: Member Defined | H166: B | I166: =$B$4+90 -> 46055 | J166: Member Defined
... A307: CS/TIM/REF/BV-10-C | B307: Power Ramp Profile, Ramp-down, Reflector, Step Mode-3 | C307: 2024-2 | D307: B | E307: 45873 | F307: Member Defined | H307: B | I307: =$B$4+90 -> 46055 | J307: Member Defined
A309: * Any technical changes in this release are indicated in the Notes column.
A310: *** Previous TCIDs of active test cases are listed in the TCID History tab at the end of this workbook.
A312: Note 1: Category B starting on 2024-09-04, Category A starting 2024-12-03
A314: 15) Ellisys Bluetooth Qualifier
A315: 20) RFcreations blueQCS

Sheet GAP
A1: Test Case Reference List
A2: Generic Access Profile Conformance | D2: Previous TS | E2: =Top!E19 -> GAP.TS.p48 | H2: TS | I2: =Top!G19 -> GAP.TS.p49 | J2: Available Date | K2: =rel_date -> 45965
A3: =Top!D19 -> Vol 3 Part C, 4.2–6.2 | D3: Previous ICS | E3: =Top!F19 -> GAP.ICS.p44 | H3: ICS | I3: =Top!H19 -> GAP.ICS.p45 | J3: Available Date | K3: =rel_date -> 45965
A4: Release date | B4: =rel_date -> 45965
A5: go to top | D5: Previously published test requirements | H5: Updated Requirements through this release
A6: TCID*** | B6: Description | C6: TCRL Package Version Last Updated | D6: TC Category | E6: Active Date | F6: Test System Alternatives | G6: Notes | H6: TC Category | I6: Active Date | J6: Test System Alternatives | K6: Notes
A7: TCMT | B7: Test Case Mapping Table | C7: pkg101 | E7: 45873 | G7: TSEs 18571, 26034, 26461, 26582, 26734 | I7: =$B$4+90 -> 46055 | K7: TSEs 27212, 27259, 27704
A8: ICS | B8: Implementation Conformance Statement | C8: pkg101 | E8: 45873 | G8: TSEs 18571, 26034, 26582, 26641, 26642, 27042 | I8: =$B$4+90 -> 46055 | K8: TSEs 26830, 27259, 27903
A9: GAP/ADV/BV-01-C | B9: AD type – Service UUID | C9: 2022-2 | D9: B | E9: 45873 | F9: 10) | H9: B | I9: =$B$4+90 -> 46055 | J9: 10)
A10: GAP/ADV/BV-02-C | B10: AD type – Local Name | C10: 2022-2 | D10: B | E10: 45873 | F10: 10) | H10: B | I10: =$B$4+90 -> 46055 | J10: 10)
A11: GAP/ADV/BV-03-C | B11: AD type – Flags | C11: 2022-2 | D11: B | E11: 45873 | F11: 10) | H11: B | I11: =$B$4+90 -> 46055 | J11: 10)
A12: GAP/ADV/BV-04-C | B12: AD type – Manufacturer Specific Data | C12: 2022-2 | D12: A | E12: 45873 | F12: 18) | H12: A | I12: =$B$4+90 -> 46055 | J12: 18)
A13: GAP/ADV/BV-05-C | B13: AD type – TX Power Level | C13: 2022-2 | D13: A | E13: 45873 | F13: 18) | H13: A | I13: =$B$4+90 -> 46055 | J13: 18)
A14: GAP/ADV/BV-08-C | B14: AD type – Peripheral Connection Interval Range | C14: 2022-2 | D14: A | E14: 45873 | F14: 18) | H14: A | I14: =$B$4+90 -> 46055 | J14: 18)
A15: GAP/ADV/BV-09-C | B15: AD type – Service Solicitation | C15: 2022-2 | D15: A | E15: 45873 | F15: 10) | H15: A | I15: =$B$4+90 -> 46055 | J15: 10)
A16: GAP/ADV/BV-10-C | B16: AD type – Service Data | C16: 2022-2 | D16: B | E16: 45873 | F16: 10) | H16: B | I16: =$B$4+90 -> 46055 | J16: 10)
A17: GAP/ADV/BV-11-C | B17: AD type – Appearance | C17: 2022-2 | D17: B | E17: 45873 | F17: 10) | H17: B | I17: =$B$4+90 -> 46055 | J17: 10)
A18: GAP/ADV/BV-12-C | B18: AD type – Public Target Address | C18: 2022-2 | D18: A | E18: 45873 | F18: 18) | H18: A | I18: =$B$4+90 -> 46055 | J18: 18)
A19: GAP/ADV/BV-13-C | B19: AD type – Random Target Address | C19: 2022-2 | D19: A | E19: 45873 | F19: 10) | H19: A | I19: =$B$4+90 -> 46055 | J19: 10)
A20: GAP/ADV/BV-14-C | B20: AD type – Advertising Interval | C20: 2022-2 | D20: A | E20: 45873 | F20: 18) | H20: A | I20: =$B$4+90 -> 46055 | J20: 18)
A21: GAP/ADV/BV-15-C to BV-16-C | B21: No longer used | C21: 2019-2
A22: GAP/ADV/BV-17-C | B22: AD type – URI | C22: 2022-2 | D22: B | E22: 45873 | F22: Member Defined | H22: B | I22: =$B$4+90 -> 46055 | J22: Member Defined
A23: GAP/ADV/BV-18-C | B23: AD type – Advertising Interval, Long | C23: 2022-2 | D23: B | E23: 45873 | F23: Member Defined | H23: B | I23: =$B$4+90 -> 46055 | J23: Member Defined
A24: GAP/ADV/BV-19-C | B24: AD type – LE Supported Features | C24: 2022-2 | D24: B | E24: 45873 | F24: Member Defined | H24: B | I24: =$B$4+90 -> 46055 | J24: Member Defined
A25: GAP/ADV/BV-20-C | B25: AD type – Encrypted Data | C25: pkg101 | D25: B | E25: 45873 | F25: Member Defined | H25: B | I25: =$B$4+90 -> 46055 | J25: Member Defined | K25: TSE 27704
A26: GAP/ADV/BV-21-C | B26: AD type – Encrypted Data | C26: pkg101 | H26: B | I26: =$B$4+180 -> 46145 | J26: Member Defined | K26: TSE 27704 (new TC)
A27: GAP/BIS/BBM/BV-01-C | B27: Broadcast Isochronous Stream Broadcasting mode | C27: 2019-2 | D27: B | E27: 45873 | F27: Member Defined | H27: B | I27: =$B$4+90 -> 46055 | J27: Member Defined
A28: GAP/BIS/BSE/BV-01-C | B28: Broadcast Isochronous Synchronization Establishment procedure | C28: 2019-2 | D28: B | E28: 45873 | F28: Member Defined | H28: B | I28: =$B$4+90 -> 46055 | J28: Member Defined
A29: GAP/BOND/BON/BV-01-C | B29: Initiate bonding – Peripheral role | C29: 2021-1 | D29: A | E29: 45873 | F29: 11) | H29: A | I29: =$B$4+90 -> 46055 | J29: 11)
A30: GAP/BOND/BON/BV-02-C | B30: Initiate bonding – Central role | C30: 2021-1 | D30: A | E30: 45873 | F30: 13) | H30: A | I30: =$B$4+90 -> 46055 | J30: 13)
A31: GAP/BOND/BON/BV-03-C | B31: Respond to bonding – Peripheral role | C31: 2021-1 | D31: A | E31: 45873 | F31: 10) | H31: A | I31: =$B$4+90 -> 46055 | J31: 10)
A32: GAP/BOND/BON/BV-04-C | B32: Respond to bonding – Central role | C32: 2021-1 | D32: A | E32: 45873 | F32: 19) | H32: A | I32: =$B$4+90 -> 46055 | J32: 19)
A33: GAP/BOND/NBON/BV-01-C | B33: Non-bondable mode – Central as Responder | D33: A | E33: 45873 | F33: 19) | H33: A | I33: =$B$4+90 -> 46055 | J33: 19)
A34: GAP/BOND/NBON/BV-02-C | B34: Non-bondable mode – Central as Initiator | D34: A | E34: 45873 | F34: 19) | H34: A | I34: =$B$4+90 -> 46055 | J34: 19)
A35: GAP/BOND/NBON/BV-03-C | B35: Non-bondable mode – Peripheral as Responder | D35: A | E35: 45873 | F35: 19) | H35: A | I35: =$B$4+90 -> 46055 | J35: 19)
A36: GAP/BROB/BCST/BV-01-C | B36: Broadcast mode, No Scan Response | D36: A | E36: 45873 | F36: 18) | H36: A | I36: =$B$4+90 -> 46055 | J36: 18)
A37: GAP/BROB/BCST/BV-02-C | B37: Broadcast mode, Scan Response | D37: A | E37: 45873 | F37: 18) | H37: A | I37: =$B$4+90 -> 46055 | J37: 18)
A38: GAP/BROB/BCST/BV-03-C | B38: Broadcast mode, Resolvable Private Address | D38: A | E38: 45873 | F38: 16) | H38: A | I38: =$B$4+90 -> 46055 | J38: 16)
A39: GAP/BROB/BCST/BV-04-C | B39: Broadcast mode, Non-Resolvable Private Address | D39: A | E39: 45873 | F39: 11) | H39: A | I39: =$B$4+90 -> 46055 | J39: 11)
A40: GAP/BROB/BCST/BV-05-C | B40: Broadcast mode, Resolvable Private Address, Scan Response | D40: B | E40: 45873 | F40: Member Defined | H40: B | I40: =$B$4+90 -> 46055 | J40: Member Defined
A41: GAP/BROB/OBSV/BV-01-C | B41: Observation procedure, Passive Scanning | D41: B | E41: 45873 | F41: Member Defined | H41: B | I41: =$B$4+90 -> 46055 | J41: Member Defined
A42: GAP/BROB/OBSV/BV-02-C | B42: Observation procedure, Active Scanning | D42: B | E42: 45873 | F42: Member Defined | H42: B | I42: =$B$4+90 -> 46055 | J42: Member Defined
A43: GAP/BROB/OBSV/BV-03-C to BV-04-C | B43: No longer used | C43: 2019-2
A44: GAP/BROB/OBSV/BV-05-C | B44: Observation procedure, Active Scanning Non-Resolvable Private Address or Resolvable Private Address | D44: B | E44: 45873 | F44: Member Defined | H44: B | I44: =$B$4+90 -> 46055 | J44: Member Defined
A45: GAP/BROB/OBSV/BV-06-C | B45: Observation procedure with Active Scanning, IUT and Peer using Resolvable Private Address | D45: B | E45: 45873 | F45: Member Defined | H45: B | I45: =$B$4+90 -> 46055 | J45: Member Defined
A46: GAP/CONN/ACEP/BV-01-C | B46: Auto Connection Establishment procedure, Directed Connectable mode | D46: A | E46: 45873 | F46: 10) | H46: A | I46: =$B$4+90 -> 46055 | J46: 10)
A47: GAP/CONN/ACEP/BV-02-C | B47: No longer used
A48: GAP/CONN/ACEP/BV-03-C | B48: Auto Connection Establishment procedure, Directed Connectable mode, Resolvable Private Address, Central Address Resolution | D48: B | E48: 45873 | F48: Member Defined | H48: B | I48: =$B$4+90 -> 46055 | J48: Member Defined
A49: GAP/CONN/ACEP/BV-04-C | B49: Auto Connection Establishment procedure, Undirected Connectable mode, Resolvable Private Address | D49: B | E49: 45873 | F49: Member Defined | H49: B | I49: =$B$4+90 -> 46055 | J49: Member Defined
A50: GAP/CONN/CPUP/BV-01-C | B50: Connection Parameter Update procedure, valid parameters, Peripheral Initiator over L2CAP | C50: 2021-1 | D50: B | E50: 45873 | F50: Member Defined | H50: B | I50: =$B$4+90 -> 46055 | J50: Member Defined
A51: GAP/CONN/CPUP/BV-02-C | B51: Connection Parameter Update procedure, valid parameters, Timeout Peripheral Initiator | C51: 2021-1 | D51: B | E51: 45873 | F51: Member Defined | H51: B | I51: =$B$4+90 -> 46055 | J51: Member Defined
A52: GAP/CONN/CPUP/BV-03-C | B52: Connection Parameter Update procedure, invalid parameters, Peripheral Initiator | C52: 2021-1 | D52: B | E52: 45873 | F52: Member Defined | H52: B | I52: =$B$4+90 -> 46055 | J52: Member Defined
A53: GAP/CONN/CPUP/BV-04-C | B53: Connection Parameter Update procedure, valid parameters, Central Responder | D53: A | E53: 45873 | F53: 12) | H53: A | I53: =$B$4+90 -> 46055 | J53: 12)
A54: GAP/CONN/CPUP/BV-05-C | B54: Connection Parameter Update procedure, invalid parameters, Central Responder | D54: A | E54: 45873 | F54: 11) | H54: A | I54: =$B$4+90 -> 46055 | J54: 11)
A55: GAP/CONN/CPUP/BV-06-C | B55: Connection Parameter Update procedure, valid parameters, Central Initiator | D55: B | E55: 45873 | F55: Member Defined | H55: B | I55: =$B$4+90 -> 46055 | J55: Member Defined
A56: GAP/CONN/CPUP/BV-07-C | B56: No longer used
A57: GAP/CONN/CPUP/BV-08-C | B57: Connection Parameter Update procedure, valid parameters, Peripheral Responder – LL Connection Parameters Request | D57: B | E57: 45873 | F57: Member Defined | H57: B | I57: =$B$4+90 -> 46055 | J57: Member Defined
A58: GAP/CONN/CPUP/BV-09-C | B58: No longer used
A59: GAP/CONN/CPUP/BV-10-C | B59: Connection Parameter Update procedure, valid parameters, Peripheral Initiator over LL | C59: 2021-1 | D59: B | E59: 45873 | F59: Member Defined | H59: B | I59: =$B$4+90 -> 46055 | J59: Member Defined
A60: GAP/CONN/DCEP/BV-01-C | B60: Direct Connection Establishment procedure, Directed Connectable mode | D60: A | E60: 45873 | F60: 10) | H60: A | I60: =$B$4+90 -> 46055 | J60: 10)
A61: GAP/CONN/DCEP/BV-02-C | B61: No longer used | C61: 2019-2
A62: GAP/CONN/DCEP/BV-03-C | B62: Direct Connection Establishment procedure, Undirected Connectable mode | D62: A | E62: 45873 | F62: 19) | H62: A | I62: =$B$4+90 -> 46055 | J62: 19)
A63: GAP/CONN/DCEP/BV-04-C | B63: No longer used | C63: 2019-2
A64: GAP/CONN/DCEP/BV-05-C | B64: Direct Connection Establishment procedure, Directed Connectable mode, Resolvable Private Address, Central Address Resolution | D64: B | E64: 45873 | F64: Member Defined | H64: B | I64: =$B$4+90 -> 46055 | J64: Member Defined
A65: GAP/CONN/DCEP/BV-06-C | B65: Direct Connection Establishment procedure, Undirected Connectable mode, Resolvable Private Address | D65: B | E65: 45873 | F65: Member Defined | H65: B | I65: =$B$4+90 -> 46055 | J65: Member Defined
A66: GAP/CONN/DCON/BV-01-C | B66: Directed Connectable mode | D66: A | E66: 45873 | F66: 19) | H66: A | I66: =$B$4+90 -> 46055 | J66: 19)
A67: GAP/CONN/DCON/BV-02-C to BV-03-C | B67: No longer used | C67: 2019-2
A68: GAP/CONN/DCON/BV-04-C | B68: Directed Connectable mode, Privacy, Resolvable Private Address, Central Address Resolution | C68: 2019-1 | D68: B | E68: 45873 | F68: Member Defined | H68: B | I68: =$B$4+90 -> 46055 | J68: Member Defined
A69: GAP/CONN/DCON/BV-05-C | B69: Directed Connectable mode, Privacy, Resolvable Private Address, Central Address Resolution not supported | C69: 2019-1 | D69: B | E69: 45873 | F69: Member Defined | H69: B | I69: =$B$4+90 -> 46055 | J69: Member Defined
A70: GAP/CONN/GCEP/BV-01-C | B70: General Connection Establishment procedure, Directed Connectable mode | D70: A | E70: 45873 | F70: 10) | H70: A | I70: =$B$4+90 -> 46055 | J70: 10)
A71: GAP/CONN/GCEP/BV-02-C | B71: General Connection Establishment procedure, Undirected Connectable mode | D71: A | E71: 45873 | F71: 19) | H71: A | I71: =$B$4+90 -> 46055 | J71: 19)
A72: GAP/CONN/GCEP/BV-03-C to BV-04-C | B72: No longer used | C72: 2019-2
A73: GAP/CONN/GCEP/BV-05-C | B73: General Connection Establishment procedure, Directed Connectable mode, Resolvable Private Address, Central Address Resolution | D73: B | E73: 45873 | F73: Member Defined | H73: B | I73: =$B$4+90 -> 46055 | J73: Member Defined
A74: GAP/CONN/GCEP/BV-06-C | B74: General Connection Establishment procedure, Undirected Connectable mode, Resolvable Private Address | D74: B | E74: 45873 | F74: Member Defined | H74: B | I74: =$B$4+90 -> 46055 | J74: Member Defined
A75: GAP/CONN/NCON/BV-01-C | B75: Non-Connectable mode | D75: A | E75: 45873 | F75: 19) | H75: A | I75: =$B$4+90 -> 46055 | J75: 19)
A76: GAP/CONN/NCON/BV-02-C | B76: Non-Connectable mode, General Discoverable mode | D76: A | E76: 45873 | F76: 19) | H76: A | I76: =$B$4+90 -> 46055 | J76: 19)
A77: GAP/CONN/NCON/BV-03-C | B77: Non-Connectable mode, Limited Discoverable mode | D77: A | E77: 45873 | F77: 19) | H77: A | I77: =$B$4+90 -> 46055 | J77: 19)
A78: GAP/CONN/PRDA/BV-01-C | B78: Respond to Private Random Device Address after Bonding – Peripheral role | D78: A | E78: 45873 | F78: 19) | H78: A | I78: =$B$4+90 -> 46055 | J78: 19)
A79: GAP/CONN/PRDA/BV-02-C | B79: Respond to Private Random Device Address after Bonding – Central role | D79: B | E79: 45873 | F79: Member Defined | H79: B | I79: =$B$4+90 -> 46055 | J79: Member Defined
A80: GAP/CONN/SCEP/BV-01-C | B80: Selective Connection Establishment procedure, Directed Connectable mode | D80: A | E80: 45873 | F80: 10) | H80: A | I80: =$B$4+90 -> 46055 | J80: 10)
A81: GAP/CONN/SCEP/BV-02-C | B81: No longer used | C81: 2019-2
A82: GAP/CONN/SCEP/BV-03-C | B82: Selective Connection Establishment procedure, Directed Connectable mode, Resolvable Private Address, Central Address Resolution | D82: B | E82: 45873 | F82: Member Defined | H82: B | I82: =$B$4+90 -> 46055 | J82: Member Defined
A83: GAP/CONN/TERM/BV-01-C | B83: Terminate Connection procedure | D83: A | E83: 45873 | F83: 19) | H83: A | I83: =$B$4+90 -> 46055 | J83: 19)
A84: GAP/CONN/UCON/BV-01-C | B84: Undirected Connectable mode, Non-Discoverable mode | D84: A | E84: 45873 | F84: 19) | H84: A | I84: =$B$4+90 -> 46055 | J84: 19)
A85: GAP/CONN/UCON/BV-02-C | B85: Undirected Connectable mode, General Discoverable mode | D85: A | E85: 45873 | F85: 19) | H85: A | I85: =$B$4+90 -> 46055 | J85: 19)
A86: GAP/CONN/UCON/BV-03-C | B86: Undirected Connectable mode, Limited Discoverable mode | D86: A | E86: 45873 | F86: 19) | H86: A | I86: =$B$4+90 -> 46055 | J86: 19)
A87: GAP/CONN/UCON/BV-04-C to BV-05-C | B87: No longer used | C87: 2019-2
A88: GAP/CONN/UCON/BV-06-C | B88: Undirected Connectable mode, Resolvable Private Address | D88: B | E88: 45873 | F88: Member Defined | H88: B | I88: =$B$4+90 -> 46055 | J88: Member Defined
A89: GAP/CS/BV-01-C | B89: Starting Channel Sounding, Initiator | C89: 2024-2 | D89: B | E89: 45873 | F89: Member Defined | H89: B | I89: =$B$4+90 -> 46055 | J89: Member Defined
A90: GAP/CS/BV-02-C | B90: Starting Channel Sounding, Reflector | C90: 2024-2 | D90: B | E90: 45873 | F90: Member Defined | H90: B | I90: =$B$4+90 -> 46055 | J90: Member Defined
A91: GAP/CSUB/CSR/BV-01-C | B91: Connection Subrate Request procedure | C91: 2021-1 | D91: B | E91: 45873 | F91: Member Defined | H91: B | I91: =$B$4+90 -> 46055 | J91: Member Defined
A92: GAP/CSUB/CSU/BV-01-C | B92: Connection Subrate Update procedure | C92: 2021-1 | D92: B | E92: 45873 | F92: Member Defined | H92: B | I92: =$B$4+90 -> 46055 | J92: Member Defined
A93: GAP/DISC/GENM/BV-01-C | B93: General Discoverable mode, Non-Connectable mode – BR/EDR/LE | D93: B | E93: 45873 | F93: Member Defined | H93: B | I93: =$B$4+90 -> 46055 | J93: Member Defined
A94: GAP/DISC/GENM/BV-02-C | B94: General Discoverable mode, Undirected Connectable mode – BR/EDR/LE | D94: A | E94: 45873 | F94: 10) | H94: A | I94: =$B$4+90 -> 46055 | J94: 10)
A95: GAP/DISC/GENM/BV-03-C | B95: General Discoverable mode, Non-Connectable mode – LE Only | D95: A | E95: 45873 | F95: 18) | H95: A | I95: =$B$4+90 -> 46055 | J95: 18)
A96: GAP/DISC/GENM/BV-04-C | B96: General Discoverable mode, Undirected Connectable mode – LE Only | D96: A | E96: 45873 | F96: 18) | H96: A | I96: =$B$4+90 -> 46055 | J96: 18)
A97: GAP/DISC/GENP/BV-01-C | B97: General Discovery procedure, finding General Discoverable device | D97: A | E97: 45873 | F97: 18) | H97: A | I97: =$B$4+90 -> 46055 | J97: 18)
A98: GAP/DISC/GENP/BV-02-C | B98: General Discovery procedure, finding Limited Discoverable device | D98: A | E98: 45873 | F98: 18) | H98: A | I98: =$B$4+90 -> 46055 | J98: 18)
A99: GAP/DISC/GENP/BV-03-C | B99: General Discovery procedure does not find Broadcast device | D99: A | E99: 45873 | F99: 18) | H99: A | I99: =$B$4+90 -> 46055 | J99: 18)
A100: GAP/DISC/GENP/BV-04-C | B100: General Discovery procedure does not find Undirected Connectable device | D100: A | E100: 45873 | F100: 18) | H100: A | I100: =$B$4+90 -> 46055 | J100: 18)
...

Sheet ATT-GATT
A1: Test Case Reference List
A2: Attribute Protocol Conformance
A3: Generic Attribute Profile Conformance | D3: Previous TS | E3: =Top!E22 -> GATT.TS.p28 | H3: TS | I3: =Top!G21 -> GATT.TS.p29 | J3: Available Date | K3: =rel_date -> 45965
A4: =Top!D22 -> Vol 3 Part G, 4.2–6.2 | D4: Previous ICS | E4: =Top!F22 -> GATT.ICS.p21 | H4: ICS | I4: =Top!H22 -> GATT.ICS.p22 | J4: Available Date | K4: =rel_date -> 45965
A5: Release date | B5: =rel_date -> 45965 | D5: Previous ICS | E5: =Top!F21 -> ATT.ICS.p14 | H5: ICS | I5: =Top!H21 -> ATT.ICS.p15 | J5: Available Date | K5: =rel_date -> 45965
A6: go to top | D6: Previously published test requirements | H6: Updated requirements through this release
A7: TCID*** | B7: Description | C7: TCRL Package Version Last Updated | D7: GATT TC Category | E7: Active Date | F7: Test System Alternatives | G7: Notes | H7: GATT TC Category | I7: Active Date | J7: Test System Alternatives | K7: Notes
A8: TCMT | B8: Test Case Mapping Table | C8: pkg101 | E8: 45873 | G8: TSE 24898 | I8: =$B$5+90 -> 46055 | K8: TSE 26905
A9: GATT ICS | B9: Implementation Conformance Statement | C9: pkg101 | E9: 45873 | G9: TSE 25608 | I9: =$B$5+90 -> 46055 | K9: TSEs 26905, 27527, 28196
A10: ATT ICS | B10: Implementation Conformance Statement | C10: pkg101 | E10: 45796 | I10: =$B$5+90 -> 46055 | K10: TSE 27575
A11: GATT/CL/GAC/BV-01-C | B11: Server Configuration - by Client | D11: B | E11: 45873 | F11: Member Defined | H11: B | I11: =$B$5+90 -> 46055 | J11: Member Defined
A12: GATT/CL/GAD/BV-01-C | B12: Discover All Primary Services - by Client | D12: B | E12: 45873 | F12: Member Defined | H12: B | I12: =$B$5+90 -> 46055 | J12: Member Defined
A13: GATT/CL/GAD/BV-02-C | B13: Discover Primary Service by Service UUID – by Client | D13: B | E13: 45873 | F13: Member Defined | H13: B | I13: =$B$5+90 -> 46055 | J13: Member Defined
A14: GATT/CL/GAD/BV-03-C | B14: Find Included Services - by Client | D14: B | E14: 45873 | F14: Member Defined | H14: B | I14: =$B$5+90 -> 46055 | J14: Member Defined
A15: GATT/CL/GAD/BV-04-C | B15: Discover All Characteristics of a Service - by Client | D15: B | E15: 45873 | F15: Member Defined | H15: B | I15: =$B$5+90 -> 46055 | J15: Member Defined
A16: GATT/CL/GAD/BV-05-C | B16: Discover Characteristics by UUID - by Client | D16: B | E16: 45873 | F16: Member Defined | H16: B | I16: =$B$5+90 -> 46055 | J16: Member Defined
A17: GATT/CL/GAD/BV-06-C | B17: Discover All Characteristic Descriptors - by Client | D17: B | E17: 45873 | F17: Member Defined | H17: B | I17: =$B$5+90 -> 46055 | J17: Member Defined
A18: GATT/CL/GAD/BV-07-C | B18: Discover Primary Services using SDP - by Client | C18: 2024-1 | D18: B | E18: 45873 | F18: Member Defined | H18: B | I18: =$B$5+90 -> 46055 | J18: Member Defined
A19: GATT/CL/GAD/BV-08-C | B19: Discover Services by UUID using SDP - by Client | C19: 2024-1 | D19: B | E19: 45873 | F19: Member Defined | H19: B | I19: =$B$5+90 -> 46055 | J19: Member Defined
A20: GATT/CL/GAI/BI-01-C | B20: Multiple Characteristic Value Indication Requests, Client | C20: 2021-1 | D20: B | E20: 45873 | F20: Member Defined | H20: B | I20: =$B$5+90 -> 46055 | J20: Member Defined
A21: GATT/CL/GAI/BV-01-C | B21: Confirm Characteristic Value Indication - by Client | C21: 2019-1 | D21: B | E21: 45873 | F21: Member Defined | H21: B | I21: =$B$5+90 -> 46055 | J21: Member Defined
A22: GATT/CL/GAN/BV-01-C | B22: Characteristic Value Notification - to Client | C22: 2019-1 | D22: B | E22: 45873 | F22: Member Defined | H22: B | I22: =$B$5+90 -> 46055 | J22: Member Defined
A23: GATT/CL/GAN/BV-02-C | B23: Handle Value Multiple Notification - to Client | C23: 2019-2 | D23: B | E23: 45873 | F23: Member Defined | H23: B | I23: =$B$5+90 -> 46055 | J23: Member Defined
A24: GATT/CL/GAR/BI-01-C | B24: Read Characteristic Value - Invalid Handle | D24: B | E24: 45873 | F24: Member Defined | H24: B | I24: =$B$5+90 -> 46055 | J24: Member Defined
A25: GATT/CL/GAR/BI-02-C | B25: Read Characteristic Value - Read Not Permitted | D25: B | E25: 45873 | F25: Member Defined | H25: B | I25: =$B$5+90 -> 46055 | J25: Member Defined
A26: GATT/CL/GAR/BI-03-C | B26: Read Characteristic Value - Insufficient Authorization | C26: 2019-1 | D26: B | E26: 45873 | F26: Member Defined | H26: B | I26: =$B$5+90 -> 46055 | J26: Member Defined
A27: GATT/CL/GAR/BI-04-C | B27: Read Characteristic Value - Insufficient Authentication | C27: 2019-1 | D27: B | E27: 45873 | F27: Member Defined | H27: B | I27: =$B$5+90 -> 46055 | J27: Member Defined
A28: GATT/CL/GAR/BI-05-C | B28: Read Characteristic Value - Insufficient Encryption Key Size | C28: 2019-1 | D28: B | E28: 45873 | F28: Member Defined | H28: B | I28: =$B$5+90 -> 46055 | J28: Member Defined
A29: GATT/CL/GAR/BI-06-C | B29: Read Using Characteristic UUID - Read Not Permitted | D29: B | E29: 45873 | F29: Member Defined | H29: B | I29: =$B$5+90 -> 46055 | J29: Member Defined
A30: GATT/CL/GAR/BI-07-C | B30: Read Using Characteristic UUID - Attribute Not Found | D30: B | E30: 45873 | F30: Member Defined | H30: B | I30: =$B$5+90 -> 46055 | J30: Member Defined
A31: GATT/CL/GAR/BI-09-C | B31: Read Using Characteristic UUID - Insufficient Authorization | C31: 2019-1 | D31: B | E31: 45873 | F31: Member Defined | H31: B | I31: =$B$5+90 -> 46055 | J31: Member Defined
A32: GATT/CL/GAR/BI-10-C | B32: Read Using Characteristic UUID - Insufficient Authentication | C32: 2019-1 | D32: B | E32: 45873 | F32: Member Defined | H32: B | I32: =$B$5+90 -> 46055 | J32: Member Defined
A33: GATT/CL/GAR/BI-11-C | B33: Read Using Characteristic UUID - Insufficient Encryption Key Size | C33: 2019-1 | D33: B | E33: 45873 | F33: Member Defined | H33: B | I33: =$B$5+90 -> 46055 | J33: Member Defined
A34: GATT/CL/GAR/BI-12-C | B34: Read Long Characteristic Value - Read Not Permitted | D34: B | E34: 45873 | F34: Member Defined | H34: B | I34: =$B$5+90 -> 46055 | J34: Member Defined
A35: GATT/CL/GAR/BI-13-C | B35: Read Long Characteristic Value - Invalid Offset | D35: B | E35: 45873 | F35: Member Defined | H35: B | I35: =$B$5+90 -> 46055 | J35: Member Defined
A36: GATT/CL/GAR/BI-14-C | B36: Read Long Characteristic Value - Invalid Handle | D36: B | E36: 45873 | F36: Member Defined | H36: B | I36: =$B$5+90 -> 46055 | J36: Member Defined
A37: GATT/CL/GAR/BI-15-C | B37: Read Long Characteristic Value - Insufficient Authorization | C37: 2019-1 | D37: B | E37: 45873 | F37: Member Defined | H37: B | I37: =$B$5+90 -> 46055 | J37: Member Defined
A38: GATT/CL/GAR/BI-16-C | B38: Read Long Characteristic Value - Insufficient Authentication | C38: 2019-1 | D38: B | E38: 45873 | F38: Member Defined | H38: B | I38: =$B$5+90 -> 46055 | J38: Member Defined
A39: GATT/CL/GAR/BI-17-C | B39: Read Long Characteristic Value - Insufficient Encryption Key Size | C39: 2019-1 | D39: B | E39: 45873 | F39: Member Defined | H39: B | I39: =$B$5+90 -> 46055 | J39: Member Defined
A40: GATT/CL/GAR/BI-18-C | B40: Read Multiple Characteristic Values - Read Not Permitted | D40: B | E40: 45873 | F40: Member Defined | H40: B | I40: =$B$5+90 -> 46055 | J40: Member Defined
A41: GATT/CL/GAR/BI-19-C | B41: Read Multiple Characteristic Values - Invalid Handle | D41: B | E41: 45873 | F41: Member Defined | H41: B | I41: =$B$5+90 -> 46055 | J41: Member Defined
A42: GATT/CL/GAR/BI-20-C | B42: Read Multiple Characteristic Values - Insufficient Authorization | C42: 2019-1 | D42: B | E42: 45873 | F42: Member Defined | H42: B | I42: =$B$5+90 -> 46055 | J42: Member Defined
A43: GATT/CL/GAR/BI-21-C | B43: Read Multiple Characteristic Values - Insufficient Authentication | C43: 2019-1 | D43: B | E43: 45873 | F43: Member Defined | H43: B | I43: =$B$5+90 -> 46055 | J43: Member Defined
A44: GATT/CL/GAR/BI-22-C | B44: Read Multiple Characteristic Values - Insufficient Encryption Key Size | C44: 2019-1 | D44: B | E44: 45873 | F44: Member Defined | H44: B | I44: =$B$5+90 -> 46055 | J44: Member Defined
A45: GATT/CL/GAR/BI-23-C to BI-33-C | B45: No longer used
A46: GATT/CL/GAR/BI-34-C | B46: Read Characteristic Value - Invalid Transport Access over BR/EDR | C46: 2019-1 | D46: B | E46: 45873 | F46: Member Defined | H46: B | I46: =$B$5+90 -> 46055 | J46: Member Defined
A47: GATT/CL/GAR/BI-35-C | B47: Read Characteristic Value - Invalid Transport Access over LE | C47: 2019-1 | D47: B | E47: 45873 | F47: Member Defined | H47: B | I47: =$B$5+90 -> 46055 | J47: Member Defined
A48: GATT/CL/GAR/BI-36-C | B48: Read Multiple Variable Length Characteristic Values - Read Not Permitted | C48: 2019-2 | D48: B | E48: 45873 | F48: Member Defined | H48: B | I48: =$B$5+90 -> 46055 | J48: Member Defined
A49: GATT/CL/GAR/BI-38-C | B49: Read Multiple Variable Length Characteristic Values - Invalid Handle | C49: 2019-2 | D49: B | E49: 45873 | F49: Member Defined | H49: B | I49: =$B$5+90 -> 46055 | J49: Member Defined
A50: GATT/CL/GAR/BI-40-C | B50: Read Multiple Variable Length Characteristic Values - Insufficient Authorization | C50: 2019-2 | D50: B | E50: 45873 | F50: Member Defined | H50: B | I50: =$B$5+90 -> 46055 | J50: Member Defined
A51: GATT/CL/GAR/BI-42-C | B51: Read Multiple Variable Length Characteristic Values - Insufficient Authentication | C51: 2019-2 | D51: B | E51: 45873 | F51: Member Defined | H51: B | I51: =$B$5+90 -> 46055 | J51: Member Defined
A52: GATT/CL/GAR/BI-44-C | B52: Read Multiple Variable Length Characteristic Values - Insufficient Encryption Key Size | C52: 2019-2 | D52: B | E52: 45873 | F52: Member Defined | H52: B | I52: =$B$5+90 -> 46055 | J52: Member Defined
A53: GATT/CL/GAR/BV-01-C | B53: Read Characteristic Value - by Client | C53: 2019-1 | D53: B | E53: 45873 | F53: Member Defined | H53: B | I53: =$B$5+90 -> 46055 | J53: Member Defined
A54: GATT/CL/GAR/BV-03-C | B54: Read Using Characteristic UUID - by Client | C54: 2019-1 | D54: B | E54: 45873 | F54: Member Defined | H54: B | I54: =$B$5+90 -> 46055 | J54: Member Defined
A55: GATT/CL/GAR/BV-04-C | B55: Read Long Characteristic Value - by Client | C55: 2019-1 | D55: B | E55: 45873 | F55: Member Defined | H55: B | I55: =$B$5+90 -> 46055 | J55: Member Defined
A56: GATT/CL/GAR/BV-05-C | B56: Read Multiple Characteristic Values - by Client | C56: 2019-1 | D56: B | E56: 45873 | F56: Member Defined | H56: B | I56: =$B$5+90 -> 46055 | J56: Member Defined
A57: GATT/CL/GAR/BV-06-C | B57: Read Characteristic Descriptor – by Client | C57: 2019-1 | D57: B | E57: 45873 | F57: Member Defined | H57: B | I57: =$B$5+90 -> 46055 | J57: Member Defined
... A66: GATT/CL/GAS/BV-05-C | B66: Enabling the Features in Client Supported Features – Multiple Handle Value Notifications | C66: 2019-2 | D66: B | E66: 45873 | F66: Member Defined | H66: B | I66: =$B$5+90 -> 46055 | J66: Member Defined
A67: GATT/CL/GAT/BV-01-C | B67: Read Characteristic Value - Server Timeout | D67: B | E67: 45873 | F67: Member Defined | H67: B | I67: =$B$5+90 -> 46055 | J67: Member Defined
A68: GATT/CL/GAT/BV-02-C | B68: Write Characteristic Value - Server Timeout | D68: B | E68: 45873 | F68: Member Defined | H68: B | I68: =$B$5+90 -> 46055 | J68: Member Defined
A69: GATT/CL/GAT/BV-03-C | B69: Read Multiple Variable Length Characteristic Values - Server Timeout | C69: 2019-2 | D69: B | E69: 45873 | F69: Member Defined | H69: B | I69: =$B$5+90 -> 46055 | J69: Member Defined
A70: GATT/CL/GAW/BI-02-C | B70: Write Characteristic Value - Invalid Handle | D70: B | E70: 45873 | F70: Member Defined | H70: B | I70: =$B$5+90 -> 46055 | J70: Member Defined
A71: GATT/CL/GAW/BI-03-C | B71: Write Characteristic Value - Write Not Permitted | D71: B | E71: 45873 | F71: Member Defined | H71: B | I71: =$B$5+90 -> 46055 | J71: Member Defined
A72: GATT/CL/GAW/BI-04-C | B72: Write Characteristic Value - Insufficient Authorization | C72: 2019-1 | D72: B | E72: 45873 | F72: Member Defined | H72: B | I72: =$B$5+90 -> 46055 | J72: Member Defined
A73: GATT/CL/GAW/BI-05-C | B73: Write Characteristic Value - Insufficient Authentication | C73: 2019-1 | D73: B | E73: 45873 | F73: Member Defined | H73: B | I73: =$B$5+90 -> 46055 | J73: Member Defined
A74: GATT/CL/GAW/BI-06-C | B74: Write Characteristic Value - Insufficient Encryption Key Size | C74: 2019-1 | D74: B | E74: 45873 | F74: Member Defined | H74: B | I74: =$B$5+90 -> 46055 | J74: Member Defined
A75: GATT/CL/GAW/BI-07-C | B75: Write Long Characteristic Value - Invalid Handle | D75: B | E75: 45873 | F75: Member Defined | H75: B | I75: =$B$5+90 -> 46055 | J75: Member Defined
A76: GATT/CL/GAW/BI-08-C | B76: Write Long Characteristic Value - Write Not Permitted | D76: B | E76: 45873 | F76: Member Defined | H76: B | I76: =$B$5+90 -> 46055 | J76: Member Defined
A77: GATT/CL/GAW/BI-09-C | B77: Write Long Characteristic Value - Invalid Offset | C77: 2021-1 | D77: B | E77: 45873 | F77: Member Defined | H77: B | I77: =$B$5+90 -> 46055 | J77: Member Defined
A78: GATT/CL/GAW/BI-11-C | B78: Write Long Characteristic Value - Insufficient Authorization | C78: 2019-1 | D78: B | E78: 45873 | F78: Member Defined | H78: B | I78: =$B$5+90 -> 46055 | J78: Member Defined
A79: GATT/CL/GAW/BI-12-C | B79: Write Long Characteristic Value - Insufficient Authentication | C79: 2019-1 | D79: B | E79: 45873 | F79: Member Defined | H79: B | I79: =$B$5+90 -> 46055 | J79: Member Defined
A80: GATT/CL/GAW/BI-13-C | B80: Write Long Characteristic Value - Insufficient Encryption Key Size | C80: 2019-1 | D80: B | E80: 45873 | F80: Member Defined | H80: B | I80: =$B$5+90 -> 46055 | J80: Member Defined
A81: GATT/CL/GAW/BI-14-C to BI-31-C | B81: No longer used
A82: GATT/CL/GAW/BI-32-C | B82: Cancel Reliable Write Characteristic - by Client | C82: 2019-1 | D82: B | E82: 45873 | F82: Member Defined | H82: B | I82: =$B$5+90 -> 46055 | J82: Member Defined
A83: GATT/CL/GAW/BI-33-C to BI-34-C | B83: No longer used | C83: 2025-2 | G83: TSE 24898 (deleted TC)
A84: GATT/CL/GAW/BI-35-C to BI-37-C | B84: No longer used
A85: GATT/CL/GAW/BV-01-C | B85: Write without Response - by Client | C85: 2019-1 | D85: B | E85: 45873 | F85: Member Defined | H85: B | I85: =$B$5+90 -> 46055 | J85: Member Defined
A86: GATT/CL/GAW/BV-02-C | B86: Write without Response with Authentication - by Client | C86: 2019-1 | D86: B | E86: 45873 | F86: Member Defined | H86: B | I86: =$B$5+90 -> 46055 | J86: Member Defined
A87: GATT/CL/GAW/BV-03-C | B87: Write Characteristic Value - by Client | C87: 2019-1 | D87: B | E87: 45873 | F87: Member Defined | H87: B | I87: =$B$5+90 -> 46055 | J87: Member Defined
A88: GATT/CL/GAW/BV-05-C | B88: Write Long Characteristic Value - by Client | C88: 2019-1 | D88: B | E88: 45873 | F88: Member Defined | H88: B | I88: =$B$5+90 -> 46055 | J88: Member Defined
A89: GATT/CL/GAW/BV-06-C | B89: Characteristic Value Reliable Write - by Client | C89: 2019-1 | D89: B | E89: 45873 | F89: Member Defined | H89: B | I89: =$B$5+90 -> 46055 | J89: Member Defined
A90: GATT/CL/GAW/BV-08-C | B90: Write Characteristic Descriptor – by Client | C90: 2019-1 | D90: B | E90: 45873 | F90: Member Defined | H90: B | I90: =$B$5+90 -> 46055 | J90: Member Defined
A91: GATT/CL/GAW/BV-09-C | B91: Write Long Characteristic Descriptors - by Client | C91: 2019-1 | D91: B | E91: 45873 | F91: Member Defined | H91: B | I91: =$B$5+90 -> 46055 | J91: Member Defined
A92: GATT/CL/GAW/BV-10-C | B92: No longer used | C92: 2021-1
A93: GATT/CL/GPA/BV-01-C to BV-08-C | B93: No longer used | C93: 2019-1
A94: GATT/CL/GPA/BV-11-C | B94: Characteristic Aggregate Format - by Client | D94: B | E94: 45873 | F94: Member Defined | H94: B | I94: =$B$5+90 -> 46055 | J94: Member Defined
A95: GATT/CL/GPA/BV-12-C | B95: Characteristic Format Descriptors - from Client | D95: B | E95: 45873 | F95: Member Defined | H95: B | I95: =$B$5+90 -> 46055 | J95: Member Defined
A96: GATT/CL/GPM/BV-07-C | B96: Multiple Client Read Requests on Unsynchronized Database with Robust Caching, ATT over BR/EDR and ATT over LE | C96: 2021-1 | D96: B | E96: 45873 | F96: Member Defined | H96: B | I96: =$B$5+90 -> 46055 | J96: Member Defined
A97: GATT/CL/GPM/BV-08-C | B97: Multiple Client Read Requests on Unsynchronized Database with Robust Caching, ATT over BR/EDR and EATT over BR/EDR | C97: 2021-1 | D97: B | E97: 45873 | F97: Member Defined | H97: B | I97: =$B$5+90 -> 46055 | J97: Member Defined
A98: GATT/CL/GPM/BV-09-C | B98: Multiple Client Read Requests on Unsynchronized Database with Robust Caching, ATT over BR/EDR and EATT over LE | C98: 2021-1 | D98: B | E98: 45873 | F98: Member Defined | H98: B | I98: =$B$5+90 -> 46055 | J98: Member Defined
A99: GATT/CL/GPM/BV-10-C | B99: Multiple Client Read Requests on Unsynchronized Database with Robust Caching, ATT over LE and EATT over BR/EDR | C99: 2021-1 | D99: B | E99: 45873 | F99: Member Defined | H99: B | I99: =$B$5+90 -> 46055 | J99: Member Defined
A100: GATT/CL/GPM/BV-11-C | B100: Multiple Client Read Requests on Unsynchronized Database with Robust Caching, ATT over LE and EATT over BR/EDR | C100: 2021-1 | D100: B | E100: 45873 | F100: Member Defined | H100: B | I100: =$B$5+90 -> 46055 | J100: Member Defined
A101: GATT/CL/GPM/BV-12-C | B101: Multiple Client Read Requests on Unsynchronized Database with Robust Caching, EATT over BR/EDR and EATT over LE | C101: 2021-1 | D101: B | E101: 45873 | F101: Member Defined | H101: B | I101: =$B$5+90 -> 46055 | J101: Member Defined
A102: GATT/SR/GAC/BI-01-C | B102: Exchange MTU – EATT bearer over LE | C102: 2021-1 | D102: B | E102: 45873 | F102: Member Defined | H102: B | I102: =$B$5+90 -> 46055 | J102: Member Defined
A103: GATT/SR/GAC/BI-02-C | B103: Exchange MTU – ATT bearer over BR/EDR | C103: 2021-1 | D103: B | E103: 45873 | F103: Member Defined | H103: B | I103: =$B$5+90 -> 46055 | J103: Member Defined
A104: GATT/SR/GAC/BI-03-C | B104: Exchange MTU – EATT bearer over BR/EDR | C104: 2021-1 | D104: B | E104: 45873 | F104: Member Defined | H104: B | I104: =$B$5+90 -> 46055 | J104: Member Defined
A105: GATT/SR/GAC/BV-01-C | B105: Server Configuration - of Server | D105: B | E105: 45873 | F105: Member Defined | H105: B | I105: =$B$5+90 -> 46055 | J105: Member Defined
A106: GATT/SR/GAD/BV-01-C | B106: Discover All Primary Services - from Server | D106: B | E106: 45873 | F106: Member Defined | H106: B | I106: =$B$5+90 -> 46055 | J106: Member Defined
A107: GATT/SR/GAD/BV-02-C | B107: Discover Primary Service by Service UUID - from Server | D107: B | E107: 45873 | F107: Member Defined | H107: B | I107: =$B$5+90 -> 46055 | J107: Member Defined
A108: GATT/SR/GAD/BV-03-C | B108: Find Included Services - from Server | D108: B | E108: 45873 | F108: Member Defined | H108: B | I108: =$B$5+90 -> 46055 | J108: Member Defined
...

Sheet HCI
A1: Test Case Reference List
A2: =Top!B15 & " Conformance" -> Host Controller Interface Conformance | D2: Previous TS | E2: =Top!E15 -> HCI.TS.p37 | H2: TS | I2: =Top!G15 -> HCI.TS.p38 | J2: Available Date | K2: =rel_date -> 45965
A3: =Top!D15 -> Vol 2 Part E, 4.2–6.2 | D3: Previous ICS | E3: =Top!F15 -> HCI.ICS.p32 | H3: ICS | I3: =Top!H15 -> HCI.ICS.p33 | J3: Available Date | K3: =rel_date -> 45965
A4: =Top!A2 -> Release Date | B4: =rel_date -> 45965
D5: Previous ICS | E5: =Top!F16 -> UHCI.ICS.p2 | H5: ICS | I5: =Top!H16 -> UHCI.ICS.p3 | J5: Available Date | K5: =rel_date -> 45965
A6: go to top | D6: Previously published test requirements | H6: Updated requirements through this release
A7: TCID*** | B7: Description | C7: TCRL Package Version Last Updated | D7: TC Category | E7: Active Date | F7: Test System Alternatives | G7: Notes | H7: TC Category | I7: Active Date | J7: Test System Alternatives | K7: Notes
A8: TCMT | B8: Test Case Mapping Table | C8: pkg101 | E8: 45873 | G8: RPA TSEs 23560, 24671, 25962, 26044, 26510, 26919 | I8: =$B$4+90 -> 46055 | K8: TSE 27934 (SCI; plus TI27749, TI27898) TSEs 26648, 27130, 27140, 27231, 27253, 27343, 27510, 27544, 27733
A9: HCI ICS | B9: HCI Implementation Conformance Statement | C9: pkg101 | E9: 45873 | G9: RPA | I9: =$B$4+90 -> 46055 | K9: TSE 27886 (LETM) TSE 27934 (SCI) TSEs 27161, 27224, 27703, 27850
A10: UHCI ICS | B10: Upper HCI Implementation Conformance Statement | C10: pkg101 | E10: 45873 | G10: TSE 27176 | I10: =$B$4+90 -> 46055 | K10: TSE 27886 (LETM)
A11: HCI/AEN/BI-01-C | B11: Generate DH Key Error With Invalid Point, v5.4 | C11: 2024-2 | D11: A | E11: 45873 | F11: 15), 16) | H11: A | I11: =$B$4+90 -> 46055 | J11: 15), 16), 20)
A12: HCI/AEN/BI-02-C | B12: Generate DH Key Error With Invalid Point, v6.0 | C12: 2024-2 | D12: A | E12: 45873 | F12: 15) | H12: A | I12: =$B$4+90 -> 46055 | J12: 15), 20)
A13: HCI/AEN/BV-01-C | B13: Link Key Commands | D13: A | E13: 45873 | F13: 15) | H13: A | I13: =$B$4+90 -> 46055 | J13: 15)
A14: HCI/AEN/BV-02-C | B14: Reading All Link Keys | D14: A | E14: 45873 | F14: 15) | H14: A | I14: =$B$4+90 -> 46055 | J14: 15)
A15: HCI/AEN/BV-03-C | B15: Reading Single Link Key | D15: A | E15: 45873 | F15: 15) | H15: A | I15: =$B$4+90 -> 46055 | J15: 15)
A16: HCI/AEN/BV-04-C | B16: Link Key Commands – IUT Returns All Zero Link Key | D16: A | E16: 45873 | F16: 15) | H16: A | I16: =$B$4+90 -> 46055 | J16: 15)
A17: HCI/AEN/BV-05-C | B17: Read Local OOB Extended Data Command, test unique values | D17: A | E17: 45873 | F17: 15) | H17: A | I17: =$B$4+90 -> 46055 | J17: 15)
A18: HCI/AEN/BV-06-C | B18: Public Keys | D18: A | E18: 45873 | F18: 15), 16) | H18: A | I18: =$B$4+90 -> 46055 | J18: 15), 16)
A19: HCI/AEN/BV-07-C | B19: Generate DH Keys | D19: A | E19: 45873 | F19: 15), 16) | H19: A | I19: =$B$4+90 -> 46055 | J19: 15), 16)
A20: HCI/AEN/BV-08-C | B20: Generate Debug Keys | C20: 2018-2 | D20: A | E20: 45873 | F20: 15), 16) | H20: A | I20: =$B$4+90 -> 46055 | J20: 15), 16)
A21: HCI/AEN/BV-09-C | B21: Read Local OOB Extended Data command, host bits not set | C21: 2025-1 | D21: B | E21: 45873 | F21: Member Defined | H21: B | I21: =$B$4+90 -> 46055 | J21: Member Defined
A22: HCI/BIS/BI-01-C | B22: Ignoring RFU Bits in HCI ISO Data Packets, BIS | C22: 2021-1 | D22: A | E22: 45873 | F22: 15), 16) | H22: A | I22: =$B$4+90 -> 46055 | J22: 15), 16)
A23: HCI/BIS/BI-02-C | B23: Broadcast Isochronous Stream, Synchronized Receiver, Reject Invalid Commands | C23: 2021-1 | D23: A | E23: 45873 | F23: 15), 16) | H23: A | I23: =$B$4+90 -> 46055 | J23: 15), 16)
A24: HCI/BIS/BI-06-C | B24: Broadcast Isochronous Stream Using Non-Test Command, Invalid BIG Parameters | C24: 2024-2 | D24: A | E24: 45873 | F24: 15), 16) | H24: A | I24: =$B$4+90 -> 46055 | J24: 15), 16), 20)
A25: HCI/BIS/BI-07-C | B25: Broadcast Isochronous Stream Using Non-Test Command, Invalid Transport Latency | C25: 2025-2 | D25: A | E25: 45873 | F25: 15), 16) | G25: TSE 27226 | H25: A | I25: =$B$4+90 -> 46055 | J25: 15), 16)
A26: HCI/BIS/BI-08-C | B26: Invalid LE BIG Create Sync Parameters and LE ISO Remove Data Path behavior, BIS | C26: 2025-1 | D26: A | E26: 45873 | F26: 15) | H26: A | I26: =$B$4+90 -> 46055 | J26: 15)
A27: HCI/BIS/BI-09-C | B27: Invalid LE BIG Create Sync Encryption Parameter, BIS | C27: 2022-2 | D27: A | E27: 45873 | F27: 15), 16) | H27: A | I27: =$B$4+90 -> 46055 | J27: 15), 16)
A28: HCI/BIS/BI-10-C | B28: LE Create BIG, Framed, Unsegmented Mode Unsupported | C28: 2025-1 | D28: A | E28: 45873 | F28: 15) | H28: A | I28: =$B$4+90 -> 46055 | J28: 15)
A29: HCI/BIS/BI-11-C | B29: Broadcast Isochronous Stream Using Non-Test Command, Invalid BIG Parameters | C29: 2024-2 | D29: A | E29: 45873 | F29: 15) | H29: A | I29: =$B$4+90 -> 46055 | J29: 15)
A30: HCI/BIS/BI-12-C | B30: Broadcast Isochronous Stream, Broadcaster, HCI Read/Write Authenticated Payload Timeout error | C30: pkg101 | D30: A | E30: 45873 | F30: 15) | H30: A | I30: =$B$4+90 -> 46055 | J30: 15) | K30: TSE 26648
A31: HCI/BIS/BI-13-C | B31: No longer used | C31: pkg101 | D31: A | E31: 45873 | F31: 15) | K31: TSE 26648 (deleted TC)
A32: HCI/BIS/BI-14-C | B32: Broadcast Isochronous Stream, Synchronized Receiver, HCI Read/Write Authenticated Payload Timeout error | C32: pkg101 | D32: A | E32: 45873 | F32: 15) | H32: A | I32: =$B$4+90 -> 46055 | J32: 15) | K32: TSE 26648
A33: HCI/BIS/BI-15-C | B33: No longer used | C33: pkg101 | D33: A | E33: 45873 | F33: 15) | K33: TSE 26648 (deleted TC)
A34: HCI/BIS/BI-16-C | B34: Reporting Failure to Sync to BIS | C34: 2024-2 | D34: A | E34: 45873 | F34: 15) | H34: A | I34: =$B$4+90 -> 46055 | J34: 15)
A35: HCI/BIS/BV-01-C | B35: Broadcast Isochronous Stream Using Non-Test Command, all PHYs | C35: 2022-2 | D35: A | E35: 45873 | F35: 15), 16) | H35: A | I35: =$B$4+90 -> 46055 | J35: 15), 16)
A36: HCI/BIS/BV-02-C | B36: Broadcast Isochronous Stream Using Non-Test Command, not all PHYs | C36: 2022-2 | D36: A | E36: 45873 | F36: 15), 16) | H36: A | I36: =$B$4+90 -> 46055 | J36: 15), 16)
A37: HCI/BIS/BV-03-C | B37: Broadcast Isochronous Stream Using Test Command, Time_Offset | C37: 2021-1 | D37: A | E37: 45873 | F37: 15), 16) | H37: A | I37: =$B$4+90 -> 46055 | J37: 15), 16)
A38: HCI/BIS/BV-04-C | B38: Broadcast Isochronous Stream, Invalid LE Read ISO TX Sync Parameters | C38: 2021-1 | D38: A | E38: 45873 | F38: 15), 16) | H38: A | I38: =$B$4+90 -> 46055 | J38: 15), 16)
A39: HCI/BIS/BV-05-C | B39: Broadcast Isochronous Stream, Time_Stamp, Isochronous Broadcaster | C39: 2021-1 | D39: A | E39: 45873 | F39: 15), 16) | H39: A | I39: =$B$4+90 -> 46055 | J39: 15), 16)
A40: HCI/BIS/BV-06-C | B40: Broadcast Isochronous Stream, Time_Stamp Optional, Synchronized Receiver | C40: 2023-1 | D40: A | E40: 45873 | F40: 15), 16) | H40: A | I40: =$B$4+90 -> 46055 | J40: 15), 16)
A41: HCI/BIS/BV-07-C | B41: Broadcast Isochronous Stream, Time_Stamp Mandatory, Synchronized Receiver | C41: 2023-1 | D41: A | E41: 45873 | F41: 15), 16) | H41: A | I41: =$B$4+90 -> 46055 | J41: 15), 16)
A42: HCI/BIS/BV-08-C | B42: Number of Completed Packets Event after Sending data in a Broadcaster | C42: 2022-2 | D42: A | E42: 45873 | F42: 15), 16) | H42: A | I42: =$B$4+90 -> 46055 | J42: 15), 16)
A43: HCI/BIS/BV-09-C | B43: Reject creating a BIG when the IUT does not support a BIG created from a Periodic Advertising with Responses, LE Create BIG | C43: 2024-2 | D43: A | E43: 45873 | F43: 15) | H43: A | I43: =$B$4+90 -> 46055 | J43: 15)
A44: HCI/BIS/BV-10-C | B44: Reject creating a BIG when the IUT does not support a BIG created from a Periodic Advertising with Responses, LE Create BIG Test | C44: 2024-2 | D44: A | E44: 45873 | F44: 15) | H44: A | I44: =$B$4+90 -> 46055 | J44: 15)
A45: HCI/BIS/BV-11-C | B45: Broadcast Isochronous Stream testing overlength data on the LE Coded PHY | C45: 2024-2 | D45: A | E45: 45873 | F45: 15) | H45: A | I45: =$B$4+90 -> 46055 | J45: 15)
A46: HCI/CCI/BI-01-C to -06-C | B46: No longer used | C46: 2023-1
A47: HCI/CCO/BI-01-C | B47: Resolving List Commands fail when list in use | C47: 2019-1 | D47: A | E47: 45873 | F47: 15), 16) | H47: A | I47: =$B$4+90 -> 46055 | J47: 15), 16), 20)
A48: HCI/CCO/BI-02-C | B48: Resolving List Commands fail when list in use | C48: 2019-1 | D48: A | E48: 45873 | F48: 15), 16) | H48: A | I48: =$B$4+90 -> 46055 | J48: 15), 16), 20)
A49: HCI/CCO/BI-03-C | B49: Resolving List Commands fail when list in use | C49: 2019-1 | D49: A | E49: 45873 | F49: 15), 16) | H49: A | I49: =$B$4+90 -> 46055 | J49: 15), 16), 20)
A50: HCI/CCO/BI-04-C | B50: Resolving List Commands fail when list in use | C50: 2019-1 | D50: A | E50: 45873 | F50: 15), 16) | H50: A | I50: =$B$4+90 -> 46055 | J50: 15), 16), 20)
A51: HCI/CCO/BI-05-C | B51: Resolving List Commands fail when list in use | C51: 2019-1 | D51: A | E51: 45873 | F51: 15), 16) | H51: A | I51: =$B$4+90 -> 46055 | J51: 15), 16), 20)
A52: HCI/CCO/BI-06-C | B52: LE Enhanced Read Transmit Power Level – Invalid Connection Handle | C52: 2019-2 | D52: A | E52: 45873 | F52: 15), 16) | H52: A | I52: =$B$4+90 -> 46055 | J52: 15), 16), 20)
A53: HCI/CCO/BI-07-C | B53: LE Enhanced Read Transmit Power Level – Invalid PHY | C53: 2019-2 | D53: A | E53: 45873 | F53: 15), 16) | H53: A | I53: =$B$4+90 -> 46055 | J53: 15), 16)
A54: HCI/CCO/BI-08-C | B54: LE Read Remote Transmit Power Level – Invalid Connection Handle | C54: 2019-2 | D54: A | E54: 45873 | F54: 15), 16) | H54: A | I54: =$B$4+90 -> 46055 | J54: 15), 16)
A55: HCI/CCO/BI-09-C | B55: LE Read Remote Transmit Power Level – Invalid PHY | C55: 2019-2 | D55: A | E55: 45873 | F55: 15), 16) | H55: A | I55: =$B$4+90 -> 46055 | J55: 15), 16)
A56: HCI/CCO/BI-10-C | B56: LE Set Path Loss Reporting Parameters – Invalid Connection Handle | C56: 2019-2 | D56: A | E56: 45873 | F56: 15), 16) | H56: A | I56: =$B$4+90 -> 46055 | J56: 15), 16)
A57: HCI/CCO/BI-11-C | B57: LE Set Path Loss Reporting Enable – Invalid Connection Handle | C57: 2019-2 | D57: A | E57: 45873 | F57: 15), 16) | H57: A | I57: =$B$4+90 -> 46055 | J57: 15), 16)
A58: HCI/CCO/BI-12-C | B58: LE Set Transmit Power Reporting Enable – Invalid Connection Handle | C58: 2019-2 | D58: A | E58: 45873 | F58: 15), 16) | H58: A | I58: =$B$4+90 -> 46055 | J58: 15), 16)
... A63: HCI/CCO/BI-17-C | B63: Validate Unsupported Packet Types are Not Accepted, Change Connection Packet Type, 5-slot | C63: 2019-2 | D63: A | E63: 45873 | F63: 15) | H63: A | I63: =$B$4+90 -> 46055 | J63: 15)
A64: HCI/CCO/BI-18-C | B64: Error Response for Commands not supporting all transports, Command Complete Response, Read Authenticated Payload Timeout, BR/EDR | C64: pkg101 | D64: B | E64: 45873 | F64: Member Defined | H64: B | I64: =$B$4+90 -> 46055 | J64: Member Defined | K64: TSE 27544
A65: HCI/CCO/BI-19-C | B65: Error Response for Commands not supporting all transports, Command Complete Response, Read Authenticated Payload Timeout, LE | C65: pkg101 | D65: A | E65: 45873 | F65: 15) | H65: A | I65: =$B$4+90 -> 46055 | J65: 15) | K65: TSE 27544
A66: HCI/CCO/BI-20-C | B66: Error Response for Commands not supporting all transports, Command Complete Response, Read Link Quality, BR/EDR | C66: pkg101 | D66: B | E66: 45873 | F66: Member Defined | H66: B | I66: =$B$4+90 -> 46055 | J66: Member Defined | K66: TSE 27544
A67: HCI/CCO/BI-21-C | B67: Error Response for Commands not supporting all transports, Command Complete Response, Read Link Quality, AMP | C67: pkg101 | D67: B | E67: 45873 | F67: Member Defined | H67: B | I67: =$B$4+90 -> 46055 | J67: Member Defined | K67: TSE 27544
A68: HCI/CCO/BI-22-C | B68: Error Response for Commands not supporting all transports, Command Complete Response, Read Link Supervision Timeout, BR/EDR | C68: pkg101 | D68: B | E68: 45873 | F68: Member Defined | H68: B | I68: =$B$4+90 -> 46055 | J68: Member Defined | K68: TSE 27544
A69: HCI/CCO/BI-23-C | B69: Error Response for Commands not supporting all transports, Command Status Response, Read Remote Version Information, BR/EDR | C69: pkg101 | D69: B | E69: 45873 | F69: Member Defined | H69: B | I69: =$B$4+90 -> 46055 | J69: Member Defined | K69: TSE 27544
A70: HCI/CCO/BI-24-C | B70: Error Response for Commands not supporting all transports, Command Status Response, Read Remote Version Information, LE | C70: pkg101 | D70: A | E70: 45873 | F70: 15) | H70: A | I70: =$B$4+90 -> 46055 | J70: 15) | K70: TSE 27544
A71: HCI/CCO/BI-25-C | B71: Error Response for Commands not supporting all transports, Command Complete Response, Read RSSI, BR/EDR | C71: pkg101 | D71: B | E71: 45873 | F71: Member Defined | H71: B | I71: =$B$4+90 -> 46055 | J71: Member Defined | K71: TSE 27544
A72: HCI/CCO/BI-26-C | B72: Error Response for Commands not supporting all transports, Command Complete Response, Read RSSI, AMP | C72: pkg101 | D72: B | E72: 45873 | F72: Member Defined | H72: B | I72: =$B$4+90 -> 46055 | J72: Member Defined | K72: TSE 27544
A73: HCI/CCO/BI-27-C | B73: Error Response for Commands not supporting all transports, Command Complete Response, Read RSSI, LE | C73: pkg101 | D73: A | E73: 45873 | F73: 15) | H73: A | I73: =$B$4+90 -> 46055 | J73: 15) | K73: TSE 27544
A74: HCI/CCO/BI-28-C | B74: Error Response for Commands not supporting all transports, Command Complete Response, Read Transmit Power Level, BR/EDR | C74: pkg101 | D74: B | E74: 45873 | F74: Member Defined | H74: B | I74: =$B$4+90 -> 46055 | J74: Member Defined | K74: TSE 27544
A75: HCI/CCO/BI-29-C | B75: Error Response for Commands not supporting all transports, Command Complete Response, Read Transmit Power Level, LE | C75: pkg101 | D75: A | E75: 45873 | F75: 15) | H75: A | I75: =$B$4+90 -> 46055 | J75: 15) | K75: TSE 27544
... A78: HCI/CCO/BI-32-C | B78: Error Response for Commands not supporting all transports, Command Complete Response, Write Link Supervision Timeout, BR/EDR | C78: pkg101 | D78: B | E78: 45873 | F78: Member Defined | H78: B | I78: =$B$4+90 -> 46055 | J78: Member Defined | K78: TSE 27544
A79: HCI/CCO/BI-33-C | B79: Invalid LE Set Periodic Advertising Data Parameters | C79: 2021-1 | D79: A | E79: 45873 | F79: 15), 16) | H79: A | I79: =$B$4+90 -> 46055 | J79: 15), 16), 20)
A80: HCI/CCO/BI-34-C | B80: Invalid LE Set Periodic Advertising Enable Parameters, Periodic Advertising ADI Not Supported | C80: 2021-1 | D80: A | E80: 45873 | F80: 15), 16) | H80: A | I80: =$B$4+90 -> 46055 | J80: 15), 16)
A81: HCI/CCO/BI-35-C | B81: Invalid Set Min Encryption Key Size Parameters | C81: 2021-1 | D81: A | E81: 45873 | F81: 15) | H81: A | I81: =$B$4+90 -> 46055 | J81: 15)
A82: HCI/CCO/BI-36-C | B82: Invalid Subrate Parameters – HCI_LE_Subrate_Request | C82: 2021-1 | D82: A | E82: 45873 | F82: 15), 16) | H82: A | I82: =$B$4+90 -> 46055 | J82: 15), 16)
A83: HCI/CCO/BI-37-C | B83: Invalid Subrate Parameters – HCI_LE_Set_Default_Subrate | C83: 2021-1 | D83: A | E83: 45873 | F83: 15), 16) | H83: A | I83: =$B$4+90 -> 46055 | J83: 15), 16)
A84: HCI/CCO/BI-38-C | B84: Invalid Connection CTE Request Enable Parameters | C84: 2021-1 | D84: A | E84: 45873 | F84: 15), 16) | H84: A | I84: =$B$4+90 -> 46055 | J84: 15), 16)
A85: HCI/CCO/BI-39-C | B85: Invalid Write Authenticated Payload Timeout Parameters | C85: 2021-1 | D85: A | E85: 45873 | F85: 15), 16) | H85: A | I85: =$B$4+90 -> 46055 | J85: 15), 16)
A86: HCI/CCO/BI-40-C | B86: LE Set Data Length, Invalid Parameters | C86: 2021-1 | D86: A | E86: 45873 | F86: 15), 16) | H86: A | I86: =$B$4+90 -> 46055 | J86: 15), 16), 20)
A87: HCI/CCO/BI-42-C | B87: Configure Data Path | C87: 2021-1 | D87: A | E87: 45873 | F87: 15), 16) | H87: A | I87: =$B$4+90 -> 46055 | J87: 15), 16)
A88: HCI/CCO/BI-43-C | B88: LE Read Channel Map – Reject Invalid Handle | C88: 2021-1 | D88: A | E88: 45873 | F88: 15), 16) | H88: A | I88: =$B$4+90 -> 46055 | J88: 15), 16), 20)
A89: HCI/CCO/BI-44-C | B89: Reject Setting Host Controlled FeatureSet Bit, Unsupported Feature on Controller, FeatureSet Bit 32 (Connected Isochronous Streams (Host Support)) | C89: 2021-1 | D89: A | E89: 45873 | F89: 15), 16) | H89: A | I89: =$B$4+90 -> 46055 | J89: 15), 16)
A90: HCI/CCO/BI-45-C | B90: Reject Setting Host Controlled FeatureSet Bit, Unsupported Feature on Controller, FeatureSet Bit 37 (Connection Subrating (Host Support)) | C90: 2021-1 | D90: A | E90: 45873 | F90: 15), 16) | H90: A | I90: =$B$4+90 -> 46055 | J90: 15), 16)
... A93: HCI/CCO/BI-48-C | B93: LE Add Device To Resolving List – Existing Peer IRK Entry | C93: 2021-1 | D93: A | E93: 45873 | F93: 15), 16) | H93: A | I93: =$B$4+90 -> 46055 | J93: 15), 16), 20)
A94: HCI/CCO/BI-49-C | B94: No longer used | C94: 2021-2
A95: HCI/CCO/BI-50-C | B95: LE Add Device To Resolving List – No Space Available, Scanner | C95: 2024-1 | D95: A | E95: 45873 | F95: 15), 16) | H95: A | I95: =$B$4+90 -> 46055 | J95: 15), 16)
A96: HCI/CCO/BI-51-C | B96: Reject Invalid Create Connection Command, 0x01, N/A | C96: 2021-1 | D96: A | E96: 45873 | F96: 15), 16) | H96: A | I96: =$B$4+90 -> 46055 | J96: 15), 16), 20)
A97: HCI/CCO/BI-52-C | B97: Reject Invalid Create Connection Command, 0x03, 0x00 | C97: 2021-1 | D97: A | E97: 45873 | F97: 15), 16) | H97: A | I97: =$B$4+90 -> 46055 | J97: 15), 16), 20)
A98: HCI/CCO/BI-53-C | B98: Reject Invalid Create Connection Command, 0x03, 0x01 | C98: 2021-1 | D98: A | E98: 45873 | F98: 15), 16) | H98: A | I98: =$B$4+90 -> 46055 | J98: 15), 16), 20)
A99: HCI/CCO/BI-54-C | B99: Reject Invalid Extended Create Connection Command, 0x01, N/A | C99: 2021-1 | D99: A | E99: 45873 | F99: 15), 16) | H99: A | I99: =$B$4+90 -> 46055 | J99: 15), 16), 20)
A100: HCI/CCO/BI-55-C | B100: Reject Invalid Extended Create Connection Command, 0x03, 0x00 | C100: 2021-1 | D100: A | E100: 45873 | F100: 15), 16) | H100: A | I100: =$B$4+90 -> 46055 | J100: 15), 16), 20)
A101: HCI/CCO/BI-56-C | B101: Reject Invalid Extended Create Connection Command, 0x03, 0x01 | C101: 2021-1 | D101: A | E101: 45873 | F101: 15), 16) | H101: A | I101: =$B$4+90 -> 46055 | J101: 15), 16), 20)
A102: HCI/CCO/BI-57-C | B102: LE Setup ISO Data Path, CIS | C102: 2024-2 | D102: A | E102: 45873 | F102: 15), 16) | H102: A | I102: =$B$4+90 -> 46055 | J102: 15), 16)
A103: HCI/CCO/BI-58-C | B103: LE Setup ISO Data Path, BIS, Isochronous Broadcaster | C103: 2024-2 | D103: A | E103: 45873 | F103: 15), 16) | H103: A | I103: =$B$4+90 -> 46055 | J103: 15), 16)
A104: HCI/CCO/BI-59-C | B104: Invalid LE Set Periodic Advertising Receive Enable Parameters, Periodic Advertising ADI Not Supported | C104: 2022-2 | D104: A | E104: 45873 | F104: 15), 16) | H104: A | I104: =$B$4+90 -> 46055 | J104: 15), 16)
A105: HCI/CCO/BI-60-C | B105: Invalid LE Set PAST Parameters, PA ADI Not Supported | C105: 2022-2 | D105: A | E105: 45873 | F105: 15), 16) | H105: A | I105: =$B$4+90 -> 46055 | J105: 15), 16)
A106: HCI/CCO/BI-61-C | B106: Invalid LE Set Default PAST Parameters, PA ADI Not Supported | C106: 2022-2 | D106: A | E106: 45873 | F106: 15), 16) | H106: A | I106: =$B$4+90 -> 46055 | J106: 15), 16)
A107: HCI/CCO/BI-62-C | B107: LE Setup ISO Data Path, BIS, Synchronized Receiver | C107: 2024-2 | D107: A | E107: 45873 | F107: 15), 16) | H107: A | I107: =$B$4+90 -> 46055 | J107: 15), 16)
A108: HCI/CCO/BI-63-C | B108: LE Extended Create Connection [v2], Invalid Parameters | C108: pkg101 | D108: A | E108: 45873 | F108: 15) | H108: A | I108: =$B$4+90 -> 46055 | J108: 15), 20) | K108: TSE 27934 (SCI)
...

Sheet IAL
A1: Test Case Reference List
A2: =Top!$C$13 -> Isochronous Adaptation Layer Conformance | D2: Previous TS | E2: =Top!E13 -> IAL.TS.p9 | H2: TS | I2: =Top!G13 -> IAL.TS.p10 | J2: Available Date | K2: =rel_date -> 45965
A3: =Top!$D$13 -> Vol 6 Part G, 5.2–6.2 | D3: Previous ICS | E3: =Top!F13 -> IAL.ICS.p3 | H3: ICS | I3: =Top!H13 -> IAL.ICS.p3 | J3: Available Date | K3: 45783
A4: =Top!A2 -> Release Date | B4: =rel_date -> 45965
A5: go to top | D5: Previously published test requirements | H5: Updated requirements through this release
A6: TCID*** | B6: Description | C6: TCRL Package Version Last Updated | D6: TC Category | E6: Active Date | F6: Test System Alternatives | G6: Notes | H6: TC Category | I6: Active Date | J6: Test System Alternatives | K6: Notes
A7: TCMT | B7: Test Case Mapping Table | C7: pkg101 | E7: 45873 | G7: TSE 26881 | I7: =$B$4+90 -> 46055 | K7: TSE 27258
A8: ICS | B8: Implementation Conformance Statement | C8: 2025-2 | E8: 45873 | G8: TSE 26827 | I8: 45873
A9: IAL/BIS/FRA/BRD/BV-06-C | B9: Broadcast Single SDU, BIS, Framed – NSE 4, BN 2 | C9: 2025-2 | D9: A | E9: 45873 | F9: 15), 16) | G9: TSE 26804 | H9: A | I9: =$B$4+90 -> 46055 | J9: 15), 16)
A10: IAL/BIS/FRA/BRD/BV-08-C | B10: Broadcast Single SDU, BIS, Framed – NSE 2, BN 1 | C10: 2025-2 | D10: A | E10: 45873 | F10: 15), 16) | G10: TSE 26804 | H10: A | I10: =$B$4+90 -> 46055 | J10: 15), 16)
A11: IAL/BIS/FRA/BRD/BV-13-C | B11: Broadcast Large SDU, BIS, Framed – NSE 10, BN 5 | C11: 2025-2 | D11: A | E11: 45873 | F11: 15), 16) | G11: TSE 26804 | H11: A | I11: =$B$4+90 -> 46055 | J11: 15), 16)
A12: IAL/BIS/FRA/BRD/BV-15-C | B12: Broadcast Large SDU, BIS, Framed – NSE 6, BN 3 | C12: 2025-2 | D12: A | E12: 45873 | F12: 15), 16) | G12: TSE 26804 | H12: A | I12: =$B$4+90 -> 46055 | J12: 15), 16)
A13: IAL/BIS/FRA/BRD/BV-17-C | B13: Broadcast Multiple, Small SDUs, BIS, Framed – NSE 2, BN 1 | C13: 2021-1 | D13: A | E13: 45873 | F13: 15), 16) | H13: A | I13: =$B$4+90 -> 46055 | J13: 15), 16)
A14: IAL/BIS/FRA/BRD/BV-18-C | B14: Broadcast Multiple, Small SDUs, BIS, Framed – NSE 2, BN 2 | C14: 2021-1 | D14: A | E14: 45873 | F14: 15), 16) | H14: A | I14: =$B$4+90 -> 46055 | J14: 15), 16)
A15: IAL/BIS/FRA/BRD/BV-20-C | B15: Broadcast Multiple, Small SDUs, BIS, Framed – NSE 4, BN 2 | C15: 2021-1 | D15: A | E15: 45873 | F15: 15), 16) | H15: A | I15: =$B$4+90 -> 46055 | J15: 15), 16)
A16: IAL/BIS/FRA/BRD/BV-25-C | B16: Broadcast Zero-Length SDU, BIS, Framed – NSE 6, BN 2 | C16: 2024-2 | D16: A | E16: 45873 | F16: 15), 16) | H16: A | I16: =$B$4+90 -> 46055 | J16: 15), 16)
A17: IAL/BIS/FRA/BRD/BV-26-C | B17: Broadcast Zero-Length SDU, BIS, Framed – NSE 2, BN 1 | C17: 2024-2 | D17: A | E17: 45873 | F17: 15), 16) | H17: A | I17: =$B$4+90 -> 46055 | J17: 15), 16)
A18: IAL/BIS/FRA/BRD/BV-27-C | B18: Broadcast Zero-Length SDU, BIS, Framed – NSE 4, BN 1 | C18: 2024-2 | D18: A | E18: 45873 | F18: 15), 16) | H18: A | I18: =$B$4+90 -> 46055 | J18: 15), 16)
A19: IAL/BIS/FRA/BRD/BV-28-C | B19: Broadcast Zero-Length SDU, BIS, Framed – NSE 6, BN 3 | C19: 2024-2 | D19: A | E19: 45873 | F19: 15), 16) | H19: A | I19: =$B$4+90 -> 46055 | J19: 15), 16)
A20: IAL/BIS/FRA/BRD/BV-29-C | B20: Broadcast Single SDU, BIS, Framed – NSE 6, BN 3 | C20: 2025-2 | D20: A | E20: 45873 | F20: 15) | G20: TSE 26804 | H20: A | I20: =$B$4+90 -> 46055 | J20: 15)
A21: IAL/BIS/FRA/BRD/BV-30-C | B21: Broadcast Zero-Length SDU, BIS, Framed – NSE 6, BN 2 | C21: 2024-2 | D21: A | E21: 45873 | F21: 15) | H21: A | I21: =$B$4+90 -> 46055 | J21: 15)
A22: IAL/BIS/FRA/BRD/BV-31-C | B22: Permitted Framing Mode Packets, Isochronous Broadcaster, Framed, Segmentable mode | C22: pkg101 | D22: A | E22: 45873 | F22: 15) | G22: TSE 26804 | H22: A | I22: =$B$4+90 -> 46055 | J22: 15) | K22: TSE 26870
A23: IAL/BIS/FRA/BRD/BV-32-C | B23: Unsegmented Framed LL Broadcast PDUs at 7.5 ms ISO Interval, Isochronous Broadcaster | C23: 2025-2 | D23: A | E23: 45873 | F23: 15) | G23: TSE 26804 | H23: A | I23: =$B$4+90 -> 46055 | J23: 15)
A24: IAL/BIS/FRA/BRD/BV-33-C | B24: Permitted Framing Mode Packets, Isochronous Broadcaster, Framed, Unsegmented mode | C24: pkg101 | D24: A | E24: 45873 | F24: 15) | G24: TSE 26804 | H24: A | I24: =$B$4+90 -> 46055 | J24: 15) | K24: TSE 26870
A25: IAL/BIS/FRA/SNC/BI-01-C | B25: SDU Reporting, BIS, Framed PDU | C25: 2025-2 | D25: A | E25: 45873 | F25: 15) | G25: TSEs 26799, 26804 | H25: A | I25: =$B$4+90 -> 46055 | J25: 15)
A26: IAL/BIS/FRA/SNC/BI-02-C | B26: SDU Reporting, BIS, BN = 1, NSE = 1, Framed PDU | C26: 2025-2 | D26: A | E26: 45873 | F26: 15), 16) | G26: TSE 26804 | H26: A | I26: =$B$4+90 -> 46055 | J26: 15), 16)
A27: IAL/BIS/FRA/SNC/BI-03-C | B27: Reporting an Unsuccessful Large SDU, Framed BIS | C27: 2025-2 | D27: A | E27: 45873 | F27: 15), 16) | G27: TSE 26804 | H27: A | I27: =$B$4+90 -> 46055 | J27: 15), 16)
A28: IAL/BIS/FRA/SNC/BI-04-C | B28: Reporting a missing or damaged SDU, Framed BIS | C28: 2025-2 | D28: A | E28: 45873 | F28: 15), 16) | G28: TSE 26804 | H28: A | I28: =$B$4+90 -> 46055 | J28: 15), 16)
A29: IAL/BIS/FRA/SNC/BV-06-C | B29: Receive Single SDU, BIS, Framed – NSE 4, BN 2 | C29: 2024-2 | D29: A | E29: 45873 | F29: 15), 16) | H29: A | I29: =$B$4+90 -> 46055 | J29: 15), 16)
A30: IAL/BIS/FRA/SNC/BV-08-C | B30: Receive Single SDU, BIS, Framed – NSE 2, BN 1 | C30: 2024-2 | D30: A | E30: 45873 | F30: 15), 16) | H30: A | I30: =$B$4+90 -> 46055 | J30: 15), 16)
A31: IAL/BIS/FRA/SNC/BV-11-C | B31: Receive Large SDU, BIS, Framed – NSE 8, BN 4 | C31: 2025-2 | D31: A | E31: 45873 | F31: 15), 16) | G31: TSE 26804 | H31: A | I31: =$B$4+90 -> 46055 | J31: 15), 16)
A32: IAL/BIS/FRA/SNC/BV-13-C | B32: Receive Large SDU, BIS, Framed – NSE 8, BN 4 | C32: 2025-2 | D32: A | E32: 45873 | F32: 15), 16) | G32: TSE 26804 | H32: A | I32: =$B$4+90 -> 46055 | J32: 15), 16)
A33: IAL/BIS/FRA/SNC/BV-15-C | B33: Receive Large SDU, BIS, Framed – NSE 8, BN 4 | C33: 2025-2 | D33: A | E33: 45873 | F33: 15), 16) | G33: TSE 26804 | H33: A | I33: =$B$4+90 -> 46055 | J33: 15), 16)
A34: IAL/BIS/FRA/SNC/BV-17-C | B34: Receive Multiple, Small SDUs, BIS, Framed – NSE 2, BN 1 | C34: 2025-2 | D34: A | E34: 45873 | F34: 15), 16) | G34: TSE 26804 | H34: A | I34: =$B$4+90 -> 46055 | J34: 15), 16)
A35: IAL/BIS/FRA/SNC/BV-18-C | B35: Receive Multiple, Small SDUs, BIS, Framed – NSE 2, BN 2 | C35: 2025-2 | D35: A | E35: 45873 | F35: 15), 16) | G35: TSE 26804 | H35: A | I35: =$B$4+90 -> 46055 | J35: 15), 16)
A36: IAL/BIS/FRA/SNC/BV-20-C | B36: Receive Multiple, Small SDUs, BIS, Framed – NSE 4, BN 2 | C36: 2025-2 | D36: A | E36: 45873 | F36: 15), 16) | G36: TSE 26804 | H36: A | I36: =$B$4+90 -> 46055 | J36: 15), 16)
A37: IAL/BIS/FRA/SNC/BV-25-C | B37: Receive Zero-Length SDU, BIS, Framed – NSE 6, BN 2 | C37: 2024-2 | D37: A | E37: 45873 | F37: 15), 16) | H37: A | I37: =$B$4+90 -> 46055 | J37: 15), 16)
A38: IAL/BIS/FRA/SNC/BV-26-C | B38: Receive Zero-Length SDU, BIS, Framed – NSE 2, BN 1 | C38: 2024-2 | D38: A | E38: 45873 | F38: 15), 16) | H38: A | I38: =$B$4+90 -> 46055 | J38: 15), 16)
A39: IAL/BIS/FRA/SNC/BV-27-C | B39: Receive Zero-Length SDU, BIS, Framed – NSE 4, BN 1 | C39: 2024-2 | D39: A | E39: 45873 | F39: 15), 16) | H39: A | I39: =$B$4+90 -> 46055 | J39: 15), 16)
A40: IAL/BIS/FRA/SNC/BV-28-C | B40: Receive Zero-Length SDU, BIS, Framed – NSE 6, BN 3 | C40: 2024-2 | D40: A | E40: 45873 | F40: 15), 16) | H40: A | I40: =$B$4+90 -> 46055 | J40: 15), 16)
A41: IAL/BIS/FRA/SNC/BV-29-C | B41: Receive Single SDU, BIS, Framed – NSE 4, BN 1 | C41: 2024-2 | D41: A | E41: 45873 | F41: 15) | H41: A | I41: =$B$4+90 -> 46055 | J41: 15)
A42: IAL/BIS/FRA/SNC/BV-30-C | B42: Receive Zero-Length SDU, BIS, Framed – NSE 6, BN 2 | C42: 2024-2 | D42: A | E42: 45873 | F42: 15) | H42: A | I42: =$B$4+90 -> 46055 | J42: 15)
A43: IAL/BIS/FRA/SNC/BV-31-C | B43: Framing_B bit in BIGInfo Ignored, Unsegmented Framed not supported, Framed, Segmentable mode | C43: 2024-2 | D43: A | E43: 45873 | F43: 15) | H43: A | I43: =$B$4+90 -> 46055 | J43: 15)
A44: IAL/BIS/FRA/SNC/BV-32-C | B44: Framing_B bit in BIGInfo Ignored, Unsegmented Framed not supported, Framed, Unsegmented mode | C44: 2024-2 | D44: A | E44: 45873 | F44: 15) | H44: A | I44: =$B$4+90 -> 46055 | J44: 15)
A45: IAL/BIS/UNF/BRD/BI-01-C, BI-03-C to BI-04-C | B45: No longer used | C45: 2021-1
A46: IAL/BIS/UNF/BRD/BV-01-C | B46: Broadcast Single SDU, BIS, Unframed – NSE 2, BN 1 | C46: 2025-2 | D46: A | E46: 45873 | F46: 15), 16) | G46: TSE 26804 | H46: A | I46: =$B$4+90 -> 46055 | J46: 15), 16)
A47: IAL/BIS/UNF/BRD/BV-02-C | B47: Broadcast Single SDU, BIS, Unframed – NSE 1, BN 2 | C47: 2025-2 | D47: A | E47: 45873 | F47: 15), 16) | G47: TSE 26804 | H47: A | I47: =$B$4+90 -> 46055 | J47: 15), 16)
A48: IAL/BIS/UNF/BRD/BV-03-C | B48: Broadcast Single SDU, BIS, Unframed – NSE 2, BN 2 | C48: 2025-2 | D48: A | E48: 45873 | F48: 15), 16) | G48: TSE 26804 | H48: A | I48: =$B$4+90 -> 46055 | J48: 15), 16)
A49: IAL/BIS/UNF/BRD/BV-09-C | B49: Broadcast Large SDU, BIS, Unframed – NSE 12, BN 6 | C49: 2025-2 | D49: A | E49: 45873 | F49: 15), 16) | G49: TSE 26804 | H49: A | I49: =$B$4+90 -> 46055 | J49: 15), 16)
A50: IAL/BIS/UNF/BRD/BV-10-C | B50: Broadcast Large SDU, BIS, Unframed – NSE 6, BN 3 | C50: 2025-2 | D50: A | E50: 45873 | F50: 15), 16) | G50: TSE 26804 | H50: A | I50: =$B$4+90 -> 46055 | J50: 15), 16)
A51: IAL/BIS/UNF/BRD/BV-11-C | B51: Broadcast Large SDU, BIS, Unframed – NSE 6, BN 3 | C51: 2025-2 | D51: A | E51: 45873 | F51: 15), 16) | G51: TSE 26804 | H51: A | I51: =$B$4+90 -> 46055 | J51: 15), 16)
A52: IAL/BIS/UNF/BRD/BV-21-C | B52: Broadcast Zero-Length SDU, BIS, Unframed – NSE 4, BN 2 | C52: 2021-1 | D52: A | E52: 45873 | F52: 15), 16) | H52: A | I52: =$B$4+90 -> 46055 | J52: 15), 16)
A53: IAL/BIS/UNF/BRD/BV-22-C | B53: Broadcast Zero-Length SDU, BIS, Unframed – NSE 6, BN 3 | C53: 2021-1 | D53: A | E53: 45873 | F53: 15), 16) | H53: A | I53: =$B$4+90 -> 46055 | J53: 15), 16)
A54: IAL/BIS/UNF/BRD/BV-23-C | B54: Broadcast Zero-Length SDU, BIS, Unframed – NSE 1, BN 1 | C54: 2021-1 | D54: A | E54: 45873 | F54: 15), 16) | H54: A | I54: =$B$4+90 -> 46055 | J54: 15), 16)
A55: IAL/BIS/UNF/BRD/BV-24-C | B55: Broadcast Zero-Length SDU, BIS, Unframed – NSE 2, BN 1 | C55: 2021-1 | D55: A | E55: 45873 | F55: 15), 16) | H55: A | I55: =$B$4+90 -> 46055 | J55: 15), 16)
A56: IAL/BIS/UNF/BRD/BV-29-C | B56: Broadcasting Unframed Empty PDUs with LLID=0b01, BIS, Encryption Disabled | C56: 2025-2 | D56: A | E56: 45873 | F56: 15), 16) | G56: TSE 26804 | H56: A | I56: =$B$4+90 -> 46055 | J56: 15), 16)
A57: IAL/BIS/UNF/BRD/BV-30-C | B57: Broadcasting Unframed Empty PDUs with LLID=0b01, BIS, Encryption Enabled | C57: 2025-2 | D57: A | E57: 45873 | F57: 15), 16) | G57: TSE 26804 | H57: A | I57: =$B$4+90 -> 46055 | J57: 15), 16)
A58: IAL/BIS/UNF/BRD/BV-31-C | B58: No longer used | C58: 2025-1
A59: IAL/BIS/UNF/SNC/BI-02-C | B59: Receive an unsuccessful Large SDU, BIS | C59: 2024-1 | D59: A | E59: 45873 | F59: 15), 16) | H59: A | I59: =$B$4+90 -> 46055 | J59: 15), 16)
A60: IAL/BIS/UNF/SNC/BI-05-C | B60: SDU Reporting, BIS, Unframed PDU | C60: 2025-2 | D60: A | E60: 45873 | F60: 15), 16) | G60: TSE 26804 | H60: A | I60: =$B$4+90 -> 46055 | J60: 15), 16)
A61: IAL/BIS/UNF/SNC/BI-06-C | B61: SDU Reporting, BIS, BN = 1, NSE = 1, Unframed PDU | C61: 2025-2 | D61: A | E61: 45873 | F61: 15), 16) | G61: TSE 26804 | H61: A | I61: =$B$4+90 -> 46055 | J61: 15), 16)
A62: IAL/BIS/UNF/SNC/BV-01-C | B62: Receive Single SDU, BIS, Unframed – NSE 2, BN 1 | C62: 2024-2 | D62: A | E62: 45873 | F62: 15), 16) | H62: A | I62: =$B$4+90 -> 46055 | J62: 15), 16)
A63: IAL/BIS/UNF/SNC/BV-02-C | B63: Receive Single SDU, BIS, Unframed – NSE 1, BN 1 | C63: 2024-2 | D63: A | E63: 45873 | F63: 15), 16) | H63: A | I63: =$B$4+90 -> 46055 | J63: 15), 16)
A64: IAL/BIS/UNF/SNC/BV-03-C | B64: Receive Single SDU, BIS, Unframed – NSE 2, BN 2 | C64: 2024-2 | D64: A | E64: 45873 | F64: 15), 16) | H64: A | I64: =$B$4+90 -> 46055 | J64: 15), 16)
A65: IAL/BIS/UNF/SNC/BV-09-C | B65: Receive Large SDU, BIS, Unframed – NSE 8, BN 4 | C65: 2025-2 | D65: A | E65: 45873 | F65: 15), 16) | G65: TSE 26804 | H65: A | I65: =$B$4+90 -> 46055 | J65: 15), 16)
A66: IAL/BIS/UNF/SNC/BV-10-C | B66: Receive Large SDU, BIS, Unframed – NSE 8, BN 4 | C66: 2025-2 | D66: A | E66: 45873 | F66: 15), 16) | G66: TSE 26804 | H66: A | I66: =$B$4+90 -> 46055 | J66: 15), 16)
A67: IAL/BIS/UNF/SNC/BV-21-C | B67: Receive Zero-Length SDU, BIS, Unframed – NSE 4, BN 2 | C67: 2024-2 | D67: A | E67: 45873 | F67: 15), 16) | H67: A | I67: =$B$4+90 -> 46055 | J67: 15), 16)
A68: IAL/BIS/UNF/SNC/BV-22-C | B68: Receive Zero-Length SDU, BIS, Unframed – NSE 6, BN 3 | C68: 2024-2 | D68: A | E68: 45873 | F68: 15), 16) | H68: A | I68: =$B$4+90 -> 46055 | J68: 15), 16)
A69: IAL/BIS/UNF/SNC/BV-23-C | B69: Receive Zero-Length SDU, BIS, Unframed – NSE 1, BN 1 | C69: 2024-2 | D69: A | E69: 45873 | F69: 15), 16) | H69: A | I69: =$B$4+90 -> 46055 | J69: 15), 16)
A70: IAL/BIS/UNF/SNC/BV-24-C | B70: Receive Zero-Length SDU, BIS, Unframed – NSE 2, BN 1 | C70: 2024-2 | D70: A | E70: 45873 | F70: 15), 16) | H70: A | I70: =$B$4+90 -> 46055 | J70: 15), 16)
A71: IAL/BIS/UNF/SNC/BV-29-C | B71: Receiving Unframed Empty PDUs with LLID=0b01, BIS, Encryption Disabled | C71: 2025-2 | D71: A | E71: 45873 | F71: 15), 16) | G71: TSE 26804 | H71: A | I71: =$B$4+90 -> 46055 | J71: 15), 16)
A72: IAL/BIS/UNF/SNC/BV-30-C | B72: Receiving Unframed Empty PDUs with LLID=0b01, BIS, Encryption Enabled | C72: 2025-2 | D72: A | E72: 45873 | F72: 15), 16) | G72: TSE 26804 | H72: A | I72: =$B$4+90 -> 46055 | J72: 15), 16)
A73: IAL/CIS/FRA/CEN/BI-01-C | B73: SDU Reporting, CIS, Framed PDU, Central | C73: 2025-2 | D73: A | E73: 45873 | F73: 15), 16) | G73: TSE 26804 | H73: A | I73: =$B$4+90 -> 46055 | J73: 15), 16)
A74: IAL/CIS/FRA/CEN/BI-02-C | B74: SDU Reporting, CIS, Framed PDU, BN = 1, NSE = 1, Central | C74: 2025-2 | D74: A | E74: 45873 | F74: 15), 16) | G74: TSE 26804 | H74: A | I74: =$B$4+90 -> 46055 | J74: 15), 16)
A75: IAL/CIS/FRA/CEN/BI-03-C | B75: Reporting an Unsuccessful Large SDU, Framed CIS | C75: 2025-2 | D75: A | E75: 45873 | F75: 15), 16) | G75: TSE 26804 | H75: A | I75: =$B$4+90 -> 46055 | J75: 15), 16)
A76: IAL/CIS/FRA/CEN/BI-04-C | B76: Reporting a missing or damaged SDU, Framed CIS | C76: 2025-2 | D76: A | E76: 45873 | F76: 15), 16) | G76: TSE 26804 | H76: A | I76: =$B$4+90 -> 46055 | J76: 15), 16)
A77: IAL/CIS/FRA/CEN/BV-03-C | B77: Send Single SDU, CIS, Framed, Central | C77: 2025-2 | D77: A | E77: 45873 | F77: 15) | G77: TSE 26804 | H77: A | I77: =$B$4+90 -> 46055 | J77: 15)
A78: IAL/CIS/FRA/CEN/BV-05-C | B78: Send Large SDU, CIS, Framed, Central | C78: 2025-2 | D78: A | E78: 45873 | F78: 15) | G78: TSE 26804 | H78: A | I78: =$B$4+90 -> 46055 | J78: 15)
A79: IAL/CIS/FRA/CEN/BV-07-C | B79: Send Multiple, Small SDUs, CIS, Framed, Central | C79: 2025-2 | D79: A | E79: 45873 | F79: 15), 16) | G79: TSE 26804 | H79: A | I79: =$B$4+90 -> 46055 | J79: 15), 16)
A80: IAL/CIS/FRA/CEN/BV-10-C | B80: Receive Single SDU, CIS, Framed, Central | C80: 2025-2 | D80: A | E80: 45873 | F80: 15), 16) | G80: TSE 26804 | H80: A | I80: =$B$4+90 -> 46055 | J80: 15), 16)
A81: IAL/CIS/FRA/CEN/BV-13-C | B81: Receive Large SDU, CIS, Framed, Central | C81: 2025-2 | D81: A | E81: 45873 | F81: 15), 16) | G81: TSE 26804 | H81: A | I81: =$B$4+90 -> 46055 | J81: 15), 16)
A82: IAL/CIS/FRA/CEN/BV-15-C | B82: Receive Multiple, Small SDUs, CIS, Framed, Central | C82: 2025-2 | D82: A | E82: 45873 | F82: 15), 16) | G82: TSE 26804 | H82: A | I82: =$B$4+90 -> 46055 | J82: 15), 16)
A83: IAL/CIS/FRA/CEN/BV-18-C | B83: Send Zero-Length SDU, CIS, Framed, Central | C83: 2025-2 | D83: A | E83: 45873 | F83: 15), 16) | G83: TSE 26804 | H83: A | I83: =$B$4+90 -> 46055 | J83: 15), 16)
A84: IAL/CIS/FRA/CEN/BV-20-C | B84: Receive Zero-Length SDU, CIS, Framed, Central | C84: 2024-2 | D84: A | E84: 45873 | F84: 15), 16) | H84: A | I84: =$B$4+90 -> 46055 | J84: 15), 16)
A85: IAL/CIS/FRA/CEN/BV-22-C | B85: Simultaneous Sending and Receiving SDUs, CIS, Framed, Central | C85: 2021-1 | D85: A | E85: 45873 | F85: 15), 16) | H85: A | I85: =$B$4+90 -> 46055 | J85: 15), 16)
A86: IAL/CIS/FRA/CEN/BV-26-C | B86: Send Single SDU, CIS, Framed, Central | C86: 2025-2 | D86: A | E86: 45873 | F86: 15) | G86: TSE 26804 | H86: A | I86: =$B$4+90 -> 46055 | J86: 15)
A87: IAL/CIS/FRA/CEN/BV-29-C | B87: Send Large SDU, CIS, Framed, Central | C87: 2025-2 | D87: A | E87: 45873 | F87: 15) | G87: TSE 26804 | H87: A | I87: =$B$4+90 -> 46055 | J87: 15)
A88: IAL/CIS/FRA/CEN/BV-31-C | B88: Send Multiple, Small SDUs, CIS, Framed, Central | C88: 2025-2 | D88: A | E88: 45873 | F88: 15), 16) | G88: TSE 26804 | H88: A | I88: =$B$4+90 -> 46055 | J88: 15), 16)
A89: IAL/CIS/FRA/CEN/BV-35-C | B89: Receive Single SDU, CIS, Framed, Central | C89: 2025-2 | D89: A | E89: 45873 | F89: 15), 16) | G89: TSE 26804 | H89: A | I89: =$B$4+90 -> 46055 | J89: 15), 16)
A90: IAL/CIS/FRA/CEN/BV-38-C | B90: Receive Large SDU, CIS, Framed, Central | C90: 2025-2 | D90: A | E90: 45873 | F90: 15), 16) | G90: TSE 26804 | H90: A | I90: =$B$4+90 -> 46055 | J90: 15), 16)
A91: IAL/CIS/FRA/CEN/BV-39-C | B91: Receive Multiple, Small SDUs, CIS, Framed, Central | C91: 2025-2 | D91: A | E91: 45873 | F91: 15) | G91: TSE 26804 | H91: A | I91: =$B$4+90 -> 46055 | J91: 15)
A92: IAL/CIS/FRA/CEN/BV-42-C | B92: Send Zero-Length SDU, CIS, Framed, Central | C92: 2025-2 | D92: A | E92: 45873 | F92: 15), 16) | G92: TSE 26804 | H92: A | I92: =$B$4+90 -> 46055 | J92: 15), 16)
A93: IAL/CIS/FRA/CEN/BV-44-C | B93: Receive Zero-Length SDU, CIS, Framed, Central | C93: 2024-2 | D93: A | E93: 45873 | F93: 15), 16) | H93: A | I93: =$B$4+90 -> 46055 | J93: 15), 16)
A94: IAL/CIS/FRA/CEN/BV-45-C | B94: Send Single SDU, CIS, Framed, Central | C94: 2025-2 | D94: A | E94: 45873 | F94: 15) | G94: TSE 26804 | H94: A | I94: =$B$4+90 -> 46055 | J94: 15)
A95: IAL/CIS/FRA/CEN/BV-46-C | B95: Send Large SDU, CIS, Framed, Central | C95: 2025-2 | D95: A | E95: 45873 | F95: 15) | G95: TSE 26804 | H95: A | I95: =$B$4+90 -> 46055 | J95: 15)
A96: IAL/CIS/FRA/CEN/BV-47-C | B96: Send Multiple, Small SDUs, CIS, Framed, Central | C96: 2025-2 | D96: A | E96: 45873 | F96: 15), 16) | G96: TSE 26804 | H96: A | I96: =$B$4+90 -> 46055 | J96: 15), 16)
A97: IAL/CIS/FRA/CEN/BV-48-C | B97: Receive Single SDU, CIS, Framed, Central | C97: 2025-2 | D97: A | E97: 45873 | F97: 15), 16) | G97: TSE 26804 | H97: A | I97: =$B$4+90 -> 46055 | J97: 15), 16)
A98: IAL/CIS/FRA/CEN/BV-49-C | B98: Receive Large SDU, CIS, Framed, Central | C98: 2025-2 | D98: A | E98: 45873 | F98: 15) | G98: TSE 26804 | H98: A | I98: =$B$4+90 -> 46055 | J98: 15)
A99: IAL/CIS/FRA/CEN/BV-50-C | B99: Receive Multiple, Small SDUs, CIS, Framed, Central | C99: 2025-2 | D99: A | E99: 45873 | F99: 15), 16) | G99: TSE 26804 | H99: A | I99: =$B$4+90 -> 46055 | J99: 15), 16)
A100: IAL/CIS/FRA/CEN/BV-51-C | B100: Send Zero-Length SDU, CIS, Framed, Central | C100: 2025-2 | D100: A | E100: 45873 | F100: 15), 16) | G100: TSE 26804 | H100: A | I100: =$B$4+90 -> 46055 | J100: 15), 16)
...

Sheet L2CAP
A1: Test Case Reference List
A2: =Top!$C$17 -> Logical Link Control and Adaptation Protocol Conformance | D2: Previous TS | E2: =Top!E17 -> L2CAP.TS.p40 | H2: TS | I2: =Top!G17 -> L2CAP.TS.p41 | J2: Available Date | K2: =rel_date -> 45965
A3: =Top!$D$17 -> Vol 3 Part A, 4.2–6.2 | D3: Previous ICS | E3: =Top!F17 -> L2CAP.ICS.p28 | H3: ICS | I3: =Top!H17 -> L2CAP.ICS.p29 | J3: Available Date | K3: =rel_date -> 45965
A4: Release date | B4: =rel_date -> 45965
A5: go to top | D5: Previously published test requirements | H5: Updated requirements through this release
A6: TCID*** | B6: Description | C6: TCRL Package Version Last Updated | D6: TC Category | E6: Active Date | F6: Test System Alternatives | G6: Notes | H6: TC Category | I6: Active Date | J6: Test System Alternatives | K6: Notes
A7: TCMT | B7: Test Case Mapping Table | C7: pkg101 | E7: 45873 | G7: TSEs 17651, 24756 | I7: =$B$4+90 -> 46055 | K7: TSEs 26118, 27163, 27265, 27636
A8: ICS | B8: Implementation Conformance Statement | C8: pkg101 | E8: 45873 | G8: TSE 27045 | I8: =$B$4+90 -> 46055 | K8: TSE 27265
A9: L2CAP/CCH/BV-01-C | B9: Create Channel Request for an AMP Physical Link | D9: B | E9: 45873 | F9: Member Defined | H9: B | I9: =$B$4+90 -> 46055 | J9: Member Defined
A10: L2CAP/CCH/BV-02-C | B10: Create Channel Request for an AMP Physical Link - Refused | D10: B | E10: 45873 | F10: Member Defined | H10: B | I10: =$B$4+90 -> 46055 | J10: Member Defined
A11: L2CAP/CCH/BV-03-C | B11: Create Channel Request for an AMP Physical Link - Failed | D11: B | E11: 45873 | F11: Member Defined | H11: B | I11: =$B$4+90 -> 46055 | J11: Member Defined
A12: L2CAP/CCH/BV-04-C | B12: Create Channel Response for an AMP Physical Link | D12: B | E12: 45873 | F12: Member Defined | H12: B | I12: =$B$4+90 -> 46055 | J12: Member Defined
A13: L2CAP/CLS/CID/BV-01-C | B13: Ignore Unsupported CIDs, APB | C13: 2021-1 | D13: B | E13: 45873 | F13: Member Defined | H13: B | I13: =$B$4+90 -> 46055 | J13: Member Defined
A14: L2CAP/CLS/CLR/BV-01-C | B14: Data Over Connectionless Channel | D14: B | E14: 45873 | F14: Member Defined | H14: B | I14: =$B$4+90 -> 46055 | J14: Member Defined
A15: L2CAP/CLS/UCD/BV-01-C | B15: Data Reception over Unicast Connectionless Channel | D15: A | E15: 45873 | F15: 2) | H15: A | I15: =$B$4+90 -> 46055 | J15: 2)
A16: L2CAP/CLS/UCD/BV-02-C | B16: Unencrypted data transmission over unicast connectionless channel | D16: B | E16: 45873 | F16: Member Defined | H16: B | I16: =$B$4+90 -> 46055 | J16: Member Defined
A17: L2CAP/CLS/UCD/BV-03-C | B17: Encrypted Data Transmission over Unicast Connectionless Channel | D17: B | E17: 45873 | F17: Member Defined | H17: B | I17: =$B$4+90 -> 46055 | J17: Member Defined
A18: L2CAP/CMC/BI-01-C | B18: Failed Configuration of Enhanced Retransmission Mode when use of the Mode is Mandatory | D18: B | E18: 45873 | F18: Member Defined | H18: B | I18: =$B$4+90 -> 46055 | J18: Member Defined
A19: L2CAP/CMC/BI-02-C | B19: Configuration Mode mismatch when use of Enhanced Retransmission Mode is Mandatory | D19: B | E19: 45873 | F19: Member Defined | H19: B | I19: =$B$4+90 -> 46055 | J19: Member Defined
A20: L2CAP/CMC/BI-03-C | B20: Failed Configuration of Streaming Mode when use of the Mode is Mandatory | D20: B | E20: 45873 | F20: Member Defined | H20: B | I20: =$B$4+90 -> 46055 | J20: Member Defined
A21: L2CAP/CMC/BI-04-C | B21: Configuration Mode mismatch when use of Streaming Mode is Mandatory | D21: B | E21: 45873 | F21: Member Defined | H21: B | I21: =$B$4+90 -> 46055 | J21: Member Defined
A22: L2CAP/CMC/BI-05-C | B22: Failed Configuration to Basic Mode by the IUT | D22: B | E22: 45873 | F22: Member Defined | H22: B | I22: =$B$4+90 -> 46055 | J22: Member Defined
A23: L2CAP/CMC/BI-06-C | B23: Configuration to Basic Mode Rejected by the Lower Tester | D23: B | E23: 45873 | F23: Member Defined | H23: B | I23: =$B$4+90 -> 46055 | J23: Member Defined
A24: L2CAP/CMC/BV-01-C | B24: IUT Initiated Configuration of Enhanced Retransmission Mode | D24: A | E24: 45873 | F24: 1) | H24: A | I24: =$B$4+90 -> 46055 | J24: 1)
A25: L2CAP/CMC/BV-02-C | B25: Lower Tester Initiated Configuration of Enhanced Retransmission Mode | D25: A | E25: 45873 | F25: 1) | H25: A | I25: =$B$4+90 -> 46055 | J25: 1)
... A38: L2CAP/CMC/BV-15-C | B38: Configuration Mode Mismatch when use of Streaming Mode is Optional and ERTM is proposed by the Lower Tester | D38: A | E38: 45873 | F38: 1) | H38: A | I38: =$B$4+90 -> 46055 | J38: 1)
A39: L2CAP/COS/CED/BI-01-C | B39: Reject Unknown Command, BR/EDR | C39: 2024-1 | D39: A | E39: 45873 | F39: 1) | H39: A | I39: =$B$4+90 -> 46055 | J39: 1)
A40: L2CAP/COS/CED/BI-02-C | B40: No longer used | C40: 2025-1
A41: L2CAP/COS/CED/BI-03-C | B41: Incorrect PDU Length, Received Data Packet, Basic | C41: 2025-1 | D41: B | E41: 45873 | F41: Member Defined | H41: B | I41: =$B$4+90 -> 46055 | J41: Member Defined
A42: L2CAP/COS/CED/BI-04-C | B42: Incorrect PDU Length, C-Frame, BR/EDR | C42: 2025-1 | D42: B | E42: 45873 | F42: Member Defined | H42: B | I42: =$B$4+90 -> 46055 | J42: Member Defined
A43: L2CAP/COS/CED/BI-05-C | B43: Incorrect PDU Length, C-Frame, LE Credit Based Connection Request | C43: pkg101 | D43: B | E43: 45873 | F43: Member Defined | H43: B | I43: =$B$4+90 -> 46055 | J43: Member Defined | K43: TSE 27636
A44: L2CAP/COS/CED/BI-06-C | B44: Incorrect PDU Length, Received Data Packets with Continuation, Basic | C44: 2025-1 | D44: B | E44: 45873 | F44: Member Defined | H44: B | I44: =$B$4+90 -> 46055 | J44: Member Defined
A45: L2CAP/COS/CED/BI-07-C | B45: Incorrect PDU Length, Received Data Packets with Multiple Continuation | C45: 2025-1 | D45: B | E45: 45873 | F45: Member Defined | H45: B | I45: =$B$4+90 -> 46055 | J45: Member Defined
A46: L2CAP/COS/CED/BI-08-C | B46: Valid Signaling Command, Data Length > PDU Space, BR/EDR | C46: 2025-1 | D46: B | E46: 45873 | F46: Member Defined | H46: B | I46: =$B$4+90 -> 46055 | J46: Member Defined
A47: L2CAP/COS/CED/BI-09-C | B47: Valid Signaling Command, Data Length > PDU Space, LE Credit Based Connection Request | C47: pkg101 | D47: B | E47: 45873 | F47: Member Defined | H47: B | I47: =$B$4+90 -> 46055 | J47: Member Defined | K47: TSE 27636
A48: L2CAP/COS/CED/BI-10-C | B48: Incorrect Signaling Command Packets, Invalid Data Length for Command, BR/EDR | C48: 2025-1 | D48: B | E48: 45873 | F48: Member Defined | H48: B | I48: =$B$4+90 -> 46055 | J48: Member Defined
A49: L2CAP/COS/CED/BI-11-C | B49: Incorrect Signaling Command Packets, Invalid Data Length for Command, LE | C49: 2025-1 | D49: B | E49: 45873 | F49: Member Defined | H49: B | I49: =$B$4+90 -> 46055 | J49: Member Defined
A50: L2CAP/COS/CED/BI-12-C | B50: Valid Signaling Command, Shorter Data Length, Extra Zero Octet, BR/EDR | C50: pkg101 | D50: B | E50: 45873 | F50: Member Defined | H50: B | I50: =$B$4+90 -> 46055 | J50: Member Defined | K50: TSE 27644
A51: L2CAP/COS/CED/BI-13-C | B51: Valid Signaling Command, Shorter Data Length, Extra Zero Octet, LE Credit Based Connection Request | C51: pkg101 | D51: B | E51: 45873 | F51: Member Defined | H51: B | I51: =$B$4+90 -> 46055 | J51: Member Defined | K51: TSE 27636
A52: L2CAP/COS/CED/BI-14-C | B52: Multiple Signaling Command in one PDU, Data Truncated, BR/EDR, Echo Request | C52: 2025-1 | D52: B | E52: 45873 | F52: Member Defined | H52: B | I52: =$B$4+90 -> 46055 | J52: Member Defined
A53: L2CAP/COS/CED/BI-15-C | B53: Multiple Signaling Command in one PDU, Data Truncated, BR/EDR, Disconnection Request | C53: 2025-1 | D53: B | E53: 45873 | F53: Member Defined | H53: B | I53: =$B$4+90 -> 46055 | J53: Member Defined
A54: L2CAP/COS/CED/BI-16-C | B54: Multiple Signaling Command in one PDU, Data Truncated, LE Credit Based Flow Control Mode, LE Credit Based Connection Request | C54: pkg101 | D54: B | E54: 45873 | F54: Member Defined | H54: B | I54: =$B$4+90 -> 46055 | J54: Member Defined | K54: TSE 27636
A55: L2CAP/COS/CED/BI-17-C | B55: Multiple Signaling Command in one PDU, Data Truncated, LE Credit Based Flow Control Mode, Disconnection Request | C55: pkg101 | D55: B | E55: 45873 | F55: Member Defined | H55: B | I55: =$B$4+90 -> 46055 | J55: Member Defined | K55: TSE 27636
A56: L2CAP/COS/CED/BI-18-C | B56: Incorrect PDU Length, C-Frame, LE Enhanced Credit Based Connection Request | C56: pkg101 | H56: B | I56: =$B$4+180 -> 46145 | J56: Member Defined | K56: TSE 27636 (new TC)
A57: L2CAP/COS/CED/BI-19-C | B57: Incorrect PDU Length, C-Frame, LE Credit Based Connection Request Rejected | C57: pkg101 | H57: B | I57: =$B$4+180 -> 46145 | J57: Member Defined | K57: TSE 27636 (new TC)
A58: L2CAP/COS/CED/BI-20-C | B58: Valid Signaling Command, Data Length > PDU Space, LE Enhanced Credit Based Connection Request | C58: pkg101 | H58: B | I58: =$B$4+180 -> 46145 | J58: Member Defined | K58: TSE 27636 (new TC)
A59: L2CAP/COS/CED/BI-21-C | B59: Valid Signaling Command, Data Length > PDU Space, LE Credit Based Connection Request Rejected | C59: pkg101 | H59: B | I59: =$B$4+180 -> 46145 | J59: Member Defined | K59: TSE 27636 (new TC)
A60: L2CAP/COS/CED/BI-22-C | B60: Valid Signaling Command, Data Length > PDU Space, LE Enhanced Credit Based Connection Request | C60: pkg101 | H60: B | I60: =$B$4+180 -> 46145 | J60: Member Defined | K60: TSE 27636 (new TC)
A61: L2CAP/COS/CED/BI-23-C | B61: Valid Signaling Command, Data Length > PDU Space, LE Enhanced Credit Based Connection Request Rejected | C61: pkg101 | H61: B | I61: =$B$4+180 -> 46145 | J61: Member Defined | K61: TSE 27636 (new TC)
A62: L2CAP/COS/CED/BI-24-C | B62: Multiple Signaling Command in one PDU, LE, Data Truncated, Enhanced Credit Based Flow Control Mode, Enhanced Credit Based Connection Request | C62: pkg101 | H62: B | I62: =$B$4+180 -> 46145 | J62: Member Defined | K62: TSE 27636 (new TC)
A63: L2CAP/COS/CED/BI-25-C | B63: Multiple Signaling Command in one PDU, LE, Data Truncated, Enhanced Credit Based Flow Control Mode, Disconnection Request | C63: pkg101 | H63: B | I63: =$B$4+180 -> 46145 | J63: Member Defined | K63: TSE 27636 (new TC)
A64: L2CAP/COS/CED/BI-28-C | B64: Ignore Command Response with Invalid ID or Duplicate Response, BR/EDR | C64: pkg101 | H64: B | I64: =$B$4+180 -> 46145 | J64: Member Defined | K64: TSE 27163 (new TC)
A65: L2CAP/COS/CED/BI-29-C | B65: Ignore Command Response with Invalid ID or Duplicate Response, LE | C65: pkg101 | H65: B | I65: =$B$4+180 -> 46145 | J65: Member Defined | K65: TSE 27163 (new TC)
A66: L2CAP/COS/CED/BV-01-C | B66: Request Connection | D66: B | E66: 45873 | F66: Member Defined | H66: B | I66: =$B$4+90 -> 46055 | J66: Member Defined
A67: L2CAP/COS/CED/BV-03-C | B67: Send Data | D67: A | E67: 45873 | F67: 2) | H67: A | I67: =$B$4+90 -> 46055 | J67: 2)
A68: L2CAP/COS/CED/BV-04-C | B68: Disconnect | D68: B | E68: 45873 | F68: Member Defined | H68: B | I68: =$B$4+90 -> 46055 | J68: Member Defined
A69: L2CAP/COS/CED/BV-05-C | B69: No longer used | C69: 2025-1
A70: L2CAP/COS/CED/BV-07-C | B70: Accept Disconnect | D70: A | E70: 45873 | F70: 1) | H70: A | I70: =$B$4+90 -> 46055 | J70: 1)
A71: L2CAP/COS/CED/BV-08-C | B71: Disconnect on Timeout | C71: pkg101 | D71: B | E71: 45873 | F71: Member Defined | H71: B | I71: =$B$4+90 -> 46055 | J71: Member Defined | K71: TSE 26689
A72: L2CAP/COS/CED/BV-09-C | B72: Receive Multi-Command Packet | D72: B | E72: 45873 | F72: Member Defined | H72: B | I72: =$B$4+90 -> 46055 | J72: Member Defined
A73: L2CAP/COS/CED/BV-10-C | B73: Transmit I-frames | D73: B | E73: 45873 | F73: Member Defined | H73: B | I73: =$B$4+90 -> 46055 | J73: Member Defined
A74: L2CAP/COS/CED/BV-11-C | B74: Configure MTU Size | D74: B | E74: 45873 | F74: Member Defined | H74: B | I74: =$B$4+90 -> 46055 | J74: Member Defined
A75: L2CAP/COS/CED/BV-12-C | B75: Recombination of Signaling Packets | C75: 2021-1 | D75: B | E75: 45873 | F75: Member Defined | H75: B | I75: =$B$4+90 -> 46055 | J75: Member Defined
A76: L2CAP/COS/CED/BV-13-C | B76: No longer used | C76: 2025-1
A77: L2CAP/COS/CFC/BV-01-C | B77: Segmentation | D77: B | E77: 45873 | F77: Member Defined | H77: B | I77: =$B$4+90 -> 46055 | J77: Member Defined
A78: L2CAP/COS/CFC/BV-02-C | B78: No Segmentation | D78: B | E78: 45873 | F78: Member Defined | H78: B | I78: =$B$4+90 -> 46055 | J78: Member Defined
A79: L2CAP/COS/CFC/BV-03-C | B79: Reassembling | D79: A | E79: 45873 | F79: 1) | H79: A | I79: =$B$4+90 -> 46055 | J79: 1)
A80: L2CAP/COS/CFC/BV-04-C | B80: Data Receiving | D80: A | E80: 45873 | F80: 1) | H80: A | I80: =$B$4+90 -> 46055 | J80: 1)
A81: L2CAP/COS/CFC/BV-05-C | B81: Multiple Channels with Interleaved Data Streams | D81: B | E81: 45873 | F81: Member Defined | H81: B | I81: =$B$4+90 -> 46055 | J81: Member Defined
A82: L2CAP/COS/CFD/BV-01-C | B82: Continuation Flag | D82: B | E82: 45873 | F82: Member Defined | H82: B | I82: =$B$4+90 -> 46055 | J82: Member Defined
A83: L2CAP/COS/CFD/BV-02-C | B83: Negotiation with Reject | D83: A | E83: 45873 | F83: 2) | H83: A | I83: =$B$4+90 -> 46055 | J83: 2)
A84: L2CAP/COS/CFD/BV-03-C | B84: Send Requested Options | D84: A | E84: 45873 | F84: 4) | H84: A | I84: =$B$4+90 -> 46055 | J84: 4)
A85: L2CAP/COS/CFD/BV-08-C | B85: Non-blocking Config Response | C85: 2017-2 | D85: A | E85: 45873 | F85: 1) | H85: A | I85: =$B$4+90 -> 46055 | J85: 1)
A86: L2CAP/COS/CFD/BV-09-C | B86: Mandatory 48 Byte MTU | D86: A | E86: 45873 | F86: 1) | H86: A | I86: =$B$4+90 -> 46055 | J86: 1)
A87: L2CAP/COS/CFD/BV-10-C | B87: Retransmission Mode Negotiation | D87: B | E87: 45873 | F87: Member Defined | H87: B | I87: =$B$4+90 -> 46055 | J87: Member Defined
A88: L2CAP/COS/CFD/BV-11-C | B88: Negotiation of Unsupported Parameter | D88: A | E88: 45873 | F88: 2) | H88: A | I88: =$B$4+90 -> 46055 | J88: 2)
A89: L2CAP/COS/CFD/BV-12-C | B89: Unknown Option Response | C89: 2019-2 | D89: A | E89: 45873 | F89: 2) | H89: A | I89: =$B$4+90 -> 46055 | J89: 2)
A90: L2CAP/COS/CFD/BV-13-C | B90: Flow Control Mode Negotiation | D90: B | E90: 45873 | F90: Member Defined | H90: B | I90: =$B$4+90 -> 46055 | J90: Member Defined
A91: L2CAP/COS/CFD/BV-14-C | B91: Unknown Mandatory Options Request | C91: 2019-2 | D91: B | E91: 45873 | F91: Member Defined | H91: B | I91: =$B$4+90 -> 46055 | J91: Member Defined
A92: L2CAP/COS/CID/BI-01-C | B92: Ignore Unsupported CIDs, ACL | C92: 2022-1 | D92: B | E92: 45873 | F92: Member Defined | H92: B | I92: =$B$4+90 -> 46055 | J92: Member Defined
A93: L2CAP/COS/ECFC/BV-01-C | B93: Segmentation, LE | C93: 2021-2 | D93: B | E93: 45873 | F93: Member Defined | H93: B | I93: =$B$4+90 -> 46055 | J93: Member Defined
A94: L2CAP/COS/ECFC/BV-02-C | B94: Reassembling, LE | C94: 2019-2 | D94: B | E94: 45873 | F94: Member Defined | H94: B | I94: =$B$4+90 -> 46055 | J94: Member Defined
A95: L2CAP/COS/ECFC/BV-03-C | B95: Multiple Channels with Interleaved Data Streams, LE | C95: 2019-2 | D95: B | E95: 45873 | F95: Member Defined | H95: B | I95: =$B$4+90 -> 46055 | J95: Member Defined
A96: L2CAP/COS/ECFC/BV-04-C | B96: Reassembling, LE | C96: 2021-2 | D96: B | E96: 45873 | F96: Member Defined | H96: B | I96: =$B$4+90 -> 46055 | J96: Member Defined
A97: L2CAP/COS/ECFC/BV-05-C | B97: Segmentation, BR/EDR | C97: 2021-2 | D97: B | E97: 45873 | F97: Member Defined | H97: B | I97: =$B$4+90 -> 46055 | J97: Member Defined
A98: L2CAP/COS/ECFC/BV-06-C | B98: Reassembling, BR/EDR | C98: 2021-2 | D98: B | E98: 45873 | F98: Member Defined | H98: B | I98: =$B$4+90 -> 46055 | J98: Member Defined
A99: L2CAP/COS/ECFC/BV-07-C | B99: Multiple Channels with Interleaved Data Streams, BR/EDR | C99: 2021-2 | D99: B | E99: 45873 | F99: Member Defined | H99: B | I99: =$B$4+90 -> 46055 | J99: Member Defined
A100: L2CAP/COS/ECFC/BV-08-C | B100: Reassembling, BR/EDR | C100: 2021-2 | D100: B | E100: 45873 | F100: Member Defined | H100: B | I100: =$B$4+90 -> 46055 | J100: Member Defined
A101: L2CAP/COS/ECH/BV-01-C | B101: Respond to Echo Request | D101: B | E101: 45873 | F101: Member Defined | H101: B | I101: =$B$4+90 -> 46055 | J101: Member Defined
A102: L2CAP/COS/ECH/BV-02-C | B102: Send Echo Request | D102: B | E102: 45873 | F102: Member Defined | H102: B | I102: =$B$4+90 -> 46055 | J102: Member Defined
A103: L2CAP/COS/FLC/BV-01-C | B103: Flow Control without Acks | D103: B | E103: 45873 | F103: Member Defined | H103: B | I103: =$B$4+90 -> 46055 | J103: Member Defined
A104: L2CAP/COS/FLC/BV-02-C | B104: Resume Flow on RR Frame Ack | D104: B | E104: 45873 | F104: Member Defined | H104: B | I104: =$B$4+90 -> 46055 | J104: Member Defined
A105: L2CAP/COS/FLC/BV-03-C | B105: Resume Flow on I-frame Ack | D105: B | E105: 45873 | F105: Member Defined | H105: B | I105: =$B$4+90 -> 46055 | J105: Member Defined
A106: L2CAP/COS/FLC/BV-04-C | B106: Transmit RR Frame on Monitor Timeout | D106: B | E106: 45873 | F106: Member Defined | H106: B | I106: =$B$4+90 -> 46055 | J106: Member Defined
A107: L2CAP/COS/IEX/BV-01-C | B107: Query for 1.2 Features | D107: B | E107: 45873 | F107: Member Defined | H107: B | I107: =$B$4+90 -> 46055 | J107: Member Defined
A108: L2CAP/COS/IEX/BV-02-C | B108: Respond with 1.2 Features | D108: B | E108: 45873 | F108: Member Defined | H108: B | I108: =$B$4+90 -> 46055 | J108: Member Defined
A109: L2CAP/COS/RTX/BV-01-C | B109: No Retransmission with R=1 | D109: B | E109: 45873 | F109: Member Defined | H109: B | I109: =$B$4+90 -> 46055 | J109: Member Defined
A110: L2CAP/COS/RTX/BV-02-C | B110: Retransmission with R=0 in RR frame | D110: B | E110: 45873 | F110: Member Defined | H110: B | I110: =$B$4+90 -> 46055 | J110: Member Defined
A111: L2CAP/COS/RTX/BV-03-C | B111: Retransmission with R=0 in I-frame | D111: B | E111: 45873 | F111: Member Defined | H111: B | I111: =$B$4+90 -> 46055 | J111: Member Defined
A112: L2CAP/ECF/BV-01-C | B112: Receive I-Frames with Extended Control Field | D112: B | E112: 45873 | F112: Member Defined | H112: B | I112: =$B$4+90 -> 46055 | J112: Member Defined
...

Sheet LL
A1: Test Case Reference List
A2: =Top!$C$11 -> Link Layer Conformance | D2: Previous TS | E2: =Top!E12 -> LL.TS.p26 | H2: TS | I2: =Top!G12 -> LL.TS.p27 | J2: Available Date | K2: =rel_date -> 45965
A3: =Top!$D$11 -> Vol 6 Part B, 4.2–6.2 | D3: Previous ICS | E3: =Top!F11 -> LL.ICS.p24 | H3: ICS | I3: =Top!H11 -> LL.ICS.p25 | J3: Available Date | K3: =rel_date -> 45965
A4: =Top!A2 -> Release Date | B4: =rel_date -> 45965 | D4: Previous ICS | E4: =Top!F12 -> LESEC.ICS.p1 | H4: ICS | I4: =Top!H12 -> LESEC.ICS.p1 | J4: Available Date | K4: 45706
A5: go to top | D5: Previously published test requirements | H5: Updated requirements through this release
A6: TCID*** | B6: Description | C6: TCRL Package Version Last Updated | D6: TC Category | E6: Active Date | F6: Test System Alternatives | G6: Notes | H6: TC Category | I6: Active Date | J6: Test System Alternatives | K6: Notes
A7: TCMT | B7: Test Case Mapping Table | C7: pkg101 | E7: 45873 | G7: TSEs 16389, 22234, 25923, 26114, 26210, 26345, 26603, 26729, 26852, 26981, 27008, 27170 | I7: =$B$4+90 -> 46055 | K7: TSE 27886 (LETM) TSE 27934 (SCI) TSEs 22940, 25028, 25609, 26740, 27203, 27206, 27267, 27407 27450, 27452, 27545, 27580, 27803, 27838, 27948
A8: LL ICS | B8: Implementation Conformance Statement | C8: pkg101 | E8: 45873 | G8: TSEs 26114, 26828 | I8: =$B$4+90 -> 46055 | K8: TSE 27886 (LETM) TSE 27934 (SCI) TSEs 27583, 28187
A9: LESEC ICS | B9: Implementation Conformance Statement | C9: 2025-1 | E9: 45796 | I9: 45796
A10: LL/BIS/BRD/BV-01-C | B10: Broadcast Isochronous Stream Setup – Encryption Disabled | C10: pkg101 | D10: A | E10: 45873 | F10: 15), 16) | H10: A | I10: =$B$4+90 -> 46055 | J10: 15), 16) | K10: TSE 27474
A11: LL/BIS/BRD/BV-02-C | B11: Broadcast Isochronous Stream Setup – Encryption Enabled | C11: pkg101 | D11: A | E11: 45873 | F11: 15), 16) | H11: A | I11: =$B$4+90 -> 46055 | J11: 15), 16) | K11: TSE 27474
A12: LL/BIS/BRD/BV-04-C | B12: Data Transmission in Multiple Broadcast Isochronous Streams, Interleaved BIG | C12: pkg101 | D12: A | E12: 45873 | F12: 15), 16) | G12: TSE 27127 | H12: A | I12: =$B$4+90 -> 46055 | J12: 15), 16) | K12: TSE 27444
A13: LL/BIS/BRD/BV-05-C | B13: Data Transmission in Multiple Broadcast Isochronous Streams, Sequential | C13: pkg101 | D13: A | E13: 45873 | F13: 15), 16) | G13: TSE 27127 | H13: A | I13: =$B$4+90 -> 46055 | J13: 15), 16) | K13: TSE 27444
A14: LL/BIS/BRD/BV-07-C | B14: Bursting of Packets in Broadcast Isochronous Stream | C14: 2021-2 | D14: A | E14: 45873 | F14: 15), 16) | H14: A | I14: =$B$4+90 -> 46055 | J14: 15), 16)
A15: LL/BIS/BRD/BV-08-C | B15: Pre-transmissions in Broadcast Isochronous Stream | C15: 2025-2 | D15: A | E15: 45873 | F15: 15), 16) | G15: TSE 27127 | H15: A | I15: =$B$4+90 -> 46055 | J15: 15), 16)
A16: LL/BIS/BRD/BV-09-C | B16: Broadcast Isochronous Group Channel Map Update Procedure, Broadcaster, Not Encrypted | C16: 2021-1 | D16: A | E16: 45873 | F16: 15), 16) | H16: A | I16: =$B$4+90 -> 46055 | J16: 15), 16)
A17: LL/BIS/BRD/BV-10-C | B17: Isochronous Broadcaster Terminates BIS Stream, Not Encrypted | C17: 2021-1 | D17: A | E17: 45873 | F17: 15), 16) | H17: A | I17: =$B$4+90 -> 46055 | J17: 15), 16)
A18: LL/BIS/BRD/BV-13-C | B18: Broadcast Isochronous Stream Using Non-Test Command – LE 1M PHY | C18: pkg101 | D18: A | E18: 45873 | F18: 15), 16) | H18: A | I18: =$B$4+90 -> 46055 | J18: 15), 16) | K18: TSE 27474
A19: LL/BIS/BRD/BV-14-C | B19: Broadcast Isochronous Stream Using Non-Test Command – LE 2M PHY | C19: pkg101 | D19: A | E19: 45873 | F19: 15), 16) | H19: A | I19: =$B$4+90 -> 46055 | J19: 15), 16) | K19: TSE 27474
A20: LL/BIS/BRD/BV-15-C | B20: Broadcast Isochronous Stream Using Non-Test Command – LE Coded PHY | C20: pkg101 | D20: A | E20: 45873 | F20: 15), 16) | H20: A | I20: =$B$4+90 -> 46055 | J20: 15), 16) | K20: TSE 27474
A21: LL/BIS/BRD/BV-16-C | B21: Maximum Supported Broadcast Isochronous Groups, Encryption Disabled | C21: 2025-2 | D21: A | E21: 45873 | F21: 15), 16) | G21: TSE 27127 | H21: A | I21: =$B$4+90 -> 46055 | J21: 15), 16)
A22: LL/BIS/BRD/BV-17-C | B22: Broadcast Isochronous Group Channel Map Update Procedure, Broadcaster, Encrypted | C22: 2024-2 | D22: A | E22: 45873 | F22: 15), 16) | H22: A | I22: =$B$4+90 -> 46055 | J22: 15), 16)
A23: LL/BIS/BRD/BV-18-C | B23: Isochronous Broadcaster Terminates BIS Stream, Encrypted | C23: 2021-1 | D23: A | E23: 45873 | F23: 15), 16) | H23: A | I23: =$B$4+90 -> 46055 | J23: 15), 16)
A24: LL/BIS/BRD/BV-19-C | B24: Maximum Supported Broadcast Isochronous Groups, Encryption Enabled | C24: 2025-2 | D24: A | E24: 45873 | F24: 15), 16) | G24: TSE 27127 | H24: A | I24: =$B$4+90 -> 46055 | J24: 15), 16)
A25: LL/BIS/BRD/BV-20-C | B25: Broadcasting Broadcast Isochronous Streams | C25: 2021-1 | D25: A | E25: 45873 | F25: 15), 16) | H25: A | I25: =$B$4+90 -> 46055 | J25: 15), 16)
A26: LL/BIS/BRD/BV-21-C | B26: Broadcasting a Broadcast Isochronous Stream, LE 2M PHY | C26: 2021-1 | D26: A | E26: 45873 | F26: 15), 16) | H26: A | I26: =$B$4+90 -> 46055 | J26: 15), 16)
A27: LL/BIS/BRD/BV-22-C | B27: Broadcasting a Broadcast Isochronous Stream, LE Coded PHY | C27: 2021-1 | D27: A | E27: 45873 | F27: 15), 16) | H27: A | I27: =$B$4+90 -> 46055 | J27: 15), 16)
A28: LL/BIS/BRD/BV-23-C | B28: Broadcast Isochronous Stream Setup – Encryption Disabled – BN=1 | C28: pkg101 | D28: A | E28: 45873 | F28: 15), 16) | H28: A | I28: =$B$4+90 -> 46055 | J28: 15), 16) | K28: TSE 27474
A29: LL/BIS/BRD/BV-24-C | B29: Broadcast Isochronous Stream Setup – Encryption Enabled – BN=1 | C29: pkg101 | D29: A | E29: 45873 | F29: 15), 16) | H29: A | I29: =$B$4+90 -> 46055 | J29: 15), 16) | K29: TSE 27474
A30: LL/BIS/BRD/BV-25-C | B30: Data Transmission in Multiple Broadcast Isochronous Streams, BN = 1 | C30: pkg101 | D30: A | E30: 45873 | F30: 15), 16) | G30: TSE 27127 | H30: A | I30: =$B$4+90 -> 46055 | J30: 15), 16) | K30: TSE 27444
A31: LL/BIS/BRD/BV-26-C | B31: Pre-transmissions in Broadcast Isochronous Stream, Verify LLID | C31: 2025-2 | D31: A | E31: 45873 | F31: 15), 16) | G31: TSE 27127 | H31: A | I31: =$B$4+90 -> 46055 | J31: 15), 16)
A32: LL/BIS/BRD/BV-27-C | B32: Immediate Repetition Count in Broadcast Isochronous Stream, Verify LLID | C32: 2025-2 | D32: A | E32: 45873 | F32: 15), 16) | G32: TSE 27127 | H32: A | I32: =$B$4+90 -> 46055 | J32: 15), 16)
A33: LL/BIS/BRD/BV-28-C | B33: Broadcast Isochronous Stream Using Non-Test Command – LE 1M PHY | C33: pkg101 | D33: A | E33: 45873 | F33: 15) | H33: A | I33: =$B$4+90 -> 46055 | J33: 15) | K33: TSE 27474
A34: LL/BIS/BRD/BV-29-C | B34: Broadcast Isochronous Stream Using Non-Test Command – LE 2M PHY | C34: pkg101 | D34: A | E34: 45873 | F34: 15) | H34: A | I34: =$B$4+90 -> 46055 | J34: 15) | K34: TSE 27474
A35: LL/BIS/BRD/BV-30-C | B35: Broadcast Isochronous Stream Using Non-Test Command – LE 2M PHY | C35: pkg101 | D35: A | E35: 45873 | F35: 15) | H35: A | I35: =$B$4+90 -> 46055 | J35: 15) | K35: TSE 27474
A36: LL/BIS/BRD/BV-31-C | B36: LE Create BIG Test Framing Parameter | C36: 2024-2 | D36: A | E36: 45873 | F36: 15) | H36: A | I36: =$B$4+90 -> 46055 | J36: 15)
A37: LL/BIS/BRD/BV-32-C | B37: LE Create BIG Test Framing Parameter | C37: 2024-2 | D37: A | E37: 45873 | F37: 15) | H37: A | I37: =$B$4+90 -> 46055 | J37: 15)
A38: LL/BIS/BRD/BV-33-C | B38: LE Create BIG Test Framing Parameter | C38: 2024-2 | D38: A | E38: 45873 | F38: 15) | H38: A | I38: =$B$4+90 -> 46055 | J38: 15)
A39: LL/BIS/BRD/BV-34-C | B39: Broadcast Isochronous Stream Setup – Encryption Disabled – BN=1 | C39: pkg101 | D39: A | E39: 45873 | F39: 15) | H39: A | I39: =$B$4+90 -> 46055 | J39: 15) | K39: TSE 27474
A40: LL/BIS/SNC/BI-01-C | B40: Broadcast Isochronous Stream Synchronization, Unsupported Features | C40: 2021-1 | D40: A | E40: 45873 | F40: 15), 16) | H40: A | I40: =$B$4+90 -> 46055 | J40: 15), 16)
A41: LL/BIS/SNC/BI-02-C | B41: Broadcast Isochronous Stream Synchronization, Unsupported Features | C41: 2021-1 | D41: A | E41: 45873 | F41: 15), 16) | H41: A | I41: =$B$4+90 -> 46055 | J41: 15), 16)
A42: LL/BIS/SNC/BI-03-C | B42: Broadcast Isochronous Stream Synchronization, Unsupported Features | C42: 2021-1 | D42: A | E42: 45873 | F42: 15), 16) | H42: A | I42: =$B$4+90 -> 46055 | J42: 15), 16)
A43: LL/BIS/SNC/BI-04-C | B43: Ignores Restricted for Future Use Opcodes, BIS | C43: 2021-1 | D43: A | E43: 45873 | F43: 15), 16) | H43: A | I43: =$B$4+90 -> 46055 | J43: 15), 16)
A44: LL/BIS/SNC/BI-05-C | B44: Broadcast Isochronous Stream Synchronization, Unsupported Features | C44: 2022-2 | D44: A | E44: 45873 | F44: 15), 16) | H44: A | I44: =$B$4+90 -> 46055 | J44: 15), 16)
A45: LL/BIS/SNC/BI-06-C | B45: No longer used | C45: 2024-2 | J45: 15), 16)
A46: LL/BIS/SNC/BV-01-C | B46: Broadcast Isochronous Stream Synchronization Setup – Encryption Disabled | C46: 2024-1 | D46: A | E46: 45873 | F46: 15), 16) | H46: A | I46: =$B$4+90 -> 46055 | J46: 15), 16)
A47: LL/BIS/SNC/BV-02-C | B47: Broadcast Isochronous Stream Synchronization Setup – Encryption Enabled | C47: 2024-1 | D47: A | E47: 45873 | F47: 15), 16) | H47: A | I47: =$B$4+90 -> 46055 | J47: 15), 16)
A48: LL/BIS/SNC/BV-04-C | B48: Data Reception in Multiple Broadcast Isochronous Streams | C48: 2019-2 | D48: A | E48: 45873 | F48: 15), 16) | H48: A | I48: =$B$4+90 -> 46055 | J48: 15), 16)
A49: LL/BIS/SNC/BV-07-C | B49: Bursting of Packets in Broadcast Isochronous Stream | C49: 2021-1 | D49: A | E49: 45873 | F49: 15), 16) | H49: A | I49: =$B$4+90 -> 46055 | J49: 15), 16)
A50: LL/BIS/SNC/BV-08-C | B50: Pre-transmissions in Broadcast Isochronous Stream | C50: 2021-1 | D50: A | E50: 45873 | F50: 15), 16) | H50: A | I50: =$B$4+90 -> 46055 | J50: 15), 16)
A51: LL/BIS/SNC/BV-09-C | B51: Broadcast Isochronous Group Channel Map Update Procedure, Synchronized Receiver, Not Encrypted | C51: 2021-1 | D51: A | E51: 45873 | F51: 15), 16) | H51: A | I51: =$B$4+90 -> 46055 | J51: 15), 16)
A52: LL/BIS/SNC/BV-10-C | B52: Broadcast Isochronous Stream Termination, Not Encrypted | C52: 2021-1 | D52: A | E52: 45873 | F52: 15), 16) | H52: A | I52: =$B$4+90 -> 46055 | J52: 15), 16)
A53: LL/BIS/SNC/BV-11-C | B53: Loss of Sync with an Isochronous Broadcaster | C53: 2021-1 | D53: A | E53: 45873 | F53: 15), 16) | H53: A | I53: =$B$4+90 -> 46055 | J53: 15), 16)
A54: LL/BIS/SNC/BV-12-C | B54: Broadcast Isochronous Stream Synchronization, Number of BISes Not Supported | C54: 2021-1 | D54: A | E54: 45873 | F54: 15), 16) | H54: A | I54: =$B$4+90 -> 46055 | J54: 15), 16)
A55: LL/BIS/SNC/BV-13-C | B55: Broadcast Isochronous Group Channel Map Update Procedure, Synchronized Receiver, Encrypted | C55: 2021-1 | D55: A | E55: 45873 | F55: 15), 16) | H55: A | I55: =$B$4+90 -> 46055 | J55: 15), 16)
A56: LL/BIS/SNC/BV-14-C | B56: Broadcast Isochronous Stream Termination, Encrypted | C56: 2021-1 | D56: A | E56: 45873 | F56: 15), 16) | H56: A | I56: =$B$4+90 -> 46055 | J56: 15), 16)
A57: LL/BIS/SNC/BV-15-C | B57: Broadcast Isochronous Stream Synchronization Setup – Encryption Disabled, BN = 1 | C57: 2024-1 | D57: A | E57: 45873 | F57: 15), 16) | H57: A | I57: =$B$4+90 -> 46055 | J57: 15), 16)
... A59: LL/BIS/SNC/BV-17-C | B59: Data Reception in Multiple Broadcast Isochronous Streams, BN = 1 | C59: 2021-1 | D59: A | E59: 45873 | F59: 15), 16) | H59: A | I59: =$B$4+90 -> 46055 | J59: 15), 16)
A60: LL/BIS/SNC/BV-18-C | B60: BIS SNC Accepts All Supported NSE Values | C60: 2025-2 | D60: A | E60: 45873 | F60: 15), 16) | G60: TSE 27127 | H60: A | I60: =$B$4+90 -> 46055 | J60: 15), 16)
A61: LL/BIS/SNC/BV-19-C | B61: Listening for Packet With Window Widening, BIS | C61: 2022-2 | D61: A | E61: 45873 | F61: 15), 16) | H61: A | I61: =$B$4+90 -> 46055 | J61: 15), 16)
A62: LL/BIS/SNC/BV-20-C | B62: Receiving Framed, Unsegmented Mode Data | C62: 2024-2 | D62: A | E62: 45873 | F62: 15) | H62: A | I62: =$B$4+90 -> 46055 | J62: 15)
A63: LL/BIS/SNC/BV-21-C | B63: Receiving Framed, Unsegmented Mode Data | C63: 2024-2 | D63: A | E63: 45873 | F63: 15) | H63: A | I63: =$B$4+90 -> 46055 | J63: 15)
A64: LL/BIS/SNC/BV-22-C | B64: Broadcast Isochronous Stream Synchronization No Pre-Transmission | C64: 2025-1 | D64: A | E64: 45873 | F64: 15) | H64: A | I64: =$B$4+90 -> 46055 | J64: 15)
A65: LL/BIS/SNC/BV-23-C | B65: BIS change of SDU length during reception, Unframed | C65: 2025-1 | D65: A | E65: 45873 | F65: 15) | H65: A | I65: =$B$4+90 -> 46055 | J65: 15)
A66: LL/BIS/SNC/BV-24-C | B66: BIS change of SDU length during reception, Framed | C66: 2025-1 | D66: A | E66: 45873 | F66: 15) | H66: A | I66: =$B$4+90 -> 46055 | J66: 15)
A67: LL/CIS/CEN/BI-01-C | B67: Error Updating Peer Clock Accuracy | C67: 2022-1 | D67: A | E67: 45873 | F67: 15), 16) | H67: A | I67: =$B$4+90 -> 46055 | J67: 15), 16)
A68: LL/CIS/CEN/BV-01-C | B68: CIS Setup Procedure, Central Initiated – LE 1M PHY | C68: 2025-2 | D68: A | E68: 45873 | F68: 15), 16) | G68: TSE 27127 | H68: A | I68: =$B$4+90 -> 46055 | J68: 15), 16)
A69: LL/CIS/CEN/BV-02-C | B69: CIS Setup Procedure, Central Initiated – LE 2M PHY | C69: 2025-2 | D69: A | E69: 45873 | F69: 15), 16) | G69: TSE 27127 | H69: A | I69: =$B$4+90 -> 46055 | J69: 15), 16)
A70: LL/CIS/CEN/BV-03-C | B70: CIS Setup Procedure, Central Initiated, Rejected | C70: 2021-2 | D70: A | E70: 45873 | F70: 15), 16) | H70: A | I70: =$B$4+90 -> 46055 | J70: 15), 16)
A71: LL/CIS/CEN/BV-04-C | B71: New Channel Map | C71: 2021-1 | D71: A | E71: 45873 | F71: 15), 16) | H71: A | I71: =$B$4+90 -> 46055 | J71: 15), 16)
A72: LL/CIS/CEN/BV-05-C | B72: Sending data in Unidirectional CIS | C72: 2024-2 | D72: A | E72: 45873 | F72: 15), 16) | H72: A | I72: =$B$4+90 -> 46055 | J72: 15), 16)
A73: LL/CIS/CEN/BV-06-C | B73: Receiving data in Unidirectional CIS | C73: 2024-2 | D73: A | E73: 45873 | F73: 15), 16) | H73: A | I73: =$B$4+90 -> 46055 | J73: 15), 16)
A74: LL/CIS/CEN/BV-07-C | B74: Sending and Receiving Data in Bidirectional CIS - Encryption Disabled | C74: 2021-1 | D74: A | E74: 45873 | F74: 15), 16) | H74: A | I74: =$B$4+90 -> 46055 | J74: 15), 16)
A75: LL/CIS/CEN/BV-08-C | B75: Sending and Receiving Data in Multiple CISes, Single CIG, Single Connection, Interleaved CIG, Central | C75: 2021-1 | D75: A | E75: 45873 | F75: 15), 16) | H75: A | I75: =$B$4+90 -> 46055 | J75: 15), 16)
A76: LL/CIS/CEN/BV-09-C | B76: Sending and Receiving Data in Multiple CISes, Single CIG, Single Connection, Sequential, Central | C76: 2021-1 | D76: A | E76: 45873 | F76: 15), 16) | H76: A | I76: =$B$4+90 -> 46055 | J76: 15), 16)
A77: LL/CIS/CEN/BV-10-C | B77: Sending and Receiving Data in Multiple CISes, Single CIG, Multiple Connections, Interleaved CIG | C77: 2021-1 | D77: A | E77: 45873 | F77: 15), 16) | H77: A | I77: =$B$4+90 -> 46055 | J77: 15), 16)
A78: LL/CIS/CEN/BV-11-C | B78: Sending Data in Multiple CISes, Single CIG, Multiple Connections, Sequential | C78: 2025-2 | D78: A | E78: 45873 | F78: 15), 16) | G78: TSE 27127 | H78: A | I78: =$B$4+90 -> 46055 | J78: 15), 16)
A79: LL/CIS/CEN/BV-13-C | B79: Acknowledgement Scheme, Central – Encryption Disabled | C79: 2025-2 | D79: A | E79: 45873 | F79: 15), 16) | G79: TSE 27127 | H79: A | I79: =$B$4+90 -> 46055 | J79: 15), 16)
A80: LL/CIS/CEN/BV-14-C | B80: Retransmissions | C80: 2025-2 | D80: A | E80: 45873 | F80: 15), 16) | G80: TSE 27127 | H80: A | I80: =$B$4+90 -> 46055 | J80: 15), 16)
A81: LL/CIS/CEN/BV-15-C | B81: CIS Terminate Procedure, Initiated | C81: 2025-2 | D81: A | E81: 45873 | F81: 15), 16) | G81: TSE 27127 | H81: A | I81: =$B$4+90 -> 46055 | J81: 15), 16)
A82: LL/CIS/CEN/BV-16-C | B82: CIS Terminate Procedure, Accepting | C82: 2025-2 | D82: A | E82: 45873 | F82: 15), 16) | G82: TSE 27127 | H82: A | I82: =$B$4+90 -> 46055 | J82: 15), 16)
A83: LL/CIS/CEN/BV-17-C | B83: Flushing of Packets in CIS, Central | C83: 2024-1 | D83: A | E83: 45873 | F83: 15), 16) | H83: A | I83: =$B$4+90 -> 46055 | J83: 15), 16)
A84: LL/CIS/CEN/BV-18-C | B84: Bursting of Payloads in CIS, Central | C84: 2025-2 | D84: A | E84: 45873 | F84: 15), 16) | G84: TSE 27127 | H84: A | I84: =$B$4+90 -> 46055 | J84: 15), 16)
A85: LL/CIS/CEN/BV-19-C | B85: Deterministic Packet Transmission in CIS, Central | C85: 2021-1 | D85: A | E85: 45873 | F85: 15), 16) | H85: A | I85: =$B$4+90 -> 46055 | J85: 15), 16)
A86: LL/CIS/CEN/BV-20-C | B86: Set Encryption After CIS Established | C86: 2025-2 | D86: A | E86: 45873 | F86: 15), 16) | G86: TSE 27127 | H86: A | I86: =$B$4+90 -> 46055 | J86: 15), 16)
A87: LL/CIS/CEN/BV-24-C | B87: CIS Updating Peer Clock Accuracy | C87: 2019-2 | D87: A | E87: 45873 | F87: 15), 16) | H87: A | I87: =$B$4+90 -> 46055 | J87: 15), 16)
A88: LL/CIS/CEN/BV-25-C | B88: CIS Setup Procedure, Central Initiated – LE Coded PHY | C88: 2025-2 | D88: A | E88: 45873 | F88: 15), 16) | G88: TSE 27127 | H88: A | I88: =$B$4+90 -> 46055 | J88: 15), 16)
A89: LL/CIS/CEN/BV-26-C | B89: Connected Isochronous Stream Using Non-Test Command, Central Initiated – LE 1M PHY | C89: 2025-1 | D89: A | E89: 45873 | F89: 15), 16) | H89: A | I89: =$B$4+90 -> 46055 | J89: 15), 16)
A90: LL/CIS/CEN/BV-27-C | B90: Connected Isochronous Stream Using Non-Test Command, Central Initiated – LE 2M PHY | C90: 2025-1 | D90: A | E90: 45873 | F90: 15), 16) | H90: A | I90: =$B$4+90 -> 46055 | J90: 15), 16)
A91: LL/CIS/CEN/BV-28-C | B91: Connected Isochronous Stream Using Non-Test Command, Central Initiated – LE Coded PHY | C91: 2025-1 | D91: A | E91: 45873 | F91: 15), 16) | H91: A | I91: =$B$4+90 -> 46055 | J91: 15), 16)
A92: LL/CIS/CEN/BV-29-C | B92: Acknowledgement Scheme, Central – Encryption Enabled | C92: 2025-2 | D92: A | E92: 45873 | F92: 15), 16) | G92: TSE 27127 | H92: A | I92: =$B$4+90 -> 46055 | J92: 15), 16)
A93: LL/CIS/CEN/BV-30-C | B93: Isochronous Channels Host Support Feature Bit | C93: 2021-2 | D93: A | E93: 45873 | F93: 15), 16) | H93: A | I93: =$B$4+90 -> 46055 | J93: 15), 16)
A94: LL/CIS/CEN/BV-31-C | B94: CIS Setup Procedure, Central Initiated – LE 2M PHY|LE 1M PHY | C94: 2025-2 | D94: A | E94: 45873 | F94: 15), 16) | G94: TSE 27127 | H94: A | I94: =$B$4+90 -> 46055 | J94: 15), 16)
A95: LL/CIS/CEN/BV-32-C | B95: CIS Setup Procedure, Central Initiated – LE 1M PHY|LE Coded PHY | C95: 2025-2 | D95: A | E95: 45873 | F95: 15), 16) | G95: TSE 27127 | H95: A | I95: =$B$4+90 -> 46055 | J95: 15), 16)
A96: LL/CIS/CEN/BV-33-C | B96: CIS Considered Lost before Establishment, Central | C96: 2021-1 | D96: A | E96: 45873 | F96: 15), 16) | H96: A | I96: =$B$4+90 -> 46055 | J96: 15), 16)
A97: LL/CIS/CEN/BV-34-C | B97: CIS Connection Loss | C97: 2021-1 | D97: A | E97: 45873 | F97: 15), 16) | H97: A | I97: =$B$4+90 -> 46055 | J97: 15), 16)
A98: LL/CIS/CEN/BV-35-C | B98: Sending and Receiving Data in Bidirectional CIS - Encryption Enabled | C98: 2021-1 | D98: A | E98: 45873 | F98: 15), 16) | H98: A | I98: =$B$4+90 -> 46055 | J98: 15), 16)
A99: LL/CIS/CEN/BV-36-C | B99: CIS Central Setup Procedure, Central Initiated – Central | C99: 2021-1 | D99: A | E99: 45873 | F99: 15), 16) | H99: A | I99: =$B$4+90 -> 46055 | J99: 15), 16)
A100: LL/CIS/CEN/BV-37-C | B100: CIS Central Setup Procedure, LE 2M PHY, Central Initiated – Central | C100: 2021-1 | D100: A | E100: 45873 | F100: 15), 16) | H100: A | I100: =$B$4+90 -> 46055 | J100: 15), 16)
A101: LL/CIS/CEN/BV-38-C | B101: CIS Central Setup Procedure, LE Coded PHY, Central Initiated – Central | C101: 2021-1 | D101: A | E101: 45873 | F101: 15), 16) | H101: A | I101: =$B$4+90 -> 46055 | J101: 15), 16)
...

Sheet LMP
A1: Test Case Reference List
A2: =Top!C7 -> Link Manager Protocol Conformance | D2: Previous TS | E2: =Top!E8 -> LMP.TS.p48 | H2: TS | I2: =Top!G8 -> LMP.TS.p49 | J2: Available Date | K2: =rel_date -> 45965
A3: =Top!$D$7 -> Vol 2 Part C, 4.2–6.2 | D3: Previous ICS | E3: =Top!F7 -> LMP.ICS.p40 | H3: ICS | I3: =Top!H7 -> LMP.ICS.p41 | J3: Available Date | K3: =rel_date -> 45965
A4: Release date | B4: =rel_date -> 45965 | D4: Previous ICS | E4: =Top!F8 -> SEC.ICS.p0 | H4: ICS | I4: =Top!H8 -> SEC.ICS.p0 | J4: Available Date | K4: 45474
A5: go to top | D5: Previously published test requirements | H5: Updated requirements through this release
A6: TCID*** | B6: Description | C6: TCRL Package Version Last Updated | D6: TC Category | E6: Active Date | F6: Test System Alternatives | G6: Notes | H6: TC Category | I6: Active Date | J6: Test System Alternatives | K6: Notes
A7: TCMT | B7: Test Case Mapping Table | C7: pkg101 | E7: 45873 | G7: TSEs 26257, 27419 | I7: =$B$4+90 -> 46055 | K7: TSEs 27094, 27117, 27257, 28050
A8: LMP ICS | B8: Implementation Conformance Statement | C8: pkg101 | E8: 45873 | G8: TSEs 26785, 26826 | I8: =$B$4+90 -> 46055 | K8: TSEs 23117, 23981, 27060, 27222
A9: SEC ICS | B9: Implementation Conformance Statement | C9: 2024-1 | E9: 45564 | I9: 45564
A10: LMP/AFH/BV-01-C | B10: AFH Enable – Peripheral | D10: A | E10: 45873 | F10: 15) | H10: A | I10: =$B$4+90 -> 46055 | J10: 15)
A11: LMP/AFH/BV-02-C | B11: AFH Disable – Peripheral | D11: A | E11: 45873 | F11: 15) | H11: A | I11: =$B$4+90 -> 46055 | J11: 15)
A12: LMP/AFH/BV-03-C | B12: AFH Switch – Peripheral | D12: A | E12: 45873 | F12: 15) | H12: A | I12: =$B$4+90 -> 46055 | J12: 15)
A13: LMP/AFH/BV-04-C | B13: Classification Reporting – Normal Operation | D13: A | E13: 45873 | F13: 15) | H13: A | I13: =$B$4+90 -> 46055 | J13: 15)
A14: LMP/AFH/BV-05-C | B14: Classification Reporting – After Successful Role Switch | C14: 2018-2 | D14: A | E14: 45873 | F14: 15) | H14: A | I14: =$B$4+90 -> 46055 | J14: 15)
A15: LMP/AFH/BV-06-C | B15: Classification Reporting – After Unsuccessful Role Switch | C15: 2018-2 | D15: A | E15: 45873 | F15: 15) | H15: A | I15: =$B$4+90 -> 46055 | J15: 15)
A16: LMP/AFH/BV-07-C | B16: No longer used | C16: 2019-1
A17: LMP/AFH/BV-08-C | B17: Classification Reporting – After Unhold | C17: 2018-2 | D17: A | E17: 45873 | F17: 15) | H17: A | I17: =$B$4+90 -> 46055 | J17: 15)
A18: LMP/AFH/BV-09-C | B18: Peripheral device does not send an LMP_SET_AFH PDU – after successful role switch | D18: A | E18: 45873 | F18: 15) | H18: A | I18: =$B$4+90 -> 46055 | J18: 15)
A19: LMP/AUT/BI-01-C | B19: Error Return When a Unit Key is Requested | C19: 2018-2 | D19: A | E19: 45873 | F19: 15) | H19: A | I19: =$B$4+90 -> 46055 | J19: 15)
A20: LMP/AUT/BI-02-C | B20: Mistimed role switch during Secure Authentication, Responder (IUT) has link key, Initiator (Lower Tester) is Central | C20: 2021-1 | D20: A | E20: 45873 | F20: 15) | H20: A | I20: =$B$4+90 -> 46055 | J20: 15)
A21: LMP/AUT/BI-03-C | B21: Mistimed role switch during Secure Authentication, Responder (Lower Tester) has link key, Initiator (IUT) is Peripheral | C21: 2021-1 | D21: A | E21: 45873 | F21: 15) | H21: A | I21: =$B$4+90 -> 46055 | J21: 15)
A22: LMP/AUT/BI-04-C | B22: Reject Role Switch, Pairing, Responder | C22: 2021-1 | D22: A | E22: 45873 | F22: 15) | H22: A | I22: =$B$4+90 -> 46055 | J22: 15)
A23: LMP/AUT/BI-05-C | B23: No longer used | C23: 2021-2
A24: LMP/AUT/BI-06-C | B24: Secure Authentication, Responder (IUT) has link Key, Initiator (Lower Tester) is Central, Reject Role Switch | C24: 2021-1 | D24: A | E24: 45873 | F24: 15) | H24: A | I24: =$B$4+90 -> 46055 | J24: 15)
A25: LMP/AUT/BI-07-C | B25: Secure Authentication, Responder (IUT) has link Key, Initiator (Lower Tester) is Peripheral, Reject Role Switch | C25: 2021-1 | D25: A | E25: 45873 | F25: 15) | H25: A | I25: =$B$4+90 -> 46055 | J25: 15)
A26: LMP/AUT/BI-08-C | B26: Pairing, IUT Initiator, Invalid Combination Key | C26: 2024-2 | D26: A | E26: 45873 | F26: 15) | H26: A | I26: =$B$4+90 -> 46055 | J26: 15)
A27: LMP/AUT/BV-01-C | B27: Authentication Reject, No Link Key | D27: A | E27: 45873 | F27: 15) | H27: A | I27: =$B$4+90 -> 46055 | J27: 15)
A28: LMP/AUT/BV-03-C | B28: Create Link Key | C28: 2018-2 | D28: A | E28: 45873 | F28: 15) | H28: A | I28: =$B$4+90 -> 46055 | J28: 15)
A29: LMP/AUT/BV-04-C | B29: Pairing, IUT Initiator | C29: 2018-2 | D29: A | E29: 45873 | F29: 15) | H29: A | I29: =$B$4+90 -> 46055 | J29: 15)
A30: LMP/AUT/BV-05-C | B30: IUT Responder, Fixed PIN | C30: 2018-2 | D30: A | E30: 45873 | F30: 15) | H30: A | I30: =$B$4+90 -> 46055 | J30: 15)
A31: LMP/AUT/BV-06-C | B31: IUT Initiator; Responder has Fixed PIN | C31: 2018-2 | D31: A | E31: 45873 | F31: 15) | H31: A | I31: =$B$4+90 -> 46055 | J31: 15)
A32: LMP/AUT/BV-12-C | B32: Change Link Key, IUT Responder | D32: A | E32: 45873 | F32: 15) | H32: A | I32: =$B$4+90 -> 46055 | J32: 15)
A33: LMP/AUT/BV-13-C | B33: Change Link Key, IUT Initiator | D33: A | E33: 45873 | F33: 15) | H33: A | I33: =$B$4+90 -> 46055 | J33: 15)
A34: LMP/AUT/BV-14-C | B34: Secure Authentication, Responder (IUT) has link key, Initiator (Lower Tester) is Central | C34: 2018-1 | D34: A | E34: 45873 | F34: 15) | H34: A | I34: =$B$4+90 -> 46055 | J34: 15)
A35: LMP/AUT/BV-15-C | B35: Secure Authentication, Responder (IUT) has link Key, Initiator (Lower Tester) is Peripheral | C35: 2018-1 | D35: A | E35: 45873 | F35: 15) | H35: A | I35: =$B$4+90 -> 46055 | J35: 15)
A36: LMP/AUT/BV-16-C | B36: Secure Authentication, Responder (Lower Tester) has link Key, Initiator (IUT) is Central | C36: 2018-1 | D36: A | E36: 45873 | F36: 15) | H36: A | I36: =$B$4+90 -> 46055 | J36: 15)
A37: LMP/AUT/BV-17-C | B37: Secure Authentication, Responder (Lower Tester) has Link Key, Initiator (IUT) is Peripheral | C37: 2018-1 | D37: A | E37: 45873 | F37: 15) | H37: A | I37: =$B$4+90 -> 46055 | J37: 15)
A38: LMP/AUT/BV-18-C | B38: Role switch during Secure Authentication before Authentication Response, Responder (IUT) has link key, Initiator (Lower Tester) is Central | C38: 2021-1 | D38: A | E38: 45873 | F38: 15) | H38: A | I38: =$B$4+90 -> 46055 | J38: 15)
A39: LMP/AUT/BV-19-C | B39: Role switch during Secure Authentication before Authentication Response, Responder (IUT) has link key, Initiator (Lower Tester) is Peripheral | C39: 2021-1 | D39: A | E39: 45873 | F39: 15) | H39: A | I39: =$B$4+90 -> 46055 | J39: 15)
A40: LMP/AUT/BV-20-C | B40: Role switch during Secure Authentication before Authentication Response, Responder (Lower Tester) has link key, Initiator (IUT) is Central | C40: 2021-1 | D40: A | E40: 45873 | F40: 15) | H40: A | I40: =$B$4+90 -> 46055 | J40: 15)
A41: LMP/AUT/BV-21-C | B41: Role switch during Secure Authentication before Authentication Response, Responder (Lower Tester) has link key, Initiator (IUT) is Peripheral | C41: 2021-1 | D41: A | E41: 45873 | F41: 15) | H41: A | I41: =$B$4+90 -> 46055 | J41: 15)
A42: LMP/AUT/BV-22-C | B42: Role switch during Secure Authentication before Random Number, Responder (Lower Tester) has link key, Initiator (IUT) is Central | C42: 2021-1 | D42: A | E42: 45873 | F42: 15) | H42: A | I42: =$B$4+90 -> 46055 | J42: 15)
A43: LMP/AUT/BV-23-C | B43: Role switch during Secure Authentication before Random Number, Responder (Lower Tester) has link key, Initiator (IUT) is Peripheral | C43: 2021-1 | D43: A | E43: 45873 | F43: 15) | H43: A | I43: =$B$4+90 -> 46055 | J43: 15)
A44: LMP/AUT/BV-24-C | B44: Create Link Key – Rejects Bad Authentication Response | C44: 2021-1 | D44: A | E44: 45873 | F44: 15) | H44: A | I44: =$B$4+90 -> 46055 | J44: 15)
A45: LMP/AUT/BV-25-C | B45: Pairing, IUT Initiator – Rejects Bad Authentication Response, Detach Optional | C45: 2025-2 | D45: A | E45: 45873 | F45: 15) | G45: TSE 26257 | H45: A | I45: =$B$4+90 -> 46055 | J45: 15)
A46: LMP/AUT/BV-26-C | B46: IUT Responder, Fixed PIN – Rejects Bad Authentication Response | C46: 2021-1 | D46: A | E46: 45873 | F46: 15) | H46: A | I46: =$B$4+90 -> 46055 | J46: 15)
A47: LMP/AUT/BV-27-C | B47: IUT Initiator; Responder has Fixed PIN – Rejects Bad Authentication Response, Detach Optional | C47: 2025-2 | D47: A | E47: 45873 | F47: 15) | G47: TSE 26257 | H47: A | I47: =$B$4+90 -> 46055 | J47: 15)
A48: LMP/AUT/BV-28-C | B48: Change Link Key, IUT Responder – Rejects Bad Authentication Response | C48: 2021-1 | D48: A | E48: 45873 | F48: 15) | H48: A | I48: =$B$4+90 -> 46055 | J48: 15)
A49: LMP/AUT/BV-29-C | B49: Change Link Key, IUT Initiator – Rejects Bad Authentication Response, Detach Optional | C49: 2025-2 | D49: A | E49: 45873 | F49: 15) | G49: TSE 26257 | H49: A | I49: =$B$4+90 -> 46055 | J49: 15)
A50: LMP/AUT/BV-30-C | B50: Secure Authentication, Responder (IUT) has Link Key, Initiator (Lower Tester) is Central – Rejects Bad Authentication Response, Detach Optional | C50: 2025-2 | D50: A | E50: 45873 | F50: 15) | G50: TSE 26257 | H50: A | I50: =$B$4+90 -> 46055 | J50: 15)
A51: LMP/AUT/BV-31-C | B51: Secure Authentication, Responder (IUT) has Link Key, Initiator (Lower Tester) is Peripheral – Rejects Bad Authentication Response, Detach Optional | C51: 2025-2 | D51: A | E51: 45873 | F51: 15) | G51: TSE 26257 | H51: A | I51: =$B$4+90 -> 46055 | J51: 15)
A52: LMP/AUT/BV-32-C | B52: Secure Authentication, Responder (Lower Tester) has Link Key, Initiator (IUT) is Central – Rejects Bad Authentication Response, Detach Optional | C52: 2025-2 | D52: A | E52: 45873 | F52: 15) | G52: TSE 26257 | H52: A | I52: =$B$4+90 -> 46055 | J52: 15)
